Workbook
Name AKTIVALAINNYA: CONTROL!$G$9
Name AKTIVALANCARLAINNYA: CONTROL!$G$6
Name AKTIVATETAP: CONTROL!$G$7
Name AKUNPIUTANG: CONTROL!$G$4
Name AKUNUTANG: CONTROL!$G$10
Name BEBAN: CONTROL!$G$21
Name BEBANLAINNYA: CONTROL!$G$22
Name COA_DEBET: COA!$E$5:$E$59
Name COA_KREDIT: COA!$F$5:$F$59
Name DEPRESIASIDANAMORTISASI: CONTROL!$G$8
Name EKUITAS: CONTROL!$G$17
Name JU_BB: JURNAL!$J$7:$J$226
Name JU_Debet: JURNAL!$G$7:$G$228
Name JU_Keterangan: JURNAL!$D$7:$D$228
Name JU_Kodeakun: JURNAL!$E$7:$E$228
Name JU_Kredit: JURNAL!$H$7:$H$228
Name JU_Namaakun: JURNAL!$F$7:$F$228
Name JU_REF: JURNAL!$C$7:$C$242
Name JU_Tanggal: JURNAL!$B$7:$B$244
Name KASDANBANK: CONTROL!$G$3
Name KEWAJIBANJANGKAPANJANG: CONTROL!$G$12
Name KEWAJIBANLANCARLAINNYA: CONTROL!$G$11
Name KODEAKUN: COA!$B$5:$B$86
Name LRSLDO: LR!$K$6:$K$45
Name LRTYPE: LR!$J$6:$J$94
Name Nama_Akun: CONTROL!$B$3:$B$84
Name NRC_TYPE: NRC!$I$8:$I$24
Name NRCL: NRL!$F:$F
Name NRCLDB: NRL!$M:$M
Name NRCLDB2: NRL!$O:$O
Name NRCLKODE: NRL!$B:$B
Name NRCLKR: NRL!$N:$N
Name NRCLKR2: NRL!$P:$P
Name NRCLSN: NRL!$F:$F
Name NRCSALDO: NRC!$J$8:$J$24
Name PEMBELIAN: CONTROL!$G$20
Name PENDAPATAN: CONTROL!$G$18
Name PENDAPATANLAINNYA: CONTROL!$G$19
Name PERSEDIAAN: CONTROL!$G$5
Name Posisi: CONTROL!$D$3:$D$84
Name SaldoNormal: CONTROL!$C$3:$C$84
Name Type: CONTROL!$B$3:$B$84

Sheet MENU
C17: Pencatatan dan Pelaporan Akuntansi Keuangan

Sheet COA
B2: DAFTAR AKUN
B4: Kode Akun | C4: Nama Akun | D4: Type | E4: Debet | F4: Kredit | H4: SN | I4: POS
B5: 1101 | C5: Kas | D5: Kas | H5: =VLOOKUP(D5,CONTROL!$B$3:$D$84,2,TRUE) -> Debet | I5: =VLOOKUP(D5,CONTROL!B3:D84,3,FALSE) -> Neraca
B6: 1102 | C6: Kas Di Bank | D6: Kas Di Bank | H6: =VLOOKUP(D6,CONTROL!$B$3:$D$84,2,TRUE) -> Debet | I6: =VLOOKUP(D6,CONTROL!B4:D85,3,FALSE) -> Neraca
B7: 1103 | C7: Petty Cash | D7: Petty Cash | H7: =VLOOKUP(D7,CONTROL!$B$3:$D$84,2,TRUE) -> Debet | I7: =VLOOKUP(D7,CONTROL!B5:D86,3,FALSE) -> Neraca
B8: 1104 | C8: Piutang | D8: Piutang | H8: =VLOOKUP(D8,CONTROL!$B$3:$D$84,2,TRUE) -> Debet | I8: =VLOOKUP(D8,CONTROL!B6:D87,3,FALSE) -> Neraca
B9: 1105 | C9: Persediaan | D9: Persediaan | H9: =VLOOKUP(D9,CONTROL!$B$3:$D$84,2,TRUE) -> Debet | I9: =VLOOKUP(D9,CONTROL!B7:D87,3,FALSE) -> Neraca
B10: 1106 | C10: Perlengkapan | D10: Perlengkapan | H10: =VLOOKUP(D10,CONTROL!$B$3:$D$84,2,TRUE) -> Debet | I10: =VLOOKUP(D10,CONTROL!B8:D88,3,FALSE) -> Neraca
B11: 1201 | C11: Peralatan | D11: Peralatan | H11: =VLOOKUP(D11,CONTROL!$B$3:$D$84,2,TRUE) -> Debet | I11: =VLOOKUP(D11,CONTROL!B9:D89,3,FALSE) -> Neraca
B12: 1202 | C12: Akumulasi Penyusutan Peralatan | D12: Akumulasi Penyusutan Peralatan | H12: =VLOOKUP(COA!D12,CONTROL!B3:D84,2,FALSE) -> Kredit | I12: =VLOOKUP(D12,CONTROL!B10:D90,3,FALSE) -> Neraca
B13: 2110 | C13: Utang | D13: Utang | H13: =VLOOKUP(COA!D13,CONTROL!B4:D85,2,FALSE) -> Kredit | I13: =VLOOKUP(D13,CONTROL!B11:D91,3,FALSE) -> Neraca
B14: 2120 | C14: Utang Gaji | D14: Utang Gaji | H14: =VLOOKUP(COA!D14,CONTROL!B5:D86,2,FALSE) -> Kredit | I14: =VLOOKUP(D14,CONTROL!B12:D92,3,FALSE) -> Neraca
B15: 2130 | C15: utang pajak | D15: utang pajak | H15: =VLOOKUP(COA!D15,CONTROL!B6:D87,2,FALSE) -> Kredit | I15: =VLOOKUP(D15,CONTROL!B13:D93,3,FALSE) -> Neraca
B16: 2140 | C16: utang pdam | D16: utang pdam | H16: =VLOOKUP(COA!D16,CONTROL!B7:D88,2,FALSE) -> Kredit | I16: =VLOOKUP(D16,CONTROL!B14:D94,3,FALSE) -> Neraca
B17: 2150 | C17: utang jne | D17: utang jne | H17: =VLOOKUP(COA!D17,CONTROL!B8:D89,2,FALSE) -> Kredit | I17: =VLOOKUP(D17,CONTROL!B15:D95,3,FALSE) -> Neraca
B18: 2160 | C18: utang pcp | D18: utang pcp | H18: =VLOOKUP(COA!D18,CONTROL!B9:D90,2,FALSE) -> Kredit | I18: =VLOOKUP(D18,CONTROL!B16:D96,3,FALSE) -> Neraca
B19: 3100 | C19: Modal | D19: Modal | H19: =VLOOKUP(COA!D19,CONTROL!B10:D91,2,FALSE) -> Kredit | I19: =VLOOKUP(D19,CONTROL!B17:D97,3,FALSE) -> Neraca
B20: 3110 | C20: Iktisar laba rugi | D20: Iktisar laba rugi | H20: =VLOOKUP(COA!D20,CONTROL!B11:D92,2,FALSE) -> Kredit | I20: =VLOOKUP(D20,CONTROL!B18:D98,3,FALSE) -> Neraca
B21: 4110 | C21: Pendapatan jasa | D21: Pendapatan jasa | H21: =VLOOKUP(COA!D21,CONTROL!B12:D93,2,FALSE) -> Kredit | I21: =VLOOKUP(D21,CONTROL!B19:D99,3,FALSE) -> Laba Rugi
B22: 4120 | C22: pendapatan shoepolice | D22: pendapatan shoepolice | H22: =VLOOKUP(COA!D22,CONTROL!B13:D94,2,FALSE) -> Kredit | I22: =VLOOKUP(D22,CONTROL!B20:D100,3,FALSE) -> Laba Rugi
B23: 4130 | C23: pendapatan affiliate | D23: pendapatan affiliate | H23: =VLOOKUP(COA!D23,CONTROL!B14:D95,2,FALSE) -> Kredit | I23: =VLOOKUP(D23,CONTROL!B21:D101,3,FALSE) -> Laba Rugi
... B85: 8010 | C85: Pajak | D85: Pajak | H85: =VLOOKUP(COA!D85,CONTROL!B76:D157,2,FALSE) -> Debet | I85: =VLOOKUP(D85,CONTROL!B83:D163,3,FALSE) -> Laba Rugi

Sheet CONTROL
F1: Arus kas
B2: TYPE Akun | C2: Saldo Normal | D2: Posisi | F2: Type
B3: Kas | C3: Debet | D3: Neraca | F3: KAS DAN BANK | G3: =SUMIF(NRC_TYPE,F3,NRCSALDO) -> 0
B4: Kas Di Bank | C4: Debet | D4: Neraca | F4: AKUN PIUTANG | G4: =SUMIF(NRC_TYPE,F4,NRCSALDO) -> 0
B5: Petty Cash | C5: Debet | D5: Neraca | F5: PERSEDIAAN | G5: =SUMIF(NRC_TYPE,F5,NRCSALDO) -> 0
B6: Piutang | C6: Debet | D6: Neraca | F6: AKTIVA LANCAR LAINNYA | G6: =SUMIF(NRC_TYPE,F6,NRCSALDO) -> 0
B7: Persediaan | C7: Debet | D7: Neraca | F7: AKTIVA TETAP | G7: =SUMIF(NRC_TYPE,F7,NRCSALDO) -> -515685
B8: Perlengkapan | C8: Debet | D8: Neraca | F8: DEPRESIASI DAN AMORTISASI | G8: =-SUMIF(NRC_TYPE,F8,NRCSALDO) -> 0
B9: Peralatan | C9: Debet | D9: Neraca | F9: AKTIVA LAINNYA | G9: =SUMIF(NRC_TYPE,F9,NRCSALDO) -> 0
B10: Akumulasi Penyusutan Peralatan | C10: Kredit | D10: Neraca | F10: AKUN UTANG | G10: =SUMIF(NRC_TYPE,F10,NRCSALDO) -> 0
B11: Utang | C11: Kredit | D11: Neraca | F11: KEWAJIBAN LANCAR LAINNYA | G11: =SUMIF(NRC_TYPE,F11,NRCSALDO) -> 0
B12: Utang Gaji | C12: Kredit | D12: Neraca | F12: KEWAJIBAN JANGKA PANJANG | G12: =SUMIF(NRC_TYPE,F12,NRCSALDO) -> 0
B13: utang pajak | C13: Kredit | D13: Neraca
B14: utang pdam | C14: Kredit | D14: Neraca
B15: utang jne | C15: Kredit | D15: Neraca
B16: utang pcp | C16: Kredit | D16: Neraca
B17: Modal | C17: Kredit | D17: Neraca | F17: EKUITAS | G17: =SUMIF(NRC_TYPE,F17,NRCSALDO) -> #N/A
B18: Iktisar laba rugi | C18: Kredit | D18: Neraca | F18: PENDAPATAN | G18: =SUMIF(LRTYPE,F18,LRSLDO) -> #REF!
B19: Pendapatan jasa | C19: Kredit | D19: Laba Rugi | F19: PENDAPATAN LAINNYA | G19: =SUMIF(LRTYPE,F19,LRSLDO) -> 0
B20: pendapatan shoepolice | C20: Kredit | D20: Laba Rugi | F20: Pembelian | G20: =-SUMIF(LRTYPE,F20,LRSLDO) -> #REF!
B21: pendapatan affiliate | C21: Kredit | D21: Laba Rugi | F21: BEBAN | G21: =-SUMIF(LRTYPE,F21,LRSLDO) -> #REF!
B22: pendapatan jasa eiger | C22: Kredit | D22: Laba Rugi | F22: BEBAN LAINNYA | G22: =-SUMIF(LRTYPE,F22,LRSLDO) -> #REF!
B23: pendapatan lain-lain | C23: Kredit | D23: Laba Rugi
B24: pendapatan ongkir | C24: Kredit | D24: Laba Rugi
B25: Retur & Refund | C25: Debet | D25: Laba Rugi
B26: Hpp sole | C26: Debet | D26: Laba Rugi
B27: Hpp upper | C27: Debet | D27: Laba Rugi
B28: Hpp reguler | C28: Debet | D28: Laba Rugi
B29: Hpp Vibram | C29: Debet | D29: Laba Rugi
B30: Hpp repaint | C30: Debet | D30: Laba Rugi
B31: Hpp general | C31: Debet | D31: Laba Rugi
B32: Hpp Aksesoris | C32: Debet | D32: Laba Rugi
B33: Beban Gaji shoepolice | C33: Debet | D33: Laba Rugi
B34: Beban Gaji Workshop | C34: Debet | D34: Laba Rugi
... B83: Pajak | C83: Debet | D83: Laba Rugi

Sheet JURNAL
B2: FORM Jurnal
F4: =IF(G4=H4,"BALANCE","CEK KEMBALI") -> CEK KEMBALI | G4: =SUM(G7:G180) -> 129849716 | H4: =SUM(H7:H180) -> 207577079
B6: Tanggal | C6: Ref | D6: Keterangan | E6: Kode Akun | F6: Nama Akun | G6: Debet | H6: Kredit | J6: KB BB
B7: 01 juni 2026 | D7: Pendapatan jasa | E7: 4110 | F7: {=IFERROR(INDEX(COA!$C$5:$C$59,MATCH(JURNAL!E7,COA!$B$5:$B$59,0)),"")} -> Pendapatan jasa | G7: 6912662 | J7: =IF(E7="","",COUNTIF($E$7:E7,E7)&E7) -> 14110
B8: 01 juni 2026 | D8: Pengembalian kelebihan perjalanan dinas | F8: {=IFERROR(INDEX(COA!$C$5:$C$59,MATCH(JURNAL!E8,COA!$B$5:$B$59,0)),"")} | G8: 392280 | J8: =IF(E8="","",COUNTIF($E$7:E8,E8)&E8)
B9: 01 juni 2026 | D9: kopi, gula, teh ws | E9: 6080 | F9: {=IFERROR(INDEX(COA!$C$5:$C$59,MATCH(JURNAL!E9,COA!$B$5:$B$59,0)),"")} | H9: 76500 | J9: =IF(E9="","",COUNTIF($E$7:E9,E9)&E9) -> 16080
B10: 01 juni 2026 | D10: MITRA | E10: 5010 | F10: {=IFERROR(INDEX(COA!$C$5:$C$59,MATCH(JURNAL!E10,COA!$B$5:$B$59,0)),"")} -> Hpp sole | H10: 133500 | J10: =IF(E10="","",COUNTIF($E$7:E10,E10)&E10) -> 15010
B11: 01 juni 2026 | D11: MEGA | E11: 5010 | F11: {=IFERROR(INDEX(COA!$C$5:$C$59,MATCH(JURNAL!E11,COA!$B$5:$B$59,0)),"")} -> Hpp sole | H11: 316500 | J11: =IF(E11="","",COUNTIF($E$7:E11,E11)&E11) -> 25010
B12: 01 juni 2026 | D12: SUMBER | E12: 5010 | F12: {=IFERROR(INDEX(COA!$C$5:$C$59,MATCH(JURNAL!E12,COA!$B$5:$B$59,0)),"")} -> Hpp sole | H12: 424000 | J12: =IF(E12="","",COUNTIF($E$7:E12,E12)&E12) -> 35010
B13: 01 juni 2026 | D13: OUTLET KITA | E13: 5010 | F13: {=IFERROR(INDEX(COA!$C$5:$C$59,MATCH(JURNAL!E13,COA!$B$5:$B$59,0)),"")} -> Hpp sole | H13: 649799 | J13: =IF(E13="","",COUNTIF($E$7:E13,E13)&E13) -> 45010
B14: 01 juni 2026 | D14: SOLE BOLA | E14: 5010 | F14: {=IFERROR(INDEX(COA!$C$5:$C$59,MATCH(JURNAL!E14,COA!$B$5:$B$59,0)),"")} -> Hpp sole | H14: 18970 | J14: =IF(E14="","",COUNTIF($E$7:E14,E14)&E14) -> 55010
B15: 01 juni 2026 | D15: BANTAL TUMIT | E15: 5010 | F15: {=IFERROR(INDEX(COA!$C$5:$C$59,MATCH(JURNAL!E15,COA!$B$5:$B$59,0)),"")} -> Hpp sole | H15: 5968 | J15: =IF(E15="","",COUNTIF($E$7:E15,E15)&E15) -> 65010
B16: 01 juni 2026 | D16: SOLE BADMINTON | E16: 5010 | F16: {=IFERROR(INDEX(COA!$C$5:$C$59,MATCH(JURNAL!E16,COA!$B$5:$B$59,0)),"")} -> Hpp sole | H16: 43620 | J16: =IF(E16="","",COUNTIF($E$7:E16,E16)&E16) -> 75010
B17: 01 juni 2026 | D17: HEEL PATCH CONVERS | E17: 5010 | F17: {=IFERROR(INDEX(COA!$C$5:$C$59,MATCH(JURNAL!E17,COA!$B$5:$B$59,0)),"")} -> Hpp sole | H17: 17648 | J17: =IF(E17="","",COUNTIF($E$7:E17,E17)&E17) -> 85010
B18: 01 juni 2026 | D18: BIAYA KIRIMAN KULIT | E18: 5310 | F18: {=IFERROR(INDEX(COA!$C$5:$C$59,MATCH(JURNAL!E18,COA!$B$5:$B$59,0)),"")} -> Biaya ekspedisi & ongkir | H18: 58975 | J18: =IF(E18="","",COUNTIF($E$7:E18,E18)&E18) -> 15310
B19: 01 juni 2026 | D19: vibram | E19: 5040 | F19: {=IFERROR(INDEX(COA!$C$5:$C$59,MATCH(JURNAL!E19,COA!$B$5:$B$59,0)),"")} -> Hpp Vibram | H19: 497000 | J19: =IF(E19="","",COUNTIF($E$7:E19,E19)&E19) -> 15040
B20: 01 juni 2026 | D20: BENSIN KIMKO | E20: 6000 | F20: {=IFERROR(INDEX(COA!$C$5:$C$59,MATCH(JURNAL!E20,COA!$B$5:$B$59,0)),"")} | H20: 20000 | J20: =IF(E20="","",COUNTIF($E$7:E20,E20)&E20) -> 16000
... B25: 01 juni 2026 | D25: gaji bulanan mei | E25: 2120 | F25: {=IFERROR(INDEX(COA!$C$5:$C$59,MATCH(JURNAL!E25,COA!$B$5:$B$59,0)),"")} -> Utang Gaji | H25: 94000000 | J25: =IF(E25="","",COUNTIF($E$7:E25,E25)&E25) -> 12120
B26: 01 juni 2026 | D26: prive | F26: {=IFERROR(INDEX(COA!$C$5:$C$59,MATCH(JURNAL!E26,COA!$B$5:$B$59,0)),"")} | H26: 100000 | J26: =IF(E26="","",COUNTIF($E$7:E26,E26)&E26)
B27: 01 juni 2026 | D27: selisih ayat silang | F27: {=IFERROR(INDEX(COA!$C$5:$C$59,MATCH(JURNAL!E27,COA!$B$5:$B$59,0)),"")} | H27: 325 | J27: =IF(E27="","",COUNTIF($E$7:E27,E27)&E27)
B28: 2 juni 2026 | D28: pendapatan jasa | E28: 4110 | F28: {=IFERROR(INDEX(COA!$C$5:$C$59,MATCH(JURNAL!E28,COA!$B$5:$B$59,0)),"")} -> Pendapatan jasa | G28: 8122933 | J28: =IF(E28="","",COUNTIF($E$7:E28,E28)&E28) -> 24110
B29: 2 juni 2026 | D29: iuran office/sortir | E29: 6020 | F29: {=IFERROR(INDEX(COA!$C$5:$C$59,MATCH(JURNAL!E29,COA!$B$5:$B$59,0)),"")} | H29: 250000 | J29: =IF(E29="","",COUNTIF($E$7:E29,E29)&E29) -> 16020
B30: 2 juni 2026 | D30: ongkir cust pick up tunggu pengembalian | E30: 5310 | F30: {=IFERROR(INDEX(COA!$C$5:$C$59,MATCH(JURNAL!E30,COA!$B$5:$B$59,0)),"")} -> Biaya ekspedisi & ongkir | H30: 80360 | J30: =IF(E30="","",COUNTIF($E$7:E30,E30)&E30) -> 25310
B31: 2 juni 2026 | D31: meeting | E31: 5200 | F31: {=IFERROR(INDEX(COA!$C$5:$C$59,MATCH(JURNAL!E31,COA!$B$5:$B$59,0)),"")} -> Konsumsi lembur & Meeting | H31: 95000 | J31: =IF(E31="","",COUNTIF($E$7:E31,E31)&E31) -> 15200
B32: 2 juni 2026 | D32: ongkir an fauzi | E32: 5310 | F32: {=IFERROR(INDEX(COA!$C$5:$C$59,MATCH(JURNAL!E32,COA!$B$5:$B$59,0)),"")} -> Biaya ekspedisi & ongkir | H32: 73000 | J32: =IF(E32="","",COUNTIF($E$7:E32,E32)&E32) -> 35310
B33: 2 juni 2026 | D33: atk | E33: 6030 | F33: {=IFERROR(INDEX(COA!$C$5:$C$59,MATCH(JURNAL!E33,COA!$B$5:$B$59,0)),"")} | H33: 187000 | J33: =IF(E33="","",COUNTIF($E$7:E33,E33)&E33) -> 16030
B34: 2 juni 2026 | D34: pajak sisa bayar th 2022 & 2024 | E34: 8010 | F34: {=IFERROR(INDEX(COA!$C$5:$C$59,MATCH(JURNAL!E34,COA!$B$5:$B$59,0)),"")} | H34: 507960 | J34: =IF(E34="","",COUNTIF($E$7:E34,E34)&E34) -> 18010
B35: 2 juni 2026 | D35: MITRA | E35: 5010 | F35: {=IFERROR(INDEX(COA!$C$5:$C$59,MATCH(JURNAL!E35,COA!$B$5:$B$59,0)),"")} -> Hpp sole | H35: 20500 | J35: =IF(E35="","",COUNTIF($E$7:E35,E35)&E35) -> 105010
B36: 2 juni 2026 | D36: SUMBER | E36: 5010 | F36: {=IFERROR(INDEX(COA!$C$5:$C$59,MATCH(JURNAL!E36,COA!$B$5:$B$59,0)),"")} -> Hpp sole | H36: 56000 | J36: =IF(E36="","",COUNTIF($E$7:E36,E36)&E36) -> 115010
B37: 2 juni 2026 | D37: MEGA | E37: 5010 | F37: {=IFERROR(INDEX(COA!$C$5:$C$59,MATCH(JURNAL!E37,COA!$B$5:$B$59,0)),"")} -> Hpp sole | H37: 81000 | J37: =IF(E37="","",COUNTIF($E$7:E37,E37)&E37) -> 125010
B38: 2 juni 2026 | D38: AFUNG | E38: 5030 | F38: {=IFERROR(INDEX(COA!$C$5:$C$59,MATCH(JURNAL!E38,COA!$B$5:$B$59,0)),"")} -> Hpp reguler | H38: 930000 | J38: =IF(E38="","",COUNTIF($E$7:E38,E38)&E38) -> 15030
B39: 2 juni 2026 | D39: BEN | E39: 5030 | F39: {=IFERROR(INDEX(COA!$C$5:$C$59,MATCH(JURNAL!E39,COA!$B$5:$B$59,0)),"")} -> Hpp reguler | H39: 524000 | J39: =IF(E39="","",COUNTIF($E$7:E39,E39)&E39) -> 25030
B40: 2 juni 2026 | D40: JUMBO | E40: 5030 | F40: {=IFERROR(INDEX(COA!$C$5:$C$59,MATCH(JURNAL!E40,COA!$B$5:$B$59,0)),"")} -> Hpp reguler | H40: 61000 | J40: =IF(E40="","",COUNTIF($E$7:E40,E40)&E40) -> 35030
... B45: 2 juni 2026 | D45: sewa sorrtir | E45: 5630 | F45: {=IFERROR(INDEX(COA!$C$5:$C$59,MATCH(JURNAL!E45,COA!$B$5:$B$59,0)),"")} | H45: 2750000 | J45: =IF(E45="","",COUNTIF($E$7:E45,E45)&E45) -> 15630
B46: 3 juni 2026 | D46: pendapatan jasa | E46: 4110 | F46: {=IFERROR(INDEX(COA!$C$5:$C$59,MATCH(JURNAL!E46,COA!$B$5:$B$59,0)),"")} -> Pendapatan jasa | G46: 11207711 | J46: =IF(E46="","",COUNTIF($E$7:E46,E46)&E46) -> 34110
B47: 3 juni 2026 | D47: DTF | E47: 5070 | H47: 25000 | J47: =IF(E47="","",COUNTIF($E$7:E47,E47)&E47) -> 15070
B48: 3 juni 2026 | D48: BENSIN KIMKO | E48: 6000 | F48: {=IFERROR(INDEX(COA!$C$5:$C$59,MATCH(JURNAL!E48,COA!$B$5:$B$59,0)),"")} | H48: 20000 | J48: =IF(E48="","",COUNTIF($E$7:E48,E48)&E48) -> 26000
B49: 3 juni 2026 | D49: SUEDE ERASER | E49: 5030 | F49: {=IFERROR(INDEX(COA!$C$5:$C$59,MATCH(JURNAL!E49,COA!$B$5:$B$59,0)),"")} -> Hpp reguler | H49: 6912 | J49: =IF(E49="","",COUNTIF($E$7:E49,E49)&E49) -> 85030
B50: 3 juni 2026 | D50: CAT SERBAGUNA | E50: 5030 | F50: {=IFERROR(INDEX(COA!$C$5:$C$59,MATCH(JURNAL!E50,COA!$B$5:$B$59,0)),"")} -> Hpp reguler | H50: 28270 | J50: =IF(E50="","",COUNTIF($E$7:E50,E50)&E50) -> 95030
B51: 3 juni 2026 | D51: FOAM SHOES | E51: 5030 | F51: {=IFERROR(INDEX(COA!$C$5:$C$59,MATCH(JURNAL!E51,COA!$B$5:$B$59,0)),"")} -> Hpp reguler | H51: 43570 | J51: =IF(E51="","",COUNTIF($E$7:E51,E51)&E51) -> 105030
B52: 3 juni 2026 | D52: HEEL PATCH | E52: 5030 | F52: {=IFERROR(INDEX(COA!$C$5:$C$59,MATCH(JURNAL!E52,COA!$B$5:$B$59,0)),"")} -> Hpp reguler | H52: 29182 | J52: =IF(E52="","",COUNTIF($E$7:E52,E52)&E52) -> 115030
B53: 3 juni 2026 | D53: ORANGE ACRYLIC | E53: 5030 | F53: {=IFERROR(INDEX(COA!$C$5:$C$59,MATCH(JURNAL!E53,COA!$B$5:$B$59,0)),"")} -> Hpp reguler | H53: 44686 | J53: =IF(E53="","",COUNTIF($E$7:E53,E53)&E53) -> 125030
B54: 3 juni 2026 | D54: RABUAN UJANG DANU | E54: 5108 | F54: {=IFERROR(INDEX(COA!$C$5:$C$59,MATCH(JURNAL!E54,COA!$B$5:$B$59,0)),"")} -> Beban gaji tukang | H54: 100000 | J54: =IF(E54="","",COUNTIF($E$7:E54,E54)&E54) -> 15108
B55: 3 juni 2026 | D55: RABUAN AGUS | E55: 5108 | F55: {=IFERROR(INDEX(COA!$C$5:$C$59,MATCH(JURNAL!E55,COA!$B$5:$B$59,0)),"")} -> Beban gaji tukang | H55: 100000 | J55: =IF(E55="","",COUNTIF($E$7:E55,E55)&E55) -> 25108
B56: 3 juni 2026 | D56: RABUAN EDI | E56: 5108 | F56: {=IFERROR(INDEX(COA!$C$5:$C$59,MATCH(JURNAL!E56,COA!$B$5:$B$59,0)),"")} -> Beban gaji tukang | H56: 100000 | J56: =IF(E56="","",COUNTIF($E$7:E56,E56)&E56) -> 35108
B57: 3 juni 2026 | D57: RABUAN DEDE | E57: 5108 | F57: {=IFERROR(INDEX(COA!$C$5:$C$59,MATCH(JURNAL!E57,COA!$B$5:$B$59,0)),"")} -> Beban gaji tukang | H57: 100000 | J57: =IF(E57="","",COUNTIF($E$7:E57,E57)&E57) -> 45108
B58: 3 juni 2026 | D58: RABUAN YAYAN | E58: 5108 | F58: {=IFERROR(INDEX(COA!$C$5:$C$59,MATCH(JURNAL!E58,COA!$B$5:$B$59,0)),"")} -> Beban gaji tukang | H58: 100000 | J58: =IF(E58="","",COUNTIF($E$7:E58,E58)&E58) -> 55108
B59: 3 juni 2026 | D59: RABUAN AJI | E59: 5108 | F59: {=IFERROR(INDEX(COA!$C$5:$C$59,MATCH(JURNAL!E59,COA!$B$5:$B$59,0)),"")} -> Beban gaji tukang | H59: 100000 | J59: =IF(E59="","",COUNTIF($E$7:E59,E59)&E59) -> 65108
... B61: 3 juni 2026 | D61: wa api | E61: 5450 | F61: {=IFERROR(INDEX(COA!$C$5:$C$59,MATCH(JURNAL!E61,COA!$B$5:$B$59,0)),"")} -> WA API | H61: 867375 | J61: =IF(E61="","",COUNTIF($E$7:E61,E61)&E61) -> 15450
B62: 3 juni 2026 | D62: prive | F62: {=IFERROR(INDEX(COA!$C$5:$C$59,MATCH(JURNAL!E62,COA!$B$5:$B$59,0)),"")} | H62: 100000 | J62: =IF(E62="","",COUNTIF($E$7:E62,E62)&E62)
B63: 3 juni 2026 | D63: meeting luar | E63: 5200 | F63: {=IFERROR(INDEX(COA!$C$5:$C$59,MATCH(JURNAL!E63,COA!$B$5:$B$59,0)),"")} -> Konsumsi lembur & Meeting | H63: 75000 | J63: =IF(E63="","",COUNTIF($E$7:E63,E63)&E63) -> 25200
B64: 4 juni 2026 | D64: pendapatan jasa | E64: 4110 | F64: {=IFERROR(INDEX(COA!$C$5:$C$59,MATCH(JURNAL!E64,COA!$B$5:$B$59,0)),"")} -> Pendapatan jasa | G64: 13057661 | J64: =IF(E64="","",COUNTIF($E$7:E64,E64)&E64) -> 44110
B65: 4 juni 2026 | D65: ads | E65: 5440 | F65: {=IFERROR(INDEX(COA!$C$5:$C$59,MATCH(JURNAL!E65,COA!$B$5:$B$59,0)),"")} -> ADS | H65: 3000000 | J65: =IF(E65="","",COUNTIF($E$7:E65,E65)&E65) -> 35440
B66: 4 juni 2026 | D66: hutang gaji mei ttl 11.901.167 | E66: 2120 | F66: {=IFERROR(INDEX(COA!$C$5:$C$59,MATCH(JURNAL!E66,COA!$B$5:$B$59,0)),"")} -> Utang Gaji | H66: 6000000 | J66: =IF(E66="","",COUNTIF($E$7:E66,E66)&E66) -> 22120
B67: 4 juni 2026 | D67: prive | F67: {=IFERROR(INDEX(COA!$C$5:$C$59,MATCH(JURNAL!E67,COA!$B$5:$B$59,0)),"")} | H67: 201000 | J67: =IF(E67="","",COUNTIF($E$7:E67,E67)&E67)
B68: 4 juni 2026 | D68: fee charger | F68: {=IFERROR(INDEX(COA!$C$5:$C$59,MATCH(JURNAL!E68,COA!$B$5:$B$59,0)),"")} | H68: 20000 | J68: =IF(E68="","",COUNTIF($E$7:E68,E68)&E68)
B69: 4 juni 2026 | D69: alat studio photo gudang | E69: 1201 | F69: {=IFERROR(INDEX(COA!$C$5:$C$59,MATCH(JURNAL!E69,COA!$B$5:$B$59,0)),"")} -> Peralatan | H69: 515685 | J69: =IF(E69="","",COUNTIF($E$7:E69,E69)&E69) -> 11201
B70: 4 juni 2026 | D70: kardus 150 kecil + 40 besar packaging gudang & admin | E70: 5300 | F70: {=IFERROR(INDEX(COA!$C$5:$C$59,MATCH(JURNAL!E70,COA!$B$5:$B$59,0)),"")} -> Biaya packaging | H70: 582500 | J70: =IF(E70="","",COUNTIF($E$7:E70,E70)&E70) -> 15300
B71: 4 juni 2026 | D71: refund kelebihan bayar an syamsul alam S-2605-31-1505-AW | E71: 5310 | F71: {=IFERROR(INDEX(COA!$C$5:$C$59,MATCH(JURNAL!E71,COA!$B$5:$B$59,0)),"")} -> Biaya ekspedisi & ongkir | H71: 75374 | J71: =IF(E71="","",COUNTIF($E$7:E71,E71)&E71) -> 45310
B72: 4 juni 2026 | D72: kompensasi ongkir an kai S-2605-07-0356-SB | F72: {=IFERROR(INDEX(COA!$C$5:$C$59,MATCH(JURNAL!E72,COA!$B$5:$B$59,0)),"")} | H72: 11000 | J72: =IF(E72="","",COUNTIF($E$7:E72,E72)&E72)
B73: 4 juni 2026 | D73: SUMBER | E73: 5010 | F73: {=IFERROR(INDEX(COA!$C$5:$C$59,MATCH(JURNAL!E73,COA!$B$5:$B$59,0)),"")} -> Hpp sole | H73: 182000 | J73: =IF(E73="","",COUNTIF($E$7:E73,E73)&E73) -> 135010
B74: 4 juni 2026 | D74: ZIPPER DAN JARUM | E74: 5020 | F74: {=IFERROR(INDEX(COA!$C$5:$C$59,MATCH(JURNAL!E74,COA!$B$5:$B$59,0)),"")} -> Hpp upper | H74: 53000 | J74: =IF(E74="","",COUNTIF($E$7:E74,E74)&E74) -> 15020
B75: 5 juni 2026 | D75: pendapatan jasa | E75: 4110 | F75: {=IFERROR(INDEX(COA!$C$5:$C$59,MATCH(JURNAL!E75,COA!$B$5:$B$59,0)),"")} -> Pendapatan jasa | G75: 12673344 | J75: =IF(E75="","",COUNTIF($E$7:E75,E75)&E75) -> 54110
B76: 5 juni 2026 | D76: pengembalian kelebihan perjalanan dinas | F76: {=IFERROR(INDEX(COA!$C$5:$C$59,MATCH(JURNAL!E76,COA!$B$5:$B$59,0)),"")} | G76: 196000 | J76: =IF(E76="","",COUNTIF($E$7:E76,E76)&E76)
B77: 5 juni 2026 | D77: loker tukang (milla hrd) | E77: 6040 | F77: {=IFERROR(INDEX(COA!$C$5:$C$59,MATCH(JURNAL!E77,COA!$B$5:$B$59,0)),"")} | H77: 59000 | J77: =IF(E77="","",COUNTIF($E$7:E77,E77)&E77) -> 16040
B78: 5 juni 2026 | D78: alat tataban cangkang mesin jahit | E78: 6100 | F78: {=IFERROR(INDEX(COA!$C$5:$C$59,MATCH(JURNAL!E78,COA!$B$5:$B$59,0)),"")} | H78: 35000 | J78: =IF(E78="","",COUNTIF($E$7:E78,E78)&E78) -> 16100
B79: 5 juni 2026 | D79: plastik ws | E79: 5300 | F79: {=IFERROR(INDEX(COA!$C$5:$C$59,MATCH(JURNAL!E79,COA!$B$5:$B$59,0)),"")} -> Biaya packaging | H79: 42500 | J79: =IF(E79="","",COUNTIF($E$7:E79,E79)&E79) -> 25300
B80: 5 juni 2026 | D80: BENSIN KIMKO | E80: 6000 | F80: {=IFERROR(INDEX(COA!$C$5:$C$59,MATCH(JURNAL!E80,COA!$B$5:$B$59,0)),"")} | H80: 20000 | J80: =IF(E80="","",COUNTIF($E$7:E80,E80)&E80) -> 36000
B81: 5 juni 2026 | D81: slekkflow | E81: 5410 | F81: {=IFERROR(INDEX(COA!$C$5:$C$59,MATCH(JURNAL!E81,COA!$B$5:$B$59,0)),"")} -> Sleekflow | H81: 11735000 | J81: =IF(E81="","",COUNTIF($E$7:E81,E81)&E81) -> 15410
B82: 5 juni 2026 | D82: hutang gaji mei ttl 11.901.167 | E82: 2120 | F82: {=IFERROR(INDEX(COA!$C$5:$C$59,MATCH(JURNAL!E82,COA!$B$5:$B$59,0)),"")} -> Utang Gaji | H82: 5901167 | J82: =IF(E82="","",COUNTIF($E$7:E82,E82)&E82) -> 32120
B83: 5 juni 2026 | D83: ads | E83: 5440 | F83: {=IFERROR(INDEX(COA!$C$5:$C$59,MATCH(JURNAL!E83,COA!$B$5:$B$59,0)),"")} -> ADS | H83: 2600000 | J83: =IF(E83="","",COUNTIF($E$7:E83,E83)&E83) -> 45440
B84: 5 juni 2026 | D84: prive | F84: {=IFERROR(INDEX(COA!$C$5:$C$59,MATCH(JURNAL!E84,COA!$B$5:$B$59,0)),"")} | H84: 200000 | J84: =IF(E84="","",COUNTIF($E$7:E84,E84)&E84)
B85: 5 juni 2026 | D85: refund ongkir an ryantino L-2605-03-0003-IK di ambil sendiri | E85: 5310 | F85: {=IFERROR(INDEX(COA!$C$5:$C$59,MATCH(JURNAL!E85,COA!$B$5:$B$59,0)),"")} -> Biaya ekspedisi & ongkir | H85: 10000 | J85: =IF(E85="","",COUNTIF($E$7:E85,E85)&E85) -> 55310
B86: 5 juni 2026 | D86: ongkir an yenny lim 5 sepatu 0041-sb pakai jne | E86: 5310 | F86: {=IFERROR(INDEX(COA!$C$5:$C$59,MATCH(JURNAL!E86,COA!$B$5:$B$59,0)),"")} -> Biaya ekspedisi & ongkir | H86: 84000 | J86: =IF(E86="","",COUNTIF($E$7:E86,E86)&E86) -> 65310
B87: 5 juni 2026 | D87: ads tambahan bca 3jt | E87: 5440 | F87: {=IFERROR(INDEX(COA!$C$5:$C$59,MATCH(JURNAL!E87,COA!$B$5:$B$59,0)),"")} -> ADS | H87: 400000 | J87: =IF(E87="","",COUNTIF($E$7:E87,E87)&E87) -> 55440
B88: 5 juni 2026 | D88: atk + parkir | E88: 6030 | F88: {=IFERROR(INDEX(COA!$C$5:$C$59,MATCH(JURNAL!E88,COA!$B$5:$B$59,0)),"")} | H88: 246000 | J88: =IF(E88="","",COUNTIF($E$7:E88,E88)&E88) -> 26030
B89: 6 juni 2026 | D89: pendapatan jasa | E89: 4110 | F89: {=IFERROR(INDEX(COA!$C$5:$C$59,MATCH(JURNAL!E89,COA!$B$5:$B$59,0)),"")} -> Pendapatan jasa | G89: 7724550 | J89: =IF(E89="","",COUNTIF($E$7:E89,E89)&E89) -> 64110
B90: 6 juni 2026 | D90: pengembalian dp kursi | E90: 7010 | F90: {=IFERROR(INDEX(COA!$C$5:$C$59,MATCH(JURNAL!E90,COA!$B$5:$B$59,0)),"")} -> pendapatan lain-lain | G90: 200000 | J90: =IF(E90="","",COUNTIF($E$7:E90,E90)&E90) -> 17010
B91: 6 juni 2026 | D91: ads 2 hari | E91: 5440 | F91: {=IFERROR(INDEX(COA!$C$5:$C$59,MATCH(JURNAL!E91,COA!$B$5:$B$59,0)),"")} -> ADS | H91: 4000000 | J91: =IF(E91="","",COUNTIF($E$7:E91,E91)&E91) -> 65440
B92: 6 juni 2026 | D92: prive | F92: {=IFERROR(INDEX(COA!$C$5:$C$59,MATCH(JURNAL!E92,COA!$B$5:$B$59,0)),"")} | H92: 100000 | J92: =IF(E92="","",COUNTIF($E$7:E92,E92)&E92)
B93: 6 juni 2026 | D93: pembelian alat listrik | E93: 6130 | F93: {=IFERROR(INDEX(COA!$C$5:$C$59,MATCH(JURNAL!E93,COA!$B$5:$B$59,0)),"")} | H93: 154500 | J93: =IF(E93="","",COUNTIF($E$7:E93,E93)&E93) -> 16130
B94: 6 juni 2026 | D94: um 8 orang | E94: 5200 | F94: {=IFERROR(INDEX(COA!$C$5:$C$59,MATCH(JURNAL!E94,COA!$B$5:$B$59,0)),"")} -> Konsumsi lembur & Meeting | H94: 120000 | J94: =IF(E94="","",COUNTIF($E$7:E94,E94)&E94) -> 35200
B95: 6 juni 2026 | D95: atk | E95: 6030 | F95: {=IFERROR(INDEX(COA!$C$5:$C$59,MATCH(JURNAL!E95,COA!$B$5:$B$59,0)),"")} | H95: 118500 | J95: =IF(E95="","",COUNTIF($E$7:E95,E95)&E95) -> 36030
B96: 6 juni 2026 | D96: pemeliharaan kebersihan | E96: 6090 | F96: {=IFERROR(INDEX(COA!$C$5:$C$59,MATCH(JURNAL!E96,COA!$B$5:$B$59,0)),"")} | H96: 104060 | J96: =IF(E96="","",COUNTIF($E$7:E96,E96)&E96) -> 16090
B97: 6 juni 2026 | D97: listrik office | E97: 5500 | F97: {=IFERROR(INDEX(COA!$C$5:$C$59,MATCH(JURNAL!E97,COA!$B$5:$B$59,0)),"")} -> Beban Listrik Office | H97: 53500 | J97: =IF(E97="","",COUNTIF($E$7:E97,E97)&E97) -> 15500
B98: 6 juni 2026 | D98: wa api tgl 1 dan 7 juni | E98: 5450 | F98: {=IFERROR(INDEX(COA!$C$5:$C$59,MATCH(JURNAL!E98,COA!$B$5:$B$59,0)),"")} -> WA API | H98: 737568 | J98: =IF(E98="","",COUNTIF($E$7:E98,E98)&E98) -> 25450
B99: 6 juni 2026 | D99: belanja ws kulit jatim | E99: 5030 | F99: {=IFERROR(INDEX(COA!$C$5:$C$59,MATCH(JURNAL!E99,COA!$B$5:$B$59,0)),"")} -> Hpp reguler | H99: 1214500 | J99: =IF(E99="","",COUNTIF($E$7:E99,E99)&E99) -> 135030
B100: 6 juni 2026 | D100: TEST PEN | F100: {=IFERROR(INDEX(COA!$C$5:$C$59,MATCH(JURNAL!E100,COA!$B$5:$B$59,0)),"")} | H100: 10000 | J100: =IF(E100="","",COUNTIF($E$7:E100,E100)&E100)
B101: 6 juni 2026 | D101: GAJI MINGGUAN UJANG DANU | E101: 5108 | F101: {=IFERROR(INDEX(COA!$C$5:$C$59,MATCH(JURNAL!E101,COA!$B$5:$B$59,0)),"")} -> Beban gaji tukang | H101: 752000 | J101: =IF(E101="","",COUNTIF($E$7:E101,E101)&E101) -> 75108
B102: 6 juni 2026 | D102: GAJI MINGGUAN AGUS | E102: 5108 | F102: {=IFERROR(INDEX(COA!$C$5:$C$59,MATCH(JURNAL!E102,COA!$B$5:$B$59,0)),"")} -> Beban gaji tukang | H102: 702000 | J102: =IF(E102="","",COUNTIF($E$7:E102,E102)&E102) -> 85108
B103: 6 juni 2026 | D103: GAJI MINGGUAN EDI | E103: 5108 | F103: {=IFERROR(INDEX(COA!$C$5:$C$59,MATCH(JURNAL!E103,COA!$B$5:$B$59,0)),"")} -> Beban gaji tukang | H103: 652000 | J103: =IF(E103="","",COUNTIF($E$7:E103,E103)&E103) -> 95108
B104: 6 juni 2026 | D104: GAJI MINGGUAN DEDE | E104: 5108 | F104: {=IFERROR(INDEX(COA!$C$5:$C$59,MATCH(JURNAL!E104,COA!$B$5:$B$59,0)),"")} -> Beban gaji tukang | H104: 574000 | J104: =IF(E104="","",COUNTIF($E$7:E104,E104)&E104) -> 105108
B105: 6 juni 2026 | D105: GAJI MINGGUAN AI | E105: 5108 | F105: {=IFERROR(INDEX(COA!$C$5:$C$59,MATCH(JURNAL!E105,COA!$B$5:$B$59,0)),"")} -> Beban gaji tukang | H105: 702000 | J105: =IF(E105="","",COUNTIF($E$7:E105,E105)&E105) -> 115108
B106: 6 juni 2026 | D106: GAJI MINGGUAN YAYAN | E106: 5108 | F106: {=IFERROR(INDEX(COA!$C$5:$C$59,MATCH(JURNAL!E106,COA!$B$5:$B$59,0)),"")} -> Beban gaji tukang | H106: 652000 | J106: =IF(E106="","",COUNTIF($E$7:E106,E106)&E106) -> 125108
B107: 6 juni 2026 | D107: GAJI MINGGUAN HADI | E107: 5108 | F107: {=IFERROR(INDEX(COA!$C$5:$C$59,MATCH(JURNAL!E107,COA!$B$5:$B$59,0)),"")} -> Beban gaji tukang | H107: 600000 | J107: =IF(E107="","",COUNTIF($E$7:E107,E107)&E107) -> 135108
B108: 6 juni 2026 | D108: GAJI MINGGUAN AJI | E108: 5108 | F108: {=IFERROR(INDEX(COA!$C$5:$C$59,MATCH(JURNAL!E108,COA!$B$5:$B$59,0)),"")} -> Beban gaji tukang | H108: 500000 | J108: =IF(E108="","",COUNTIF($E$7:E108,E108)&E108) -> 145108
B109: 6 juni 2026 | D109: GAJI MINGUAN RUDI | E109: 5108 | F109: {=IFERROR(INDEX(COA!$C$5:$C$59,MATCH(JURNAL!E109,COA!$B$5:$B$59,0)),"")} -> Beban gaji tukang | H109: 600000 | J109: =IF(E109="","",COUNTIF($E$7:E109,E109)&E109) -> 155108
B110: 6 juni 2026 | D110: GAJI MINGGUAN ILHAM | E110: 5108 | F110: {=IFERROR(INDEX(COA!$C$5:$C$59,MATCH(JURNAL!E110,COA!$B$5:$B$59,0)),"")} -> Beban gaji tukang | H110: 500000 | J110: =IF(E110="","",COUNTIF($E$7:E110,E110)&E110) -> 165108
B111: 6 juni 2026 | D111: GAJI MINGGUAN RIZKI | E111: 5108 | F111: {=IFERROR(INDEX(COA!$C$5:$C$59,MATCH(JURNAL!E111,COA!$B$5:$B$59,0)),"")} -> Beban gaji tukang | H111: 500000 | J111: =IF(E111="","",COUNTIF($E$7:E111,E111)&E111) -> 175108
B112: 6 juni 2026 | D112: GAJI MINGGUAN ADE | E112: 5108 | F112: {=IFERROR(INDEX(COA!$C$5:$C$59,MATCH(JURNAL!E112,COA!$B$5:$B$59,0)),"")} -> Beban gaji tukang | H112: 600000 | J112: =IF(E112="","",COUNTIF($E$7:E112,E112)&E112) -> 185108
...

Sheet BUKU BESAR
B2: PT. TERANG GARAM SOLUSINDO | I2: AKUN | J2: 1104
B3: BUKU BESAR | H3: {=INDEX(Type,MATCH(J2,KODEAKUN,0))} -> Piutang
B4: PERIODE | H4: {=INDEX(SaldoNormal,MATCH(H3,Type,0))} -> Debet
B6: KODE AKUN | D6: =IF(J2="","PILIHAKUN",J2) -> 1104 | F6: SALDO AWAL | G6: =IF(H4="Debet",H6-H7,H7-H6) -> 0
B7: NAMA AKUN | D7: {=INDEX(Nama_Akun,MATCH(J2,KODEAKUN,0))} -> Piutang | F7: SALDO AKHIR | G7: =IF($H$4="Debet",G6+(SUM(E11:E90)-SUM(F11:F90)),G6+(SUM(F11:F90)-SUM(E11:E90))) -> 0 | H7: {=INDEX(COA_KREDIT,MATCH(J2,KODEAKUN,0))} -> 0
B9: Tanggal | C9: REF | D9: Keterangan | E9: Debet | F9: Kredit | G9: Saldo | I9: FILTER
H10: =IF(B11="",0,1) -> 0
A11: 1 | B11: {=IFERROR(INDEX(JU_Tanggal,MATCH(A11&$J$2,JU_BB,0)),"")} | C11: {=IFERROR(INDEX(JU_REF,MATCH(A11&$J$2,JU_BB,0)),"")} | D11: {=IFERROR(INDEX(JU_Keterangan,MATCH(A11&$J$2,JU_BB,0)),"")} | E11: {=IFERROR(INDEX(JU_Debet,MATCH(A11&$J$2,JU_BB,0)),"")} | F11: {=IFERROR(INDEX(JU_Kredit,MATCH(A11&$J$2,JU_BB,0)),"")} | G11: =IFERROR(IF($H$4="Debet",G6+E11-F11,G6+F11-E11),"") | H11: =IF(B11="",0,1) -> 0
A12: 2 | B12: {=IFERROR(INDEX(JU_Tanggal,MATCH(A12&$J$2,JU_BB,0)),"")} | C12: {=IFERROR(INDEX(JU_REF,MATCH(A12&$J$2,JU_BB,0)),"")} | D12: {=IFERROR(INDEX(JU_Keterangan,MATCH(A12&$J$2,JU_BB,0)),"")} | E12: {=IFERROR(INDEX(JU_Debet,MATCH(A12&$J$2,JU_BB,0)),"")} | F12: {=IFERROR(INDEX(JU_Kredit,MATCH(A12&$J$2,JU_BB,0)),"")} | G12: =IFERROR(IF($H$4="Debet",G11+E12-F12,G11+F12-E12),"") | H12: =IF(B12="",0,1) -> 0 | I12: beban
A13: 3 | B13: {=IFERROR(INDEX(JU_Tanggal,MATCH(A13&$J$2,JU_BB,0)),"")} | C13: {=IFERROR(INDEX(JU_REF,MATCH(A13&$J$2,JU_BB,0)),"")} | D13: {=IFERROR(INDEX(JU_Keterangan,MATCH(A13&$J$2,JU_BB,0)),"")} | E13: {=IFERROR(INDEX(JU_Debet,MATCH(A13&$J$2,JU_BB,0)),"")} | F13: {=IFERROR(INDEX(JU_Kredit,MATCH(A13&$J$2,JU_BB,0)),"")} | G13: =IFERROR(IF($H$4="Debet",G12+E13-F13,G12+F13-E13),"") | H13: =IF(B13="",0,1) -> 0 | I13: beban
A14: 4 | B14: {=IFERROR(INDEX(JU_Tanggal,MATCH(A14&$J$2,JU_BB,0)),"")} | C14: {=IFERROR(INDEX(JU_REF,MATCH(A14&$J$2,JU_BB,0)),"")} | D14: {=IFERROR(INDEX(JU_Keterangan,MATCH(A14&$J$2,JU_BB,0)),"")} | E14: {=IFERROR(INDEX(JU_Debet,MATCH(A14&$J$2,JU_BB,0)),"")} | F14: {=IFERROR(INDEX(JU_Kredit,MATCH(A14&$J$2,JU_BB,0)),"")} | G14: =IFERROR(IF($H$4="Debet",G13+E14-F14,G13+F14-E14),"") | H14: =IF(B14="",0,1) -> 0 | I14: beban
A15: 5 | B15: {=IFERROR(INDEX(JU_Tanggal,MATCH(A15&$J$2,JU_BB,0)),"")} | C15: {=IFERROR(INDEX(JU_REF,MATCH(A15&$J$2,JU_BB,0)),"")} | D15: {=IFERROR(INDEX(JU_Keterangan,MATCH(A15&$J$2,JU_BB,0)),"")} | E15: {=IFERROR(INDEX(JU_Debet,MATCH(A15&$J$2,JU_BB,0)),"")} | F15: {=IFERROR(INDEX(JU_Kredit,MATCH(A15&$J$2,JU_BB,0)),"")} | G15: =IFERROR(IF($H$4="Debet",G14+E15-F15,G14+F15-E15),"") | H15: =IF(B15="",0,1) -> 0 | I15: persediaan
A16: 6 | B16: {=IFERROR(INDEX(JU_Tanggal,MATCH(A16&$J$2,JU_BB,0)),"")} | C16: {=IFERROR(INDEX(JU_REF,MATCH(A16&$J$2,JU_BB,0)),"")} | D16: {=IFERROR(INDEX(JU_Keterangan,MATCH(A16&$J$2,JU_BB,0)),"")} | E16: {=IFERROR(INDEX(JU_Debet,MATCH(A16&$J$2,JU_BB,0)),"")} | F16: {=IFERROR(INDEX(JU_Kredit,MATCH(A16&$J$2,JU_BB,0)),"")} | G16: =IFERROR(IF($H$4="Debet",G15+E16-F16,G15+F16-E16),"") | H16: =IF(B16="",0,1) -> 0 | I16: piutang
A17: 7 | B17: {=IFERROR(INDEX(JU_Tanggal,MATCH(A17&$J$2,JU_BB,0)),"")} | C17: {=IFERROR(INDEX(JU_REF,MATCH(A17&$J$2,JU_BB,0)),"")} | D17: {=IFERROR(INDEX(JU_Keterangan,MATCH(A17&$J$2,JU_BB,0)),"")} | E17: {=IFERROR(INDEX(JU_Debet,MATCH(A17&$J$2,JU_BB,0)),"")} | F17: {=IFERROR(INDEX(JU_Kredit,MATCH(A17&$J$2,JU_BB,0)),"")} | G17: =IFERROR(IF($H$4="Debet",G16+E17-F17,G16+F17-E17),"") | H17: =IF(B17="",0,1) -> 0 | I17: pendapatan
A18: 8 | B18: {=IFERROR(INDEX(JU_Tanggal,MATCH(A18&$J$2,JU_BB,0)),"")} | C18: {=IFERROR(INDEX(JU_REF,MATCH(A18&$J$2,JU_BB,0)),"")} | D18: {=IFERROR(INDEX(JU_Keterangan,MATCH(A18&$J$2,JU_BB,0)),"")} | E18: {=IFERROR(INDEX(JU_Debet,MATCH(A18&$J$2,JU_BB,0)),"")} | F18: {=IFERROR(INDEX(JU_Kredit,MATCH(A18&$J$2,JU_BB,0)),"")} | G18: =IFERROR(IF($H$4="Debet",G17+E18-F18,G17+F18-E18),"") | H18: =IF(B18="",0,1) -> 0 | I18: pendapatan
A19: 9 | B19: {=IFERROR(INDEX(JU_Tanggal,MATCH(A19&$J$2,JU_BB,0)),"")} | C19: {=IFERROR(INDEX(JU_REF,MATCH(A19&$J$2,JU_BB,0)),"")} | D19: {=IFERROR(INDEX(JU_Keterangan,MATCH(A19&$J$2,JU_BB,0)),"")} | E19: {=IFERROR(INDEX(JU_Debet,MATCH(A19&$J$2,JU_BB,0)),"")} | F19: {=IFERROR(INDEX(JU_Kredit,MATCH(A19&$J$2,JU_BB,0)),"")} | G19: =IFERROR(IF($H$4="Debet",G18+E19-F19,G18+F19-E19),"") | H19: =IF(B19="",0,1) -> 0 | I19: beban
A20: 10 | B20: {=IFERROR(INDEX(JU_Tanggal,MATCH(A20&$J$2,JU_BB,0)),"")} | C20: {=IFERROR(INDEX(JU_REF,MATCH(A20&$J$2,JU_BB,0)),"")} | D20: {=IFERROR(INDEX(JU_Keterangan,MATCH(A20&$J$2,JU_BB,0)),"")} | E20: {=IFERROR(INDEX(JU_Debet,MATCH(A20&$J$2,JU_BB,0)),"")} | F20: {=IFERROR(INDEX(JU_Kredit,MATCH(A20&$J$2,JU_BB,0)),"")} | G20: =IFERROR(IF($H$4="Debet",G19+E20-F20,G19+F20-E20),"") | H20: =IF(B20="",0,1) -> 0 | I20: pendapatan
A21: 11 | B21: {=IFERROR(INDEX(JU_Tanggal,MATCH(A21&$J$2,JU_BB,0)),"")} | C21: {=IFERROR(INDEX(JU_REF,MATCH(A21&$J$2,JU_BB,0)),"")} | D21: {=IFERROR(INDEX(JU_Keterangan,MATCH(A21&$J$2,JU_BB,0)),"")} | E21: {=IFERROR(INDEX(JU_Debet,MATCH(A21&$J$2,JU_BB,0)),"")} | F21: {=IFERROR(INDEX(JU_Kredit,MATCH(A21&$J$2,JU_BB,0)),"")} | G21: =IFERROR(IF($H$4="Debet",G20+E21-F21,G20+F21-E21),"") | H21: =IF(B21="",0,1) -> 0 | I21: peralatan
A22: 12 | B22: {=IFERROR(INDEX(JU_Tanggal,MATCH(A22&$J$2,JU_BB,0)),"")} | C22: {=IFERROR(INDEX(JU_REF,MATCH(A22&$J$2,JU_BB,0)),"")} | D22: {=IFERROR(INDEX(JU_Keterangan,MATCH(A22&$J$2,JU_BB,0)),"")} | E22: {=IFERROR(INDEX(JU_Debet,MATCH(A22&$J$2,JU_BB,0)),"")} | F22: {=IFERROR(INDEX(JU_Kredit,MATCH(A22&$J$2,JU_BB,0)),"")} | G22: =IFERROR(IF($H$4="Debet",G21+E22-F22,G21+F22-E22),"") | H22: =IF(B22="",0,1) -> 0 | I22: peralatan
A23: 13 | B23: {=IFERROR(INDEX(JU_Tanggal,MATCH(A23&$J$2,JU_BB,0)),"")} | C23: {=IFERROR(INDEX(JU_REF,MATCH(A23&$J$2,JU_BB,0)),"")} | D23: {=IFERROR(INDEX(JU_Keterangan,MATCH(A23&$J$2,JU_BB,0)),"")} | E23: {=IFERROR(INDEX(JU_Debet,MATCH(A23&$J$2,JU_BB,0)),"")} | F23: {=IFERROR(INDEX(JU_Kredit,MATCH(A23&$J$2,JU_BB,0)),"")} | G23: =IFERROR(IF($H$4="Debet",G22+E23-F23,G22+F23-E23),"") | H23: =IF(B23="",0,1) -> 0 | I23: pendapatan
... A26: 16 | B26: {=IFERROR(INDEX(JU_Tanggal,MATCH(A26&$J$2,JU_BB,0)),"")} | C26: {=IFERROR(INDEX(JU_REF,MATCH(A26&$J$2,JU_BB,0)),"")} | D26: {=IFERROR(INDEX(JU_Keterangan,MATCH(A26&$J$2,JU_BB,0)),"")} | E26: {=IFERROR(INDEX(JU_Debet,MATCH(A26&$J$2,JU_BB,0)),"")} | F26: {=IFERROR(INDEX(JU_Kredit,MATCH(A26&$J$2,JU_BB,0)),"")} | G26: =IFERROR(IF($H$4="Debet",G25+E26-F26,G25+F26-E26),"") | H26: =IF(B26="",0,1) -> 0 | I26: pendapatan
A27: =A26+1 -> 17 | B27: {=IFERROR(INDEX(JU_Tanggal,MATCH(A27&$J$2,JU_BB,0)),"")} | C27: {=IFERROR(INDEX(JU_REF,MATCH(A27&$J$2,JU_BB,0)),"")} | D27: {=IFERROR(INDEX(JU_Keterangan,MATCH(A27&$J$2,JU_BB,0)),"")} | E27: {=IFERROR(INDEX(JU_Debet,MATCH(A27&$J$2,JU_BB,0)),"")} | F27: {=IFERROR(INDEX(JU_Kredit,MATCH(A27&$J$2,JU_BB,0)),"")} | G27: =IFERROR(IF($H$4="Debet",G26+E27-F27,G26+F27-E27),"") | H27: =IF(B27="",0,1) -> 0 | I27: beban
A28: =A27+1 -> 18 | B28: {=IFERROR(INDEX(JU_Tanggal,MATCH(A28&$J$2,JU_BB,0)),"")} | C28: {=IFERROR(INDEX(JU_REF,MATCH(A28&$J$2,JU_BB,0)),"")} | D28: {=IFERROR(INDEX(JU_Keterangan,MATCH(A28&$J$2,JU_BB,0)),"")} | E28: {=IFERROR(INDEX(JU_Debet,MATCH(A28&$J$2,JU_BB,0)),"")} | F28: {=IFERROR(INDEX(JU_Kredit,MATCH(A28&$J$2,JU_BB,0)),"")} | G28: =IFERROR(IF($H$4="Debet",G27+E28-F28,G27+F28-E28),"") | H28: =IF(B28="",0,1) -> 0 | I28: persediaan
A29: =A28+1 -> 19 | B29: {=IFERROR(INDEX(JU_Tanggal,MATCH(A29&$J$2,JU_BB,0)),"")} | C29: {=IFERROR(INDEX(JU_REF,MATCH(A29&$J$2,JU_BB,0)),"")} | D29: {=IFERROR(INDEX(JU_Keterangan,MATCH(A29&$J$2,JU_BB,0)),"")} | E29: {=IFERROR(INDEX(JU_Debet,MATCH(A29&$J$2,JU_BB,0)),"")} | F29: {=IFERROR(INDEX(JU_Kredit,MATCH(A29&$J$2,JU_BB,0)),"")} | G29: =IFERROR(IF($H$4="Debet",G28+E29-F29,G28+F29-E29),"") | H29: =IF(B29="",0,1) -> 0 | I29: pendapatan
A30: =A29+1 -> 20 | B30: {=IFERROR(INDEX(JU_Tanggal,MATCH(A30&$J$2,JU_BB,0)),"")} | C30: {=IFERROR(INDEX(JU_REF,MATCH(A30&$J$2,JU_BB,0)),"")} | D30: {=IFERROR(INDEX(JU_Keterangan,MATCH(A30&$J$2,JU_BB,0)),"")} | E30: {=IFERROR(INDEX(JU_Debet,MATCH(A30&$J$2,JU_BB,0)),"")} | F30: {=IFERROR(INDEX(JU_Kredit,MATCH(A30&$J$2,JU_BB,0)),"")} | G30: =IFERROR(IF($H$4="Debet",G29+E30-F30,G29+F30-E30),"") | H30: =IF(B30="",0,1) -> 0 | I30: pendapatan
A31: =A30+1 -> 21 | B31: {=IFERROR(INDEX(JU_Tanggal,MATCH(A31&$J$2,JU_BB,0)),"")} | C31: {=IFERROR(INDEX(JU_REF,MATCH(A31&$J$2,JU_BB,0)),"")} | D31: {=IFERROR(INDEX(JU_Keterangan,MATCH(A31&$J$2,JU_BB,0)),"")} | E31: {=IFERROR(INDEX(JU_Debet,MATCH(A31&$J$2,JU_BB,0)),"")} | F31: {=IFERROR(INDEX(JU_Kredit,MATCH(A31&$J$2,JU_BB,0)),"")} | G31: =IFERROR(IF($H$4="Debet",G30+E31-F31,G30+F31-E31),"") | H31: =IF(B31="",0,1) -> 0 | I31: pendapatan
A32: =A31+1 -> 22 | B32: {=IFERROR(INDEX(JU_Tanggal,MATCH(A32&$J$2,JU_BB,0)),"")} | C32: {=IFERROR(INDEX(JU_REF,MATCH(A32&$J$2,JU_BB,0)),"")} | D32: {=IFERROR(INDEX(JU_Keterangan,MATCH(A32&$J$2,JU_BB,0)),"")} | E32: {=IFERROR(INDEX(JU_Debet,MATCH(A32&$J$2,JU_BB,0)),"")} | F32: {=IFERROR(INDEX(JU_Kredit,MATCH(A32&$J$2,JU_BB,0)),"")} | G32: =IFERROR(IF($H$4="Debet",G31+E32-F32,G31+F32-E32),"") | H32: =IF(B32="",0,1) -> 0 | I32: beban
A33: =A32+1 -> 23 | B33: {=IFERROR(INDEX(JU_Tanggal,MATCH(A33&$J$2,JU_BB,0)),"")} | C33: {=IFERROR(INDEX(JU_REF,MATCH(A33&$J$2,JU_BB,0)),"")} | D33: {=IFERROR(INDEX(JU_Keterangan,MATCH(A33&$J$2,JU_BB,0)),"")} | E33: {=IFERROR(INDEX(JU_Debet,MATCH(A33&$J$2,JU_BB,0)),"")} | F33: {=IFERROR(INDEX(JU_Kredit,MATCH(A33&$J$2,JU_BB,0)),"")} | G33: =IFERROR(IF($H$4="Debet",G32+E33-F33,G32+F33-E33),"") | H33: =IF(B33="",0,1) -> 0 | I33: pendapatan
A34: =A33+1 -> 24 | B34: {=IFERROR(INDEX(JU_Tanggal,MATCH(A34&$J$2,JU_BB,0)),"")} | C34: {=IFERROR(INDEX(JU_REF,MATCH(A34&$J$2,JU_BB,0)),"")} | D34: {=IFERROR(INDEX(JU_Keterangan,MATCH(A34&$J$2,JU_BB,0)),"")} | E34: {=IFERROR(INDEX(JU_Debet,MATCH(A34&$J$2,JU_BB,0)),"")} | F34: {=IFERROR(INDEX(JU_Kredit,MATCH(A34&$J$2,JU_BB,0)),"")} | G34: =IFERROR(IF($H$4="Debet",G33+E34-F34,G33+F34-E34),"") | H34: =IF(B34="",0,1) -> 0 | I34: beban
A35: =A34+1 -> 25 | B35: {=IFERROR(INDEX(JU_Tanggal,MATCH(A35&$J$2,JU_BB,0)),"")} | C35: {=IFERROR(INDEX(JU_REF,MATCH(A35&$J$2,JU_BB,0)),"")} | D35: {=IFERROR(INDEX(JU_Keterangan,MATCH(A35&$J$2,JU_BB,0)),"")} | E35: {=IFERROR(INDEX(JU_Debet,MATCH(A35&$J$2,JU_BB,0)),"")} | F35: {=IFERROR(INDEX(JU_Kredit,MATCH(A35&$J$2,JU_BB,0)),"")} | G35: =IFERROR(IF($H$4="Debet",G34+E35-F35,G34+F35-E35),"") | H35: =IF(B35="",0,1) -> 0 | I35: pendapatan
A36: =A35+1 -> 26 | B36: {=IFERROR(INDEX(JU_Tanggal,MATCH(A36&$J$2,JU_BB,0)),"")} | C36: {=IFERROR(INDEX(JU_REF,MATCH(A36&$J$2,JU_BB,0)),"")} | D36: {=IFERROR(INDEX(JU_Keterangan,MATCH(A36&$J$2,JU_BB,0)),"")} | E36: {=IFERROR(INDEX(JU_Debet,MATCH(A36&$J$2,JU_BB,0)),"")} | F36: {=IFERROR(INDEX(JU_Kredit,MATCH(A36&$J$2,JU_BB,0)),"")} | G36: =IFERROR(IF($H$4="Debet",G35+E36-F36,G35+F36-E36),"") | H36: =IF(B36="",0,1) -> 0 | I36: pendapatan
A37: =A36+1 -> 27 | B37: {=IFERROR(INDEX(JU_Tanggal,MATCH(A37&$J$2,JU_BB,0)),"")} | C37: {=IFERROR(INDEX(JU_REF,MATCH(A37&$J$2,JU_BB,0)),"")} | D37: {=IFERROR(INDEX(JU_Keterangan,MATCH(A37&$J$2,JU_BB,0)),"")} | E37: {=IFERROR(INDEX(JU_Debet,MATCH(A37&$J$2,JU_BB,0)),"")} | F37: {=IFERROR(INDEX(JU_Kredit,MATCH(A37&$J$2,JU_BB,0)),"")} | G37: =IFERROR(IF($H$4="Debet",G36+E37-F37,G36+F37-E37),"") | H37: =IF(B37="",0,1) -> 0 | I37: persediaan
A38: =A37+1 -> 28 | B38: {=IFERROR(INDEX(JU_Tanggal,MATCH(A38&$J$2,JU_BB,0)),"")} | C38: {=IFERROR(INDEX(JU_REF,MATCH(A38&$J$2,JU_BB,0)),"")} | D38: {=IFERROR(INDEX(JU_Keterangan,MATCH(A38&$J$2,JU_BB,0)),"")} | E38: {=IFERROR(INDEX(JU_Debet,MATCH(A38&$J$2,JU_BB,0)),"")} | F38: {=IFERROR(INDEX(JU_Kredit,MATCH(A38&$J$2,JU_BB,0)),"")} | G38: =IFERROR(IF($H$4="Debet",G37+E38-F38,G37+F38-E38),"") | H38: =IF(B38="",0,1) -> 0 | I38: beban
... A73: =A72+1 -> 63 | B73: {=IFERROR(INDEX(JU_Tanggal,MATCH(A73&$J$2,JU_BB,0)),"")} | C73: {=IFERROR(INDEX(JU_REF,MATCH(A73&$J$2,JU_BB,0)),"")} | D73: {=IFERROR(INDEX(JU_Keterangan,MATCH(A73&$J$2,JU_BB,0)),"")} | E73: {=IFERROR(INDEX(JU_Debet,MATCH(A73&$J$2,JU_BB,0)),"")} | F73: {=IFERROR(INDEX(JU_Kredit,MATCH(A73&$J$2,JU_BB,0)),"")} | G73: =IFERROR(IF($H$4="Debet",G72+E73-F73,G72+F73-E73),"") | H73: =IF(B73="",0,1) -> 0 | I73: beban
B74: {=IFERROR(INDEX(JU_Tanggal,MATCH(A74&$J$2,JU_BB,0)),"")} | C74: {=IFERROR(INDEX(JU_REF,MATCH(A74&$J$2,JU_BB,0)),"")} | D74: {=IFERROR(INDEX(JU_Keterangan,MATCH(A74&$J$2,JU_BB,0)),"")} | E74: {=IFERROR(INDEX(JU_Debet,MATCH(A74&$J$2,JU_BB,0)),"")} | F74: {=IFERROR(INDEX(JU_Kredit,MATCH(A74&$J$2,JU_BB,0)),"")} | H74: =IF(B74="",0,1) -> 0
B75: {=IFERROR(INDEX(JU_Tanggal,MATCH(A75&$J$2,JU_BB,0)),"")} | C75: {=IFERROR(INDEX(JU_REF,MATCH(A75&$J$2,JU_BB,0)),"")} | D75: {=IFERROR(INDEX(JU_Keterangan,MATCH(A75&$J$2,JU_BB,0)),"")} | E75: {=IFERROR(INDEX(JU_Debet,MATCH(A75&$J$2,JU_BB,0)),"")} | F75: {=IFERROR(INDEX(JU_Kredit,MATCH(A75&$J$2,JU_BB,0)),"")} | H75: =IF(B75="",0,1) -> 0
B76: {=IFERROR(INDEX(JU_Tanggal,MATCH(A76&$J$2,JU_BB,0)),"")} | C76: {=IFERROR(INDEX(JU_REF,MATCH(A76&$J$2,JU_BB,0)),"")} | D76: {=IFERROR(INDEX(JU_Keterangan,MATCH(A76&$J$2,JU_BB,0)),"")} | E76: {=IFERROR(INDEX(JU_Debet,MATCH(A76&$J$2,JU_BB,0)),"")} | F76: {=IFERROR(INDEX(JU_Kredit,MATCH(A76&$J$2,JU_BB,0)),"")} | H76: =IF(B76="",0,1) -> 0
B77: {=IFERROR(INDEX(JU_Tanggal,MATCH(A77&$J$2,JU_BB,0)),"")} | C77: {=IFERROR(INDEX(JU_REF,MATCH(A77&$J$2,JU_BB,0)),"")} | D77: {=IFERROR(INDEX(JU_Keterangan,MATCH(A77&$J$2,JU_BB,0)),"")} | E77: {=IFERROR(INDEX(JU_Debet,MATCH(A77&$J$2,JU_BB,0)),"")} | F77: {=IFERROR(INDEX(JU_Kredit,MATCH(A77&$J$2,JU_BB,0)),"")} | H77: =IF(B77="",0,1) -> 0
B78: {=IFERROR(INDEX(JU_Tanggal,MATCH(A78&$J$2,JU_BB,0)),"")} | C78: {=IFERROR(INDEX(JU_REF,MATCH(A78&$J$2,JU_BB,0)),"")} | D78: {=IFERROR(INDEX(JU_Keterangan,MATCH(A78&$J$2,JU_BB,0)),"")} | E78: {=IFERROR(INDEX(JU_Debet,MATCH(A78&$J$2,JU_BB,0)),"")} | F78: {=IFERROR(INDEX(JU_Kredit,MATCH(A78&$J$2,JU_BB,0)),"")} | H78: =IF(B78="",0,1) -> 0
B79: {=IFERROR(INDEX(JU_Tanggal,MATCH(A79&$J$2,JU_BB,0)),"")} | C79: {=IFERROR(INDEX(JU_REF,MATCH(A79&$J$2,JU_BB,0)),"")} | D79: {=IFERROR(INDEX(JU_Keterangan,MATCH(A79&$J$2,JU_BB,0)),"")} | E79: {=IFERROR(INDEX(JU_Debet,MATCH(A79&$J$2,JU_BB,0)),"")} | F79: {=IFERROR(INDEX(JU_Kredit,MATCH(A79&$J$2,JU_BB,0)),"")} | H79: =IF(B79="",0,1) -> 0
B80: {=IFERROR(INDEX(JU_Tanggal,MATCH(A80&$J$2,JU_BB,0)),"")} | C80: {=IFERROR(INDEX(JU_REF,MATCH(A80&$J$2,JU_BB,0)),"")} | D80: {=IFERROR(INDEX(JU_Keterangan,MATCH(A80&$J$2,JU_BB,0)),"")} | E80: {=IFERROR(INDEX(JU_Debet,MATCH(A80&$J$2,JU_BB,0)),"")} | F80: {=IFERROR(INDEX(JU_Kredit,MATCH(A80&$J$2,JU_BB,0)),"")} | H80: =IF(B80="",0,1) -> 0
B81: {=IFERROR(INDEX(JU_Tanggal,MATCH(A81&$J$2,JU_BB,0)),"")} | C81: {=IFERROR(INDEX(JU_REF,MATCH(A81&$J$2,JU_BB,0)),"")} | D81: {=IFERROR(INDEX(JU_Keterangan,MATCH(A81&$J$2,JU_BB,0)),"")} | E81: {=IFERROR(INDEX(JU_Debet,MATCH(A81&$J$2,JU_BB,0)),"")} | F81: {=IFERROR(INDEX(JU_Kredit,MATCH(A81&$J$2,JU_BB,0)),"")} | G81: =IFERROR(IF($H$4="Debet",#REF!+E81-F81,#REF!+F81-E81),"") | H81: =IF(B81="",0,1) -> 0
B82: {=IFERROR(INDEX(JU_Tanggal,MATCH(A82&$J$2,JU_BB,0)),"")} | C82: {=IFERROR(INDEX(JU_REF,MATCH(A82&$J$2,JU_BB,0)),"")} | D82: {=IFERROR(INDEX(JU_Keterangan,MATCH(A82&$J$2,JU_BB,0)),"")} | E82: {=IFERROR(INDEX(JU_Debet,MATCH(A82&$J$2,JU_BB,0)),"")} | F82: {=IFERROR(INDEX(JU_Kredit,MATCH(A82&$J$2,JU_BB,0)),"")} | H82: =IF(B82="",0,1) -> 0
B83: {=IFERROR(INDEX(JU_Tanggal,MATCH(A83&$J$2,JU_BB,0)),"")} | C83: {=IFERROR(INDEX(JU_REF,MATCH(A83&$J$2,JU_BB,0)),"")} | D83: {=IFERROR(INDEX(JU_Keterangan,MATCH(A83&$J$2,JU_BB,0)),"")} | E83: {=IFERROR(INDEX(JU_Debet,MATCH(A83&$J$2,JU_BB,0)),"")} | F83: {=IFERROR(INDEX(JU_Kredit,MATCH(A83&$J$2,JU_BB,0)),"")} | H83: =IF(B83="",0,1) -> 0
B84: {=IFERROR(INDEX(JU_Tanggal,MATCH(A84&$J$2,JU_BB,0)),"")} | C84: {=IFERROR(INDEX(JU_REF,MATCH(A84&$J$2,JU_BB,0)),"")} | D84: {=IFERROR(INDEX(JU_Keterangan,MATCH(A84&$J$2,JU_BB,0)),"")} | E84: {=IFERROR(INDEX(JU_Debet,MATCH(A84&$J$2,JU_BB,0)),"")} | F84: {=IFERROR(INDEX(JU_Kredit,MATCH(A84&$J$2,JU_BB,0)),"")} | H84: =IF(B84="",0,1) -> 0
B85: {=IFERROR(INDEX(JU_Tanggal,MATCH(A85&$J$2,JU_BB,0)),"")} | C85: {=IFERROR(INDEX(JU_REF,MATCH(A85&$J$2,JU_BB,0)),"")} | D85: {=IFERROR(INDEX(JU_Keterangan,MATCH(A85&$J$2,JU_BB,0)),"")} | E85: {=IFERROR(INDEX(JU_Debet,MATCH(A85&$J$2,JU_BB,0)),"")} | F85: {=IFERROR(INDEX(JU_Kredit,MATCH(A85&$J$2,JU_BB,0)),"")} | H85: =IF(B85="",0,1) -> 0
B86: {=IFERROR(INDEX(JU_Tanggal,MATCH(A86&$J$2,JU_BB,0)),"")} | C86: {=IFERROR(INDEX(JU_REF,MATCH(A86&$J$2,JU_BB,0)),"")} | D86: {=IFERROR(INDEX(JU_Keterangan,MATCH(A86&$J$2,JU_BB,0)),"")} | E86: {=IFERROR(INDEX(JU_Debet,MATCH(A86&$J$2,JU_BB,0)),"")} | F86: {=IFERROR(INDEX(JU_Kredit,MATCH(A86&$J$2,JU_BB,0)),"")} | H86: =IF(B86="",0,1) -> 0
B87: {=IFERROR(INDEX(JU_Tanggal,MATCH(A87&$J$2,JU_BB,0)),"")} | C87: {=IFERROR(INDEX(JU_REF,MATCH(A87&$J$2,JU_BB,0)),"")} | D87: {=IFERROR(INDEX(JU_Keterangan,MATCH(A87&$J$2,JU_BB,0)),"")} | E87: {=IFERROR(INDEX(JU_Debet,MATCH(A87&$J$2,JU_BB,0)),"")} | F87: {=IFERROR(INDEX(JU_Kredit,MATCH(A87&$J$2,JU_BB,0)),"")} | H87: =IF(B87="",0,1) -> 0
B88: {=IFERROR(INDEX(JU_Tanggal,MATCH(A88&$J$2,JU_BB,0)),"")} | C88: {=IFERROR(INDEX(JU_REF,MATCH(A88&$J$2,JU_BB,0)),"")} | D88: {=IFERROR(INDEX(JU_Keterangan,MATCH(A88&$J$2,JU_BB,0)),"")} | E88: {=IFERROR(INDEX(JU_Debet,MATCH(A88&$J$2,JU_BB,0)),"")} | F88: {=IFERROR(INDEX(JU_Kredit,MATCH(A88&$J$2,JU_BB,0)),"")} | H88: =IF(B88="",0,1) -> 0
B89: {=IFERROR(INDEX(JU_Tanggal,MATCH(A89&$J$2,JU_BB,0)),"")} | C89: {=IFERROR(INDEX(JU_REF,MATCH(A89&$J$2,JU_BB,0)),"")} | D89: {=IFERROR(INDEX(JU_Keterangan,MATCH(A89&$J$2,JU_BB,0)),"")} | E89: {=IFERROR(INDEX(JU_Debet,MATCH(A89&$J$2,JU_BB,0)),"")} | F89: {=IFERROR(INDEX(JU_Kredit,MATCH(A89&$J$2,JU_BB,0)),"")} | H89: =IF(B89="",0,1) -> 0
B90: {=IFERROR(INDEX(JU_Tanggal,MATCH(A90&$J$2,JU_BB,0)),"")} | C90: {=IFERROR(INDEX(JU_REF,MATCH(A90&$J$2,JU_BB,0)),"")} | D90: {=IFERROR(INDEX(JU_Keterangan,MATCH(A90&$J$2,JU_BB,0)),"")} | E90: {=IFERROR(INDEX(JU_Debet,MATCH(A90&$J$2,JU_BB,0)),"")} | F90: {=IFERROR(INDEX(JU_Kredit,MATCH(A90&$J$2,JU_BB,0)),"")} | H90: =IF(B90="",0,1) -> 0
H91: =IF(B91="",0,1) -> 0

Sheet NRL
B2: ='BUKU BESAR'!B2:F2 -> PT. TERANG GARAM SOLUSINDO
B3: NERACA LAJUR
B4: ='BUKU BESAR'!B4:F4 -> PERIODE
B6: KODE | C6: NAMA AKUN | E6: POS | F6: SN | G6: SALDO AWAL | I6: PERGERAKAN | K6: SALDO AKHIR | M6: LABA RUGI | O6: NERACA
G7: DEBET | H7: KREDIT | I7: DEBET | J7: KREDIT | K7: DEBET | L7: Kredit | M7: DEBET | N7: KREDIT | O7: DEBET | P7: KREDIT
B8: =IF(COA!B5="","",COA!B5) -> 1101 | C8: =IFERROR(INDEX(Nama_Akun,MATCH(B8,KODEAKUN,0)),"") -> Kas | D8: {=IFERROR(INDEX(Type,MATCH(B8,KODEAKUN,0)),"")} -> Kas | E8: {=INDEX(Posisi,MATCH(D8,Type,0))} -> Neraca | F8: {=IFERROR(INDEX(SaldoNormal,MATCH(D8,Type,)),"")} -> Debet | G8: {=IFERROR(INDEX(COA_DEBET,MATCH(B8,KODEAKUN,0)),"")} -> 0 | H8: {=IFERROR(INDEX(COA_KREDIT,MATCH(B8,KODEAKUN,0)),"")} -> 0 | I8: =IF(B8="","",SUMIF(JU_Kodeakun,B8,JU_Debet)) -> 0 | J8: =IF(B8="","",SUMIF(JU_Kodeakun,B8,JU_Kredit)) -> 0 | K8: =IF(F8="Debet",G8+I8-H8-J8,0) -> 0 | L8: =IF(F8="Kredit",H8+J8-G8-I8,0) -> 0 | M8: =IF(E8="Laba Rugi",K8,0) -> 0 | N8: =IF(E8="Laba Rugi",L8,0) -> 0 | O8: =IF(E8="Neraca",K8,0) -> 0 | P8: =IF(E8="Neraca",L8,0) -> 0 | R8: FILTER
B9: =IF(COA!B6="","",COA!B6) -> 1102 | C9: {=IFERROR(INDEX(Nama_Akun,MATCH(B9,KODEAKUN,0)),"")} -> Kas Di Bank | D9: {=IFERROR(INDEX(Type,MATCH(B9,KODEAKUN,0)),"")} -> Kas Di Bank | E9: {=INDEX(Posisi,MATCH(D9,Type,0))} -> Neraca | F9: {=IFERROR(INDEX(SaldoNormal,MATCH(D9,Type,)),"")} -> Debet | G9: {=IFERROR(INDEX(COA_DEBET,MATCH(B9,KODEAKUN,0)),"")} -> 0 | H9: {=IFERROR(INDEX(COA_KREDIT,MATCH(B9,KODEAKUN,0)),"")} -> 0 | I9: =IF(B9="","",SUMIF(JU_Kodeakun,B9,JU_Debet)) -> 0 | J9: =IF(B9="","",SUMIF(JU_Kodeakun,B9,JU_Kredit)) -> 0 | K9: =IF(F9="Debet",G9+I9-H9-J9,0) -> 0 | L9: =IF(F9="Kredit",H9+J9-G9-I9,0) -> 0 | M9: =IF(E9="Laba Rugi",K9,0) -> 0 | N9: =IF(E9="Laba Rugi",L9,0) -> 0 | O9: =IF(E9="Neraca",K9,0) -> 0 | P9: =IF(E9="Neraca",L9,0) -> 0 | R9: =IF(AND(G9=0,H9=0,I9=0,J9=0,K9=0,L9=0,M9=0,N9=0,O9=0,P9=0),0,1) -> 0
B10: =IF(COA!B7="","",COA!B7) -> 1103 | C10: {=IFERROR(INDEX(Nama_Akun,MATCH(B10,KODEAKUN,0)),"")} -> Petty Cash | D10: {=IFERROR(INDEX(Type,MATCH(B10,KODEAKUN,0)),"")} -> Petty Cash | E10: {=INDEX(Posisi,MATCH(D10,Type,0))} -> Neraca | F10: {=IFERROR(INDEX(SaldoNormal,MATCH(D10,Type,)),"")} -> Debet | G10: {=IFERROR(INDEX(COA_DEBET,MATCH(B10,KODEAKUN,0)),"")} -> 0 | H10: {=IFERROR(INDEX(COA_KREDIT,MATCH(B10,KODEAKUN,0)),"")} -> 0 | I10: =IF(B10="","",SUMIF(JU_Kodeakun,B10,JU_Debet)) -> 0 | J10: =IF(B10="","",SUMIF(JU_Kodeakun,B10,JU_Kredit)) -> 0 | K10: =IF(F10="Debet",G10+I10-H10-J10,0) -> 0 | L10: =IF(F10="Kredit",H10+J10-G10-I10,0) -> 0 | M10: =IF(E10="Laba Rugi",K10,0) -> 0 | N10: =IF(E10="Laba Rugi",L10,0) -> 0 | O10: =IF(E10="Neraca",K10,0) -> 0 | P10: =IF(E10="Neraca",L10,0) -> 0 | R10: =IF(AND(G10=0,H10=0,I10=0,J10=0,K10=0,L10=0,M10=0,N10=0,O10=0,P10=0),0,1) -> 0
B11: =IF(COA!B8="","",COA!B8) -> 1104 | C11: {=IFERROR(INDEX(Nama_Akun,MATCH(B11,KODEAKUN,0)),"")} -> Piutang | D11: {=IFERROR(INDEX(Type,MATCH(B11,KODEAKUN,0)),"")} -> Piutang | E11: {=INDEX(Posisi,MATCH(D11,Type,0))} -> Neraca | F11: {=IFERROR(INDEX(SaldoNormal,MATCH(D11,Type,)),"")} -> Debet | G11: {=IFERROR(INDEX(COA_DEBET,MATCH(B11,KODEAKUN,0)),"")} -> 0 | H11: {=IFERROR(INDEX(COA_KREDIT,MATCH(B11,KODEAKUN,0)),"")} -> 0 | I11: =IF(B11="","",SUMIF(JU_Kodeakun,B11,JU_Debet)) -> 0 | J11: =IF(B11="","",SUMIF(JU_Kodeakun,B11,JU_Kredit)) -> 0 | K11: =IF(F11="Debet",G11+I11-H11-J11,0) -> 0 | L11: =IF(F11="Kredit",H11+J11-G11-I11,0) -> 0 | M11: =IF(E11="Laba Rugi",K11,0) -> 0 | N11: =IF(E11="Laba Rugi",L11,0) -> 0 | O11: =IF(E11="Neraca",K11,0) -> 0 | P11: =IF(E11="Neraca",L11,0) -> 0 | R11: =IF(AND(G12=0,H12=0,I12=0,J12=0,K12=0,L12=0,M12=0,N12=0,O12=0,P12=0),0,1) -> 0
B12: =IF(COA!B9="","",COA!B9) -> 1105 | C12: {=IFERROR(INDEX(Nama_Akun,MATCH(B12,KODEAKUN,0)),"")} -> Persediaan | D12: {=IFERROR(INDEX(Type,MATCH(B12,KODEAKUN,0)),"")} -> Persediaan | E12: {=INDEX(Posisi,MATCH(D12,Type,0))} -> Neraca | F12: {=IFERROR(INDEX(SaldoNormal,MATCH(D12,Type,)),"")} -> Debet | G12: {=IFERROR(INDEX(COA_DEBET,MATCH(B12,KODEAKUN,0)),"")} -> 0 | H12: {=IFERROR(INDEX(COA_KREDIT,MATCH(B12,KODEAKUN,0)),"")} -> 0 | I12: =IF(B12="","",SUMIF(JU_Kodeakun,B12,JU_Debet)) -> 0 | J12: =IF(B12="","",SUMIF(JU_Kodeakun,B12,JU_Kredit)) -> 0 | K12: =IF(F12="Debet",G12+I12-H12-J12,0) -> 0 | L12: =IF(F12="Kredit",H12+J12-G12-I12,0) -> 0 | M12: =IF(E12="Laba Rugi",K12,0) -> 0 | N12: =IF(E12="Laba Rugi",L12,0) -> 0 | O12: =IF(E12="Neraca",K12,0) -> 0 | P12: =IF(E12="Neraca",L12,0) -> 0 | R12: =IF(AND(G13=0,H13=0,I13=0,J13=0,K13=0,L13=0,M13=0,N13=0,O13=0,P13=0),0,1) -> 0
B13: =IF(COA!B10="","",COA!B10) -> 1106 | C13: {=IFERROR(INDEX(Nama_Akun,MATCH(B13,KODEAKUN,0)),"")} -> Perlengkapan | D13: {=IFERROR(INDEX(Type,MATCH(B13,KODEAKUN,0)),"")} -> Perlengkapan | E13: {=INDEX(Posisi,MATCH(D13,Type,0))} -> Neraca | F13: {=IFERROR(INDEX(SaldoNormal,MATCH(D13,Type,)),"")} -> Debet | G13: {=IFERROR(INDEX(COA_DEBET,MATCH(B13,KODEAKUN,0)),"")} -> 0 | H13: {=IFERROR(INDEX(COA_KREDIT,MATCH(B13,KODEAKUN,0)),"")} -> 0 | I13: =IF(B13="","",SUMIF(JU_Kodeakun,B13,JU_Debet)) -> 0 | J13: =IF(B13="","",SUMIF(JU_Kodeakun,B13,JU_Kredit)) -> 0 | K13: =IF(F13="Debet",G13+I13-H13-J13,0) -> 0 | L13: =IF(F13="Kredit",H13+J13-G13-I13,0) -> 0 | M13: =IF(E13="Laba Rugi",K13,0) -> 0 | N13: =IF(E13="Laba Rugi",L13,0) -> 0 | O13: =IF(E13="Neraca",K13,0) -> 0 | P13: =IF(E13="Neraca",L13,0) -> 0 | R13: =IF(AND(G14=0,H14=0,I14=0,J14=0,K14=0,L14=0,M14=0,N14=0,O14=0,P14=0),0,1) -> 1
B14: =IF(COA!B11="","",COA!B11) -> 1201 | C14: {=IFERROR(INDEX(Nama_Akun,MATCH(B14,KODEAKUN,0)),"")} -> Peralatan | D14: {=IFERROR(INDEX(Type,MATCH(B14,KODEAKUN,0)),"")} -> Peralatan | E14: {=INDEX(Posisi,MATCH(D14,Type,0))} -> Neraca | F14: {=IFERROR(INDEX(SaldoNormal,MATCH(D14,Type,)),"")} -> Debet | G14: {=IFERROR(INDEX(COA_DEBET,MATCH(B14,KODEAKUN,0)),"")} -> 0 | H14: {=IFERROR(INDEX(COA_KREDIT,MATCH(B14,KODEAKUN,0)),"")} -> 0 | I14: =IF(B14="","",SUMIF(JU_Kodeakun,B14,JU_Debet)) -> 0 | J14: =IF(B14="","",SUMIF(JU_Kodeakun,B14,JU_Kredit)) -> 515685 | K14: =IF(F14="Debet",G14+I14-H14-J14,0) -> -515685 | L14: =IF(F14="Kredit",H14+J14-G14-I14,0) -> 0 | M14: =IF(E14="Laba Rugi",K14,0) -> 0 | N14: =IF(E14="Laba Rugi",L14,0) -> 0 | O14: =IF(E14="Neraca",K14,0) -> -515685 | P14: =IF(E14="Neraca",L14,0) -> 0 | R14: =IF(AND(G15=0,H15=0,I15=0,J15=0,K15=0,L15=0,M15=0,N15=0,O15=0,P15=0),0,1) -> 0
B15: =IF(COA!B12="","",COA!B12) -> 1202 | C15: {=IFERROR(INDEX(Nama_Akun,MATCH(B15,KODEAKUN,0)),"")} -> Akumulasi Penyusutan Peralatan | D15: {=IFERROR(INDEX(Type,MATCH(B15,KODEAKUN,0)),"")} -> Akumulasi Penyusutan Peralatan | E15: {=INDEX(Posisi,MATCH(D15,Type,0))} -> Neraca | F15: {=IFERROR(INDEX(SaldoNormal,MATCH(D15,Type,)),"")} -> Kredit | G15: {=IFERROR(INDEX(COA_DEBET,MATCH(B15,KODEAKUN,0)),"")} -> 0 | H15: {=IFERROR(INDEX(COA_KREDIT,MATCH(B15,KODEAKUN,0)),"")} -> 0 | I15: =IF(B15="","",SUMIF(JU_Kodeakun,B15,JU_Debet)) -> 0 | J15: =IF(B15="","",SUMIF(JU_Kodeakun,B15,JU_Kredit)) -> 0 | K15: =IF(F15="Debet",G15+I15-H15-J15,0) -> 0 | L15: =IF(F15="Kredit",H15+J15-G15-I15,0) -> 0 | M15: =IF(E15="Laba Rugi",K15,0) -> 0 | N15: =IF(E15="Laba Rugi",L15,0) -> 0 | O15: =IF(E15="Neraca",K15,0) -> 0 | P15: =IF(E15="Neraca",L15,0) -> 0 | R15: =IF(AND(G16=0,H16=0,I16=0,J16=0,K16=0,L16=0,M16=0,N16=0,O16=0,P16=0),0,1) -> 0
B16: =IF(COA!B13="","",COA!B13) -> 2110 | C16: {=IFERROR(INDEX(Nama_Akun,MATCH(B16,KODEAKUN,0)),"")} -> Utang | D16: {=IFERROR(INDEX(Type,MATCH(B16,KODEAKUN,0)),"")} -> Utang | E16: {=INDEX(Posisi,MATCH(D16,Type,0))} -> Neraca | F16: {=IFERROR(INDEX(SaldoNormal,MATCH(D16,Type,)),"")} -> Kredit | G16: {=IFERROR(INDEX(COA_DEBET,MATCH(B16,KODEAKUN,0)),"")} -> 0 | H16: {=IFERROR(INDEX(COA_KREDIT,MATCH(B16,KODEAKUN,0)),"")} -> 0 | I16: =IF(B16="","",SUMIF(JU_Kodeakun,B16,JU_Debet)) -> 0 | J16: =IF(B16="","",SUMIF(JU_Kodeakun,B16,JU_Kredit)) -> 0 | K16: =IF(F16="Debet",G16+I16-H16-J16,0) -> 0 | L16: =IF(F16="Kredit",H16+J16-G16-I16,0) -> 0 | M16: =IF(E16="Laba Rugi",K16,0) -> 0 | N16: =IF(E16="Laba Rugi",L16,0) -> 0 | O16: =IF(E16="Neraca",K16,0) -> 0 | P16: =IF(E16="Neraca",L16,0) -> 0 | R16: =IF(AND(G17=0,H17=0,I17=0,J17=0,K17=0,L17=0,M17=0,N17=0,O17=0,P17=0),0,1) -> 1
B17: =IF(COA!B14="","",COA!B14) -> 2120 | C17: {=IFERROR(INDEX(Nama_Akun,MATCH(B17,KODEAKUN,0)),"")} -> Utang Gaji | D17: {=IFERROR(INDEX(Type,MATCH(B17,KODEAKUN,0)),"")} -> Utang Gaji | E17: {=INDEX(Posisi,MATCH(D17,Type,0))} -> Neraca | F17: {=IFERROR(INDEX(SaldoNormal,MATCH(D17,Type,)),"")} -> Kredit | G17: {=IFERROR(INDEX(COA_DEBET,MATCH(B17,KODEAKUN,0)),"")} -> 0 | H17: {=IFERROR(INDEX(COA_KREDIT,MATCH(B17,KODEAKUN,0)),"")} -> 0 | I17: =IF(B17="","",SUMIF(JU_Kodeakun,B17,JU_Debet)) -> 0 | J17: =IF(B17="","",SUMIF(JU_Kodeakun,B17,JU_Kredit)) -> 105901167 | K17: =IF(F17="Debet",G17+I17-H17-J17,0) -> 0 | L17: =IF(F17="Kredit",H17+J17-G17-I17,0) -> 105901167 | M17: =IF(E17="Laba Rugi",K17,0) -> 0 | N17: =IF(E17="Laba Rugi",L17,0) -> 0 | O17: =IF(E17="Neraca",K17,0) -> 0 | P17: =IF(E17="Neraca",L17,0) -> 105901167 | R17: =IF(AND(G18=0,H18=0,I18=0,J18=0,K18=0,L18=0,M18=0,N18=0,O18=0,P18=0),0,1) -> 0
B18: =IF(COA!B15="","",COA!B15) -> 2130 | C18: {=IFERROR(INDEX(Nama_Akun,MATCH(B18,KODEAKUN,0)),"")} -> utang pajak | D18: {=IFERROR(INDEX(Type,MATCH(B18,KODEAKUN,0)),"")} -> utang pajak | E18: {=INDEX(Posisi,MATCH(D18,Type,0))} -> Neraca | F18: {=IFERROR(INDEX(SaldoNormal,MATCH(D18,Type,)),"")} -> Kredit | G18: {=IFERROR(INDEX(COA_DEBET,MATCH(B18,KODEAKUN,0)),"")} -> 0 | H18: {=IFERROR(INDEX(COA_KREDIT,MATCH(B18,KODEAKUN,0)),"")} -> 0 | I18: =IF(B18="","",SUMIF(JU_Kodeakun,B18,JU_Debet)) -> 0 | J18: =IF(B18="","",SUMIF(JU_Kodeakun,B18,JU_Kredit)) -> 0 | K18: =IF(F18="Debet",G18+I18-H18-J18,0) -> 0 | L18: =IF(F18="Kredit",H18+J18-G18-I18,0) -> 0 | M18: =IF(E18="Laba Rugi",K18,0) -> 0 | N18: =IF(E18="Laba Rugi",L18,0) -> 0 | O18: =IF(E18="Neraca",K18,0) -> 0 | P18: =IF(E18="Neraca",L18,0) -> 0 | R18: =IF(AND(G19=0,H19=0,I19=0,J19=0,K19=0,L19=0,M19=0,N19=0,O19=0,P19=0),0,1) -> 0
B19: =IF(COA!B16="","",COA!B16) -> 2140 | C19: {=IFERROR(INDEX(Nama_Akun,MATCH(B19,KODEAKUN,0)),"")} -> utang pdam | D19: {=IFERROR(INDEX(Type,MATCH(B19,KODEAKUN,0)),"")} -> utang pdam | E19: {=INDEX(Posisi,MATCH(D19,Type,0))} -> Neraca | F19: {=IFERROR(INDEX(SaldoNormal,MATCH(D19,Type,)),"")} -> Kredit | G19: {=IFERROR(INDEX(COA_DEBET,MATCH(B19,KODEAKUN,0)),"")} -> 0 | H19: {=IFERROR(INDEX(COA_KREDIT,MATCH(B19,KODEAKUN,0)),"")} -> 0 | I19: =IF(B19="","",SUMIF(JU_Kodeakun,B19,JU_Debet)) -> 0 | J19: =IF(B19="","",SUMIF(JU_Kodeakun,B19,JU_Kredit)) -> 0 | K19: =IF(F19="Debet",G19+I19-H19-J19,0) -> 0 | L19: =IF(F19="Kredit",H19+J19-G19-I19,0) -> 0 | M19: =IF(E19="Laba Rugi",K19,0) -> 0 | N19: =IF(E19="Laba Rugi",L19,0) -> 0 | O19: =IF(E19="Neraca",K19,0) -> 0 | P19: =IF(E19="Neraca",L19,0) -> 0 | R19: =IF(AND(G20=0,H20=0,I20=0,J20=0,K20=0,L20=0,M20=0,N20=0,O20=0,P20=0),0,1) -> 0
B20: =IF(COA!B17="","",COA!B17) -> 2150 | C20: {=IFERROR(INDEX(Nama_Akun,MATCH(B20,KODEAKUN,0)),"")} -> utang jne | D20: {=IFERROR(INDEX(Type,MATCH(B20,KODEAKUN,0)),"")} -> utang jne | E20: {=INDEX(Posisi,MATCH(D20,Type,0))} -> Neraca | F20: {=IFERROR(INDEX(SaldoNormal,MATCH(D20,Type,)),"")} -> Kredit | G20: {=IFERROR(INDEX(COA_DEBET,MATCH(B20,KODEAKUN,0)),"")} -> 0 | H20: {=IFERROR(INDEX(COA_KREDIT,MATCH(B20,KODEAKUN,0)),"")} -> 0 | I20: =IF(B20="","",SUMIF(JU_Kodeakun,B20,JU_Debet)) -> 0 | J20: =IF(B20="","",SUMIF(JU_Kodeakun,B20,JU_Kredit)) -> 0 | K20: =IF(F20="Debet",G20+I20-H20-J20,0) -> 0 | L20: =IF(F20="Kredit",H20+J20-G20-I20,0) -> 0 | M20: =IF(E20="Laba Rugi",K20,0) -> 0 | N20: =IF(E20="Laba Rugi",L20,0) -> 0 | O20: =IF(E20="Neraca",K20,0) -> 0 | P20: =IF(E20="Neraca",L20,0) -> 0 | R20: =IF(AND(G25=0,H25=0,I25=0,J25=0,K25=0,L25=0,M25=0,N25=0,O25=0,P25=0),0,1) -> 1
B21: =IF(COA!B18="","",COA!B18) -> 2160 | C21: {=IFERROR(INDEX(Nama_Akun,MATCH(B21,KODEAKUN,0)),"")} -> utang pcp | D21: {=IFERROR(INDEX(Type,MATCH(B21,KODEAKUN,0)),"")} -> utang pcp | E21: {=INDEX(Posisi,MATCH(D21,Type,0))} -> Neraca | F21: {=IFERROR(INDEX(SaldoNormal,MATCH(D21,Type,)),"")} -> Kredit | G21: {=IFERROR(INDEX(COA_DEBET,MATCH(B21,KODEAKUN,0)),"")} -> 0 | H21: {=IFERROR(INDEX(COA_KREDIT,MATCH(B21,KODEAKUN,0)),"")} -> 0 | I21: =IF(B21="","",SUMIF(JU_Kodeakun,B21,JU_Debet)) -> 0 | J21: =IF(B21="","",SUMIF(JU_Kodeakun,B21,JU_Kredit)) -> 0 | K21: =IF(F21="Debet",G21+I21-H21-J21,0) -> 0 | L21: =IF(F21="Kredit",H21+J21-G21-I21,0) -> 0 | M21: =IF(E21="Laba Rugi",K21,0) -> 0 | N21: =IF(E21="Laba Rugi",L21,0) -> 0 | O21: =IF(E21="Neraca",K21,0) -> 0 | P21: =IF(E21="Neraca",L21,0) -> 0 | R21: =IF(AND(G26=0,H26=0,I26=0,J26=0,K26=0,L26=0,M26=0,N26=0,O26=0,P26=0),0,1) -> 0
B22: =IF(COA!B19="","",COA!B19) -> 3100 | C22: {=IFERROR(INDEX(Nama_Akun,MATCH(B22,KODEAKUN,0)),"")} -> Modal | D22: {=IFERROR(INDEX(Type,MATCH(B22,KODEAKUN,0)),"")} -> Modal | E22: {=INDEX(Posisi,MATCH(D22,Type,0))} -> Neraca | F22: {=IFERROR(INDEX(SaldoNormal,MATCH(D22,Type,)),"")} -> Kredit | G22: {=IFERROR(INDEX(COA_DEBET,MATCH(B22,KODEAKUN,0)),"")} -> 0 | H22: {=IFERROR(INDEX(COA_KREDIT,MATCH(B22,KODEAKUN,0)),"")} -> 0 | I22: =IF(B22="","",SUMIF(JU_Kodeakun,B22,JU_Debet)) -> 0 | J22: =IF(B22="","",SUMIF(JU_Kodeakun,B22,JU_Kredit)) -> 0 | K22: =IF(F22="Debet",G22+I22-H22-J22,0) -> 0 | L22: =IF(F22="Kredit",H22+J22-G22-I22,0) -> 0 | M22: =IF(E22="Laba Rugi",K22,0) -> 0 | N22: =IF(E22="Laba Rugi",L22,0) -> 0 | O22: =IF(E22="Neraca",K22,0) -> 0 | P22: =IF(E22="Neraca",L22,0) -> 0 | R22: =IF(AND(G27=0,H27=0,I27=0,J27=0,K27=0,L27=0,M27=0,N27=0,O27=0,P27=0),0,1) -> 1
B23: =IF(COA!B20="","",COA!B20) -> 3110 | C23: {=IFERROR(INDEX(Nama_Akun,MATCH(B23,KODEAKUN,0)),"")} -> Iktisar laba rugi | D23: {=IFERROR(INDEX(Type,MATCH(B23,KODEAKUN,0)),"")} -> Iktisar laba rugi | E23: {=INDEX(Posisi,MATCH(D23,Type,0))} -> Neraca | F23: {=IFERROR(INDEX(SaldoNormal,MATCH(D23,Type,)),"")} -> Kredit | G23: {=IFERROR(INDEX(COA_DEBET,MATCH(B23,KODEAKUN,0)),"")} -> 0 | H23: {=IFERROR(INDEX(COA_KREDIT,MATCH(B23,KODEAKUN,0)),"")} -> 0 | I23: =IF(B23="","",SUMIF(JU_Kodeakun,B23,JU_Debet)) -> 0 | J23: =IF(B23="","",SUMIF(JU_Kodeakun,B23,JU_Kredit)) -> 0 | K23: =IF(F23="Debet",G23+I23-H23-J23,0) -> 0 | L23: =IF(F23="Kredit",H23+J23-G23-I23,0) -> 0 | M23: =IF(E23="Laba Rugi",K23,0) -> 0 | N23: =IF(E23="Laba Rugi",L23,0) -> 0 | O23: =IF(E23="Neraca",K23,0) -> 0 | P23: =IF(E23="Neraca",L23,0) -> 0 | R23: =IF(AND(G28=0,H28=0,I28=0,J28=0,K28=0,L28=0,M28=0,N28=0,O28=0,P28=0),0,1) -> 1
B24: =IF(COA!B21="","",COA!B21) -> 4110 | C24: {=IFERROR(INDEX(Nama_Akun,MATCH(B24,KODEAKUN,0)),"")} -> Pendapatan jasa | D24: {=IFERROR(INDEX(Type,MATCH(B24,KODEAKUN,0)),"")} -> Pendapatan jasa | E24: {=INDEX(Posisi,MATCH(D24,Type,0))} -> Laba Rugi | F24: {=IFERROR(INDEX(SaldoNormal,MATCH(D24,Type,)),"")} -> Kredit | G24: {=IFERROR(INDEX(COA_DEBET,MATCH(B24,KODEAKUN,0)),"")} -> 0 | H24: {=IFERROR(INDEX(COA_KREDIT,MATCH(B24,KODEAKUN,0)),"")} -> 0 | I24: =IF(B24="","",SUMIF(JU_Kodeakun,B24,JU_Debet)) -> 124642329 | J24: =IF(B24="","",SUMIF(JU_Kodeakun,B24,JU_Kredit)) -> 0 | K24: =IF(F24="Debet",G24+I24-H24-J24,0) -> 0 | L24: =IF(F24="Kredit",H24+J24-G24-I24,0) -> -124642329 | M24: =IF(E24="Laba Rugi",K24,0) -> 0 | N24: =IF(E24="Laba Rugi",L24,0) -> -124642329 | O24: =IF(E24="Neraca",K24,0) -> 0 | P24: =IF(E24="Neraca",L24,0) -> 0 | R24: =IF(AND(G29=0,H29=0,I29=0,J29=0,K29=0,L29=0,M29=0,N29=0,O29=0,P29=0),0,1) -> 0
B25: =IF(COA!B22="","",COA!B22) -> 4120 | C25: {=IFERROR(INDEX(Nama_Akun,MATCH(B25,KODEAKUN,0)),"")} -> pendapatan shoepolice | D25: {=IFERROR(INDEX(Type,MATCH(B25,KODEAKUN,0)),"")} -> pendapatan shoepolice | E25: {=INDEX(Posisi,MATCH(D25,Type,0))} -> Laba Rugi | F25: {=IFERROR(INDEX(SaldoNormal,MATCH(D25,Type,)),"")} -> Kredit | G25: {=IFERROR(INDEX(COA_DEBET,MATCH(B25,KODEAKUN,0)),"")} -> 0 | H25: {=IFERROR(INDEX(COA_KREDIT,MATCH(B25,KODEAKUN,0)),"")} -> 0 | I25: =IF(B25="","",SUMIF(JU_Kodeakun,B25,JU_Debet)) -> 2000000 | J25: =IF(B25="","",SUMIF(JU_Kodeakun,B25,JU_Kredit)) -> 0 | K25: =IF(F25="Debet",G25+I25-H25-J25,0) -> 0 | L25: =IF(F25="Kredit",H25+J25-G25-I25,0) -> -2000000 | M25: =IF(E25="Laba Rugi",K25,0) -> 0 | N25: =IF(E25="Laba Rugi",L25,0) -> -2000000 | O25: =IF(E25="Neraca",K25,0) -> 0 | P25: =IF(E25="Neraca",L25,0) -> 0 | R25: =IF(AND(G30=0,H30=0,I30=0,J30=0,K30=0,L30=0,M30=0,N30=0,O30=0,P30=0),0,1) -> 1
B26: =IF(COA!B23="","",COA!B23) -> 4130 | C26: {=IFERROR(INDEX(Nama_Akun,MATCH(B26,KODEAKUN,0)),"")} -> pendapatan affiliate | D26: {=IFERROR(INDEX(Type,MATCH(B26,KODEAKUN,0)),"")} -> pendapatan affiliate | E26: {=INDEX(Posisi,MATCH(D26,Type,0))} -> Laba Rugi | F26: {=IFERROR(INDEX(SaldoNormal,MATCH(D26,Type,)),"")} -> Kredit | G26: {=IFERROR(INDEX(COA_DEBET,MATCH(B26,KODEAKUN,0)),"")} -> 0 | H26: {=IFERROR(INDEX(COA_KREDIT,MATCH(B26,KODEAKUN,0)),"")} -> 0 | I26: =IF(B26="","",SUMIF(JU_Kodeakun,B26,JU_Debet)) -> 0 | J26: =IF(B26="","",SUMIF(JU_Kodeakun,B26,JU_Kredit)) -> 0 | K26: =IF(F26="Debet",G26+I26-H26-J26,0) -> 0 | L26: =IF(F26="Kredit",H26+J26-G26-I26,0) -> 0 | M26: =IF(E26="Laba Rugi",K26,0) -> 0 | N26: =IF(E26="Laba Rugi",L26,0) -> 0 | O26: =IF(E26="Neraca",K26,0) -> 0 | P26: =IF(E26="Neraca",L26,0) -> 0 | R26: =IF(AND(G31=0,H31=0,I31=0,J31=0,K31=0,L31=0,M31=0,N31=0,O31=0,P31=0),0,1) -> 1
B27: =IF(COA!B24="","",COA!B24) -> 4140 | C27: {=IFERROR(INDEX(Nama_Akun,MATCH(B27,KODEAKUN,0)),"")} -> pendapatan jasa eiger | D27: {=IFERROR(INDEX(Type,MATCH(B27,KODEAKUN,0)),"")} -> pendapatan jasa eiger | E27: {=INDEX(Posisi,MATCH(D27,Type,0))} -> Laba Rugi | F27: {=IFERROR(INDEX(SaldoNormal,MATCH(D27,Type,)),"")} -> Kredit | G27: {=IFERROR(INDEX(COA_DEBET,MATCH(B27,KODEAKUN,0)),"")} -> 0 | H27: {=IFERROR(INDEX(COA_KREDIT,MATCH(B27,KODEAKUN,0)),"")} -> 0 | I27: =IF(B27="","",SUMIF(JU_Kodeakun,B27,JU_Debet)) -> 1663000 | J27: =IF(B27="","",SUMIF(JU_Kodeakun,B27,JU_Kredit)) -> 0 | K27: =IF(F27="Debet",G27+I27-H27-J27,0) -> 0 | L27: =IF(F27="Kredit",H27+J27-G27-I27,0) -> -1663000 | M27: =IF(E27="Laba Rugi",K27,0) -> 0 | N27: =IF(E27="Laba Rugi",L27,0) -> -1663000 | O27: =IF(E27="Neraca",K27,0) -> 0 | P27: =IF(E27="Neraca",L27,0) -> 0 | R27: =IF(AND(G32=0,H32=0,I32=0,J32=0,K32=0,L32=0,M32=0,N32=0,O32=0,P32=0),0,1) -> 1
B28: =IF(COA!B25="","",COA!B25) -> 7010 | C28: {=IFERROR(INDEX(Nama_Akun,MATCH(B28,KODEAKUN,0)),"")} -> pendapatan lain-lain | D28: {=IFERROR(INDEX(Type,MATCH(B28,KODEAKUN,0)),"")} -> pendapatan lain-lain | E28: {=INDEX(Posisi,MATCH(D28,Type,0))} -> Laba Rugi | F28: {=IFERROR(INDEX(SaldoNormal,MATCH(D28,Type,)),"")} -> Kredit | G28: {=IFERROR(INDEX(COA_DEBET,MATCH(B28,KODEAKUN,0)),"")} -> 0 | H28: {=IFERROR(INDEX(COA_KREDIT,MATCH(B28,KODEAKUN,0)),"")} -> 0 | I28: =IF(B28="","",SUMIF(JU_Kodeakun,B28,JU_Debet)) -> 349000 | J28: =IF(B28="","",SUMIF(JU_Kodeakun,B28,JU_Kredit)) -> 0 | K28: =IF(F28="Debet",G28+I28-H28-J28,0) -> 0 | L28: =IF(F28="Kredit",H28+J28-G28-I28,0) -> -349000 | M28: =IF(E28="Laba Rugi",K28,0) -> 0 | N28: =IF(E28="Laba Rugi",L28,0) -> -349000 | O28: =IF(E28="Neraca",K28,0) -> 0 | P28: =IF(E28="Neraca",L28,0) -> 0 | R28: =IF(AND(G33=0,H33=0,I33=0,J33=0,K33=0,L33=0,M33=0,N33=0,O33=0,P33=0),0,1) -> 1
B29: =IF(COA!B26="","",COA!B26) -> 4160 | C29: {=IFERROR(INDEX(Nama_Akun,MATCH(B29,KODEAKUN,0)),"")} -> pendapatan ongkir | D29: {=IFERROR(INDEX(Type,MATCH(B29,KODEAKUN,0)),"")} -> pendapatan ongkir | E29: {=INDEX(Posisi,MATCH(D29,Type,0))} -> Laba Rugi | F29: {=IFERROR(INDEX(SaldoNormal,MATCH(D29,Type,)),"")} -> Kredit | G29: {=IFERROR(INDEX(COA_DEBET,MATCH(B29,KODEAKUN,0)),"")} -> 0 | H29: {=IFERROR(INDEX(COA_KREDIT,MATCH(B29,KODEAKUN,0)),"")} -> 0 | I29: =IF(B29="","",SUMIF(JU_Kodeakun,B29,JU_Debet)) -> 0 | J29: =IF(B29="","",SUMIF(JU_Kodeakun,B29,JU_Kredit)) -> 0 | K29: =IF(F29="Debet",G29+I29-H29-J29,0) -> 0 | L29: =IF(F29="Kredit",H29+J29-G29-I29,0) -> 0 | M29: =IF(E29="Laba Rugi",K29,0) -> 0 | N29: =IF(E29="Laba Rugi",L29,0) -> 0 | O29: =IF(E29="Neraca",K29,0) -> 0 | P29: =IF(E29="Neraca",L29,0) -> 0 | R29: =IF(AND(G34=0,H34=0,I34=0,J34=0,K34=0,L34=0,M34=0,N34=0,O34=0,P34=0),0,1) -> 1
B30: =IF(COA!B27="","",COA!B27) -> 4170 | C30: {=IFERROR(INDEX(Nama_Akun,MATCH(B30,KODEAKUN,0)),"")} -> Retur & Refund | D30: {=IFERROR(INDEX(Type,MATCH(B30,KODEAKUN,0)),"")} -> Retur & Refund | E30: {=INDEX(Posisi,MATCH(D30,Type,0))} -> Laba Rugi | F30: {=IFERROR(INDEX(SaldoNormal,MATCH(D30,Type,)),"")} -> Debet | G30: {=IFERROR(INDEX(COA_DEBET,MATCH(B30,KODEAKUN,0)),"")} -> 0 | H30: {=IFERROR(INDEX(COA_KREDIT,MATCH(B30,KODEAKUN,0)),"")} -> 0 | I30: =IF(B30="","",SUMIF(JU_Kodeakun,B30,JU_Debet)) -> 0 | J30: =IF(B30="","",SUMIF(JU_Kodeakun,B30,JU_Kredit)) -> 150000 | K30: =IF(F30="Debet",G30+I30-H30-J30,0) -> -150000 | L30: =IF(F30="Kredit",H30+J30-G30-I30,0) -> 0 | M30: =IF(E30="Laba Rugi",K30,0) -> -150000 | N30: =IF(E30="Laba Rugi",L30,0) -> 0 | O30: =IF(E30="Neraca",K30,0) -> 0 | P30: =IF(E30="Neraca",L30,0) -> 0 | R30: =IF(AND(G35=0,H35=0,I35=0,J35=0,K35=0,L35=0,M35=0,N35=0,O35=0,P35=0),0,1) -> 0
B31: =IF(COA!B28="","",COA!B28) -> 5010 | C31: {=IFERROR(INDEX(Nama_Akun,MATCH(B31,KODEAKUN,0)),"")} -> Hpp sole | D31: {=IFERROR(INDEX(Type,MATCH(B31,KODEAKUN,0)),"")} -> Hpp sole | E31: {=INDEX(Posisi,MATCH(D31,Type,0))} -> Laba Rugi | F31: {=IFERROR(INDEX(SaldoNormal,MATCH(D31,Type,)),"")} -> Debet | G31: {=IFERROR(INDEX(COA_DEBET,MATCH(B31,KODEAKUN,0)),"")} -> 0 | H31: {=IFERROR(INDEX(COA_KREDIT,MATCH(B31,KODEAKUN,0)),"")} -> 0 | I31: =IF(B31="","",SUMIF(JU_Kodeakun,B31,JU_Debet)) -> 0 | J31: =IF(B31="","",SUMIF(JU_Kodeakun,B31,JU_Kredit)) -> 6006717 | K31: =IF(F31="Debet",G31+I31-H31-J31,0) -> -6006717 | L31: =IF(F31="Kredit",H31+J31-G31-I31,0) -> 0 | M31: =IF(E31="Laba Rugi",K31,0) -> -6006717 | N31: =IF(E31="Laba Rugi",L31,0) -> 0 | O31: =IF(E31="Neraca",K31,0) -> 0 | P31: =IF(E31="Neraca",L31,0) -> 0 | R31: =IF(AND(G36=0,H36=0,I36=0,J36=0,K36=0,L36=0,M36=0,N36=0,O36=0,P36=0),0,1) -> 0
... B34: =IF(COA!B31="","",COA!B31) -> 5040 | C34: {=IFERROR(INDEX(Nama_Akun,MATCH(B34,KODEAKUN,0)),"")} -> Hpp Vibram | D34: {=IFERROR(INDEX(Type,MATCH(B34,KODEAKUN,0)),"")} -> Hpp Vibram | E34: {=INDEX(Posisi,MATCH(D34,Type,0))} -> Laba Rugi | F34: {=IFERROR(INDEX(SaldoNormal,MATCH(D34,Type,)),"")} -> Debet | G34: {=IFERROR(INDEX(COA_DEBET,MATCH(B34,KODEAKUN,0)),"")} -> 0 | H34: {=IFERROR(INDEX(COA_KREDIT,MATCH(B34,KODEAKUN,0)),"")} -> 0 | I34: =IF(B34="","",SUMIF(JU_Kodeakun,B34,JU_Debet)) -> 0 | J34: =IF(B34="","",SUMIF(JU_Kodeakun,B34,JU_Kredit)) -> 497000 | K34: =IF(F34="Debet",G34+I34-H34-J34,0) -> -497000 | L34: =IF(F34="Kredit",H34+J34-G34-I34,0) -> 0 | M34: =IF(E34="Laba Rugi",K34,0) -> -497000 | N34: =IF(E34="Laba Rugi",L34,0) -> 0 | O34: =IF(E34="Neraca",K34,0) -> 0 | P34: =IF(E34="Neraca",L34,0) -> 0 | R34: =IF(AND(G39=0,H39=0,I39=0,J39=0,K39=0,L39=0,M39=0,N39=0,O39=0,P39=0),0,1) -> 1
B35: =IF(COA!B32="","",COA!B32) -> 5050 | C35: {=IFERROR(INDEX(Nama_Akun,MATCH(B35,KODEAKUN,0)),"")} -> Hpp repaint | G35: {=IFERROR(INDEX(COA_DEBET,MATCH(B35,KODEAKUN,0)),"")} -> 0 | H35: {=IFERROR(INDEX(COA_KREDIT,MATCH(B35,KODEAKUN,0)),"")} -> 0 | I35: =IF(B35="","",SUMIF(JU_Kodeakun,B35,JU_Debet)) -> 0 | J35: =IF(B35="","",SUMIF(JU_Kodeakun,B35,JU_Kredit)) -> 0 | K35: =IF(F35="Debet",G35+I35-H35-J35,0) -> 0 | L35: =IF(F35="Kredit",H35+J35-G35-I35,0) -> 0 | M35: =IF(E35="Laba Rugi",K35,0) -> 0 | N35: =IF(E35="Laba Rugi",L35,0) -> 0 | O35: =IF(E35="Neraca",K35,0) -> 0 | P35: =IF(E35="Neraca",L35,0) -> 0 | R35: =IF(AND(G40=0,H40=0,I40=0,J40=0,K40=0,L40=0,M40=0,N40=0,O40=0,P40=0),0,1) -> 0
B36: =IF(COA!B33="","",COA!B33) -> 5060 | C36: {=IFERROR(INDEX(Nama_Akun,MATCH(B36,KODEAKUN,0)),"")} -> Hpp general | G36: {=IFERROR(INDEX(COA_DEBET,MATCH(B36,KODEAKUN,0)),"")} -> 0 | H36: {=IFERROR(INDEX(COA_KREDIT,MATCH(B36,KODEAKUN,0)),"")} -> 0 | I36: =IF(B36="","",SUMIF(JU_Kodeakun,B36,JU_Debet)) -> 0 | J36: =IF(B36="","",SUMIF(JU_Kodeakun,B36,JU_Kredit)) -> 0 | K36: =IF(F36="Debet",G36+I36-H36-J36,0) -> 0 | L36: =IF(F36="Kredit",H36+J36-G36-I36,0) -> 0 | M36: =IF(E36="Laba Rugi",K36,0) -> 0 | N36: =IF(E36="Laba Rugi",L36,0) -> 0 | O36: =IF(E36="Neraca",K36,0) -> 0 | P36: =IF(E36="Neraca",L36,0) -> 0 | R36: =IF(AND(G41=0,H41=0,I41=0,J41=0,K41=0,L41=0,M41=0,N41=0,O41=0,P41=0),0,1) -> 0
B37: =IF(COA!B34="","",COA!B34) -> 5070 | C37: {=IFERROR(INDEX(Nama_Akun,MATCH(B37,KODEAKUN,0)),"")} -> Hpp Aksesoris | G37: {=IFERROR(INDEX(COA_DEBET,MATCH(B37,KODEAKUN,0)),"")} -> 0 | H37: {=IFERROR(INDEX(COA_KREDIT,MATCH(B37,KODEAKUN,0)),"")} -> 0 | I37: =IF(B37="","",SUMIF(JU_Kodeakun,B37,JU_Debet)) -> 0 | J37: =IF(B37="","",SUMIF(JU_Kodeakun,B37,JU_Kredit)) -> 50000 | K37: =IF(F37="Debet",G37+I37-H37-J37,0) -> 0 | L37: =IF(F37="Kredit",H37+J37-G37-I37,0) -> 0 | M37: =IF(E37="Laba Rugi",K37,0) -> 0 | N37: =IF(E37="Laba Rugi",L37,0) -> 0 | O37: =IF(E37="Neraca",K37,0) -> 0 | P37: =IF(E37="Neraca",L37,0) -> 0 | R37: =IF(AND(G42=0,H42=0,I42=0,J42=0,K42=0,L42=0,M42=0,N42=0,O42=0,P42=0),0,1) -> 0
B38: =IF(COA!B35="","",COA!B35) -> 5101 | C38: {=IFERROR(INDEX(Nama_Akun,MATCH(B38,KODEAKUN,0)),"")} -> Beban Gaji shoepolice | G38: {=IFERROR(INDEX(COA_DEBET,MATCH(B38,KODEAKUN,0)),"")} -> 0 | H38: {=IFERROR(INDEX(COA_KREDIT,MATCH(B38,KODEAKUN,0)),"")} -> 0 | I38: =IF(B38="","",SUMIF(JU_Kodeakun,B38,JU_Debet)) -> 0 | J38: =IF(B38="","",SUMIF(JU_Kodeakun,B38,JU_Kredit)) -> 0 | K38: =IF(F38="Debet",G38+I38-H38-J38,0) -> 0 | L38: =IF(F38="Kredit",H38+J38-G38-I38,0) -> 0 | M38: =IF(E38="Laba Rugi",K38,0) -> 0 | N38: =IF(E38="Laba Rugi",L38,0) -> 0 | O38: =IF(E38="Neraca",K38,0) -> 0 | P38: =IF(E38="Neraca",L38,0) -> 0 | R38: =IF(AND(G43=0,H43=0,I43=0,J43=0,K43=0,L43=0,M43=0,N43=0,O43=0,P43=0),0,1) -> 0
B39: =IF(COA!B36="","",COA!B36) -> 5102 | C39: {=IFERROR(INDEX(Nama_Akun,MATCH(B39,KODEAKUN,0)),"")} -> Beban Gaji Workshop | G39: {=IFERROR(INDEX(COA_DEBET,MATCH(B39,KODEAKUN,0)),"")} -> 0 | H39: {=IFERROR(INDEX(COA_KREDIT,MATCH(B39,KODEAKUN,0)),"")} -> 0 | I39: =IF(B39="","",SUMIF(JU_Kodeakun,B39,JU_Debet)) -> 0 | J39: =IF(B39="","",SUMIF(JU_Kodeakun,B39,JU_Kredit)) -> 500000 | K39: =IF(F39="Debet",G39+I39-H39-J39,0) -> 0 | L39: =IF(F39="Kredit",H39+J39-G39-I39,0) -> 0 | M39: =IF(E39="Laba Rugi",K39,0) -> 0 | N39: =IF(E39="Laba Rugi",L39,0) -> 0 | O39: =IF(E39="Neraca",K39,0) -> 0 | P39: =IF(E39="Neraca",L39,0) -> 0 | R39: =IF(AND(G44=0,H44=0,I44=0,J44=0,K44=0,L44=0,M44=0,N44=0,O44=0,P44=0),0,1) -> 1
B40: =IF(COA!B37="","",COA!B37) -> 5103 | C40: {=IFERROR(INDEX(Nama_Akun,MATCH(B40,KODEAKUN,0)),"")} -> Beban Gaji CS | G40: {=IFERROR(INDEX(COA_DEBET,MATCH(B40,KODEAKUN,0)),"")} -> 0 | H40: {=IFERROR(INDEX(COA_KREDIT,MATCH(B40,KODEAKUN,0)),"")} -> 0 | I40: =IF(B40="","",SUMIF(JU_Kodeakun,B40,JU_Debet)) -> 0 | J40: =IF(B40="","",SUMIF(JU_Kodeakun,B40,JU_Kredit)) -> 0 | K40: =IF(F40="Debet",G40+I40-H40-J40,0) -> 0 | L40: =IF(F40="Kredit",H40+J40-G40-I40,0) -> 0 | M40: =IF(E40="Laba Rugi",K40,0) -> 0 | N40: =IF(E40="Laba Rugi",L40,0) -> 0 | O40: =IF(E40="Neraca",K40,0) -> 0 | P40: =IF(E40="Neraca",L40,0) -> 0 | R40: =IF(AND(G45=0,H45=0,I45=0,J45=0,K45=0,L45=0,M45=0,N45=0,O45=0,P45=0),0,1) -> 1
B41: =IF(COA!B38="","",COA!B38) -> 5104 | C41: {=IFERROR(INDEX(Nama_Akun,MATCH(B41,KODEAKUN,0)),"")} -> Beban Gaji Finance | G41: {=IFERROR(INDEX(COA_DEBET,MATCH(B41,KODEAKUN,0)),"")} -> 0 | H41: {=IFERROR(INDEX(COA_KREDIT,MATCH(B41,KODEAKUN,0)),"")} -> 0 | I41: =IF(B41="","",SUMIF(JU_Kodeakun,B41,JU_Debet)) -> 0 | J41: =IF(B41="","",SUMIF(JU_Kodeakun,B41,JU_Kredit)) -> 0 | K41: =IF(F41="Debet",G41+I41-H41-J41,0) -> 0 | L41: =IF(F41="Kredit",H41+J41-G41-I41,0) -> 0 | M41: =IF(E41="Laba Rugi",K41,0) -> 0 | N41: =IF(E41="Laba Rugi",L41,0) -> 0 | O41: =IF(E41="Neraca",K41,0) -> 0 | P41: =IF(E41="Neraca",L41,0) -> 0 | R41: =IF(AND(G46=0,H46=0,I46=0,J46=0,K46=0,L46=0,M46=0,N46=0,O46=0,P46=0),0,1) -> 0
B42: =IF(COA!B39="","",COA!B39) -> 5105 | C42: {=IFERROR(INDEX(Nama_Akun,MATCH(B42,KODEAKUN,0)),"")} -> Beban Gaji CC | G42: {=IFERROR(INDEX(COA_DEBET,MATCH(B42,KODEAKUN,0)),"")} -> 0 | H42: {=IFERROR(INDEX(COA_KREDIT,MATCH(B42,KODEAKUN,0)),"")} -> 0 | I42: =IF(B42="","",SUMIF(JU_Kodeakun,B42,JU_Debet)) -> 0 | J42: =IF(B42="","",SUMIF(JU_Kodeakun,B42,JU_Kredit)) -> 0 | K42: =IF(F42="Debet",G42+I42-H42-J42,0) -> 0 | L42: =IF(F42="Kredit",H42+J42-G42-I42,0) -> 0 | M42: =IF(E42="Laba Rugi",K42,0) -> 0 | N42: =IF(E42="Laba Rugi",L42,0) -> 0 | O42: =IF(E42="Neraca",K42,0) -> 0 | P42: =IF(E42="Neraca",L42,0) -> 0 | R42: =IF(AND(G47=0,H47=0,I47=0,J47=0,K47=0,L47=0,M47=0,N47=0,O47=0,P47=0),0,1) -> 0
B43: =IF(COA!B40="","",COA!B40) -> 5106 | C43: {=IFERROR(INDEX(Nama_Akun,MATCH(B43,KODEAKUN,0)),"")} -> Beban Gaji Data analisis | G43: {=IFERROR(INDEX(COA_DEBET,MATCH(B43,KODEAKUN,0)),"")} -> 0 | H43: {=IFERROR(INDEX(COA_KREDIT,MATCH(B43,KODEAKUN,0)),"")} -> 0 | I43: =IF(B43="","",SUMIF(JU_Kodeakun,B43,JU_Debet)) -> 0 | J43: =IF(B43="","",SUMIF(JU_Kodeakun,B43,JU_Kredit)) -> 0 | K43: =IF(F43="Debet",G43+I43-H43-J43,0) -> 0 | L43: =IF(F43="Kredit",H43+J43-G43-I43,0) -> 0 | M43: =IF(E43="Laba Rugi",K43,0) -> 0 | N43: =IF(E43="Laba Rugi",L43,0) -> 0 | O43: =IF(E43="Neraca",K43,0) -> 0 | P43: =IF(E43="Neraca",L43,0) -> 0 | R43: =IF(AND(G48=0,H48=0,I48=0,J48=0,K48=0,L48=0,M48=0,N48=0,O48=0,P48=0),0,1) -> 0
B44: =IF(COA!B41="","",COA!B41) -> 5107 | C44: {=IFERROR(INDEX(Nama_Akun,MATCH(B44,KODEAKUN,0)),"")} -> Beban Gaji Gudang | G44: {=IFERROR(INDEX(COA_DEBET,MATCH(B44,KODEAKUN,0)),"")} -> 0 | H44: {=IFERROR(INDEX(COA_KREDIT,MATCH(B44,KODEAKUN,0)),"")} -> 0 | I44: =IF(B44="","",SUMIF(JU_Kodeakun,B44,JU_Debet)) -> 0 | J44: =IF(B44="","",SUMIF(JU_Kodeakun,B44,JU_Kredit)) -> 583333 | K44: =IF(F44="Debet",G44+I44-H44-J44,0) -> 0 | L44: =IF(F44="Kredit",H44+J44-G44-I44,0) -> 0 | M44: =IF(E44="Laba Rugi",K44,0) -> 0 | N44: =IF(E44="Laba Rugi",L44,0) -> 0 | O44: =IF(E44="Neraca",K44,0) -> 0 | P44: =IF(E44="Neraca",L44,0) -> 0 | R44: =IF(AND(G49=0,H49=0,I49=0,J49=0,K49=0,L49=0,M49=0,N49=0,O49=0,P49=0),0,1) -> 1
B45: =IF(COA!B42="","",COA!B42) -> 5108 | C45: {=IFERROR(INDEX(Nama_Akun,MATCH(B45,KODEAKUN,0)),"")} -> Beban gaji tukang | G45: {=IFERROR(INDEX(COA_DEBET,MATCH(B45,KODEAKUN,0)),"")} -> 0 | H45: {=IFERROR(INDEX(COA_KREDIT,MATCH(B45,KODEAKUN,0)),"")} -> 0 | I45: =IF(B45="","",SUMIF(JU_Kodeakun,B45,JU_Debet)) -> 0 | J45: =IF(B45="","",SUMIF(JU_Kodeakun,B45,JU_Kredit)) -> 16453778 | K45: =IF(F45="Debet",G45+I45-H45-J45,0) -> 0 | L45: =IF(F45="Kredit",H45+J45-G45-I45,0) -> 0 | M45: =IF(E45="Laba Rugi",K45,0) -> 0 | N45: =IF(E45="Laba Rugi",L45,0) -> 0 | O45: =IF(E45="Neraca",K45,0) -> 0 | P45: =IF(E45="Neraca",L45,0) -> 0 | R45: =IF(AND(G50=0,H50=0,I50=0,J50=0,K50=0,L50=0,M50=0,N50=0,O50=0,P50=0),0,1) -> 1
B46: =IF(COA!B43="","",COA!B43) -> 5110 | C46: {=IFERROR(INDEX(Nama_Akun,MATCH(B46,KODEAKUN,0)),"")} -> Bonus CS | G46: {=IFERROR(INDEX(COA_DEBET,MATCH(B46,KODEAKUN,0)),"")} -> 0 | H46: {=IFERROR(INDEX(COA_KREDIT,MATCH(B46,KODEAKUN,0)),"")} -> 0 | I46: =IF(B46="","",SUMIF(JU_Kodeakun,B46,JU_Debet)) -> 0 | J46: =IF(B46="","",SUMIF(JU_Kodeakun,B46,JU_Kredit)) -> 0 | K46: =IF(F46="Debet",G46+I46-H46-J46,0) -> 0 | L46: =IF(F46="Kredit",H46+J46-G46-I46,0) -> 0 | M46: =IF(E46="Laba Rugi",K46,0) -> 0 | N46: =IF(E46="Laba Rugi",L46,0) -> 0 | O46: =IF(E46="Neraca",K46,0) -> 0 | P46: =IF(E46="Neraca",L46,0) -> 0 | R46: =IF(AND(G51=0,H51=0,I51=0,J51=0,K51=0,L51=0,M51=0,N51=0,O51=0,P51=0),0,1) -> 1
... B62: =IF(COA!B59="","",COA!B59) -> 5530 | C62: {=IFERROR(INDEX(Nama_Akun,MATCH(B62,KODEAKUN,0)),"")} -> Beban PDAM Office | G62: {=IFERROR(INDEX(COA_DEBET,MATCH(B62,KODEAKUN,0)),"")} -> 0 | H62: {=IFERROR(INDEX(COA_KREDIT,MATCH(B62,KODEAKUN,0)),"")} -> 0 | I62: =IF(B62="","",SUMIF(JU_Kodeakun,B62,JU_Debet)) -> 0 | J62: =IF(B62="","",SUMIF(JU_Kodeakun,B62,JU_Kredit)) -> 0 | K62: =IF(F62="Debet",G62+I62-H62-J62,0) -> 0 | L62: =IF(F62="Kredit",H62+J62-G62-I62,0) -> 0 | M62: =IF(E62="Laba Rugi",K62,0) -> 0 | N62: =IF(E62="Laba Rugi",L62,0) -> 0 | O62: =IF(E62="Neraca",K62,0) -> 0 | P62: =IF(E62="Neraca",L62,0) -> 0 | R62: =IF(AND(G67=0,H67=0,I67=0,J67=0,K67=0,L67=0,M67=0,N67=0,O67=0,P67=0),0,1) -> 1
B63: =IF(COA!B60="","",COA!B60) -> 5540 | C63: {=IFERROR(INDEX(Nama_Akun,MATCH(B63,KODEAKUN,0)),"")} -> Beban PDAM Workshop | G63: {=IFERROR(INDEX(COA_DEBET,MATCH(B63,KODEAKUN,0)),"")} | H63: {=IFERROR(INDEX(COA_KREDIT,MATCH(B63,KODEAKUN,0)),"")} | I63: =IF(B63="","",SUMIF(JU_Kodeakun,B63,JU_Debet)) -> 0 | J63: =IF(B63="","",SUMIF(JU_Kodeakun,B63,JU_Kredit)) -> 0 | K63: =IF(F63="Debet",G63+I63-H63-J63,0) -> 0 | L63: =IF(F63="Kredit",H63+J63-G63-I63,0) -> 0 | M63: =IF(E63="Laba Rugi",K63,0) -> 0 | N63: =IF(E63="Laba Rugi",L63,0) -> 0 | O63: =IF(E63="Neraca",K63,0) -> 0 | P63: =IF(E63="Neraca",L63,0) -> 0 | R63: =IF(AND(G148=0,H148=0,I148=0,J148=0,K148=0,L148=0,M148=0,N148=0,O148=0,P148=0),0,1) -> 0
B64: =IF(COA!B61="","",COA!B61) -> 5550 | C64: {=IFERROR(INDEX(Nama_Akun,MATCH(B64,KODEAKUN,0)),"")} -> Beban PDAM sortir | G64: {=IFERROR(INDEX(COA_DEBET,MATCH(B64,KODEAKUN,0)),"")} | H64: {=IFERROR(INDEX(COA_KREDIT,MATCH(B64,KODEAKUN,0)),"")} | I64: =IF(B64="","",SUMIF(JU_Kodeakun,B64,JU_Debet)) -> 0 | J64: =IF(B64="","",SUMIF(JU_Kodeakun,B64,JU_Kredit)) -> 0 | K64: =IF(F64="Debet",G64+I64-H64-J64,0) -> 0 | L64: =IF(F64="Kredit",H64+J64-G64-I64,0) -> 0 | M64: =IF(E64="Laba Rugi",K64,0) -> 0 | N64: =IF(E64="Laba Rugi",L64,0) -> 0 | O64: =IF(E64="Neraca",K64,0) -> 0 | P64: =IF(E64="Neraca",L64,0) -> 0 | R64: =IF(AND(G149=0,H149=0,I149=0,J149=0,K149=0,L149=0,M149=0,N149=0,O149=0,P149=0),0,1) -> 0
B65: =IF(COA!B62="","",COA!B62) -> 5560 | C65: {=IFERROR(INDEX(Nama_Akun,MATCH(B65,KODEAKUN,0)),"")} -> Beban Wifi Office | G65: {=IFERROR(INDEX(COA_DEBET,MATCH(B65,KODEAKUN,0)),"")} | H65: {=IFERROR(INDEX(COA_KREDIT,MATCH(B65,KODEAKUN,0)),"")} | I65: =IF(B65="","",SUMIF(JU_Kodeakun,B65,JU_Debet)) -> 0 | J65: =IF(B65="","",SUMIF(JU_Kodeakun,B65,JU_Kredit)) -> 0 | K65: =IF(F65="Debet",G65+I65-H65-J65,0) -> 0 | L65: =IF(F65="Kredit",H65+J65-G65-I65,0) -> 0 | M65: =IF(E65="Laba Rugi",K65,0) -> 0 | N65: =IF(E65="Laba Rugi",L65,0) -> 0 | O65: =IF(E65="Neraca",K65,0) -> 0 | P65: =IF(E65="Neraca",L65,0) -> 0 | R65: =IF(AND(G150=0,H150=0,I150=0,J150=0,K150=0,L150=0,M150=0,N150=0,O150=0,P150=0),0,1) -> 0
B66: =IF(COA!B63="","",COA!B63) -> 5570 | C66: {=IFERROR(INDEX(Nama_Akun,MATCH(B66,KODEAKUN,0)),"")} -> Beban Wifi Sortir | G66: {=IFERROR(INDEX(COA_DEBET,MATCH(B66,KODEAKUN,0)),"")} | H66: {=IFERROR(INDEX(COA_KREDIT,MATCH(B66,KODEAKUN,0)),"")} | I66: =IF(B66="","",SUMIF(JU_Kodeakun,B66,JU_Debet)) -> 0 | J66: =IF(B66="","",SUMIF(JU_Kodeakun,B66,JU_Kredit)) -> 2333000 | K66: =IF(F66="Debet",G66+I66-H66-J66,0) -> 0 | L66: =IF(F66="Kredit",H66+J66-G66-I66,0) -> 0 | M66: =IF(E66="Laba Rugi",K66,0) -> 0 | N66: =IF(E66="Laba Rugi",L66,0) -> 0 | O66: =IF(E66="Neraca",K66,0) -> 0 | P66: =IF(E66="Neraca",L66,0) -> 0 | R66: =IF(AND(G151=0,H151=0,I151=0,J151=0,K151=0,L151=0,M151=0,N151=0,O151=0,P151=0),0,1) -> 0
B67: =IF(COA!B64="","",COA!B64) -> 5580 | C67: {=IFERROR(INDEX(Nama_Akun,MATCH(B67,KODEAKUN,0)),"")} -> Beban Wifi Workshop | G67: {=IFERROR(INDEX(COA_DEBET,MATCH(B67,KODEAKUN,0)),"")} | H67: {=IFERROR(INDEX(COA_KREDIT,MATCH(B67,KODEAKUN,0)),"")} | I67: =IF(B67="","",SUMIF(JU_Kodeakun,B67,JU_Debet)) -> 0 | J67: =IF(B67="","",SUMIF(JU_Kodeakun,B67,JU_Kredit)) -> 0 | K67: =IF(F67="Debet",G67+I67-H67-J67,0) -> 0 | L67: =IF(F67="Kredit",H67+J67-G67-I67,0) -> 0 | M67: =IF(E67="Laba Rugi",K67,0) -> 0 | N67: =IF(E67="Laba Rugi",L67,0) -> 0 | O67: =IF(E67="Neraca",K67,0) -> 0 | P67: =IF(E67="Neraca",L67,0) -> 0 | R67: =IF(AND(G152=0,H152=0,I152=0,J152=0,K152=0,L152=0,M152=0,N152=0,O152=0,P152=0),0,1) -> 0
B68: =IF(COA!B65="","",COA!B65) -> 5600 | C68: {=IFERROR(INDEX(Nama_Akun,MATCH(B68,KODEAKUN,0)),"")} -> Sewa Tempat Office | G68: {=IFERROR(INDEX(COA_DEBET,MATCH(B68,KODEAKUN,0)),"")} | H68: {=IFERROR(INDEX(COA_KREDIT,MATCH(B68,KODEAKUN,0)),"")} | I68: =IF(B68="","",SUMIF(JU_Kodeakun,B68,JU_Debet)) -> 0 | J68: =IF(B68="","",SUMIF(JU_Kodeakun,B68,JU_Kredit)) -> 25000000 | K68: =IF(F68="Debet",G68+I68-H68-J68,0) -> 0 | L68: =IF(F68="Kredit",H68+J68-G68-I68,0) -> 0 | M68: =IF(E68="Laba Rugi",K68,0) -> 0 | N68: =IF(E68="Laba Rugi",L68,0) -> 0 | O68: =IF(E68="Neraca",K68,0) -> 0 | P68: =IF(E68="Neraca",L68,0) -> 0 | R68: =IF(AND(G153=0,H153=0,I153=0,J153=0,K153=0,L153=0,M153=0,N153=0,O153=0,P153=0),0,1) -> 0
B69: =IF(COA!B66="","",COA!B66) -> 5610 | C69: {=IFERROR(INDEX(Nama_Akun,MATCH(B69,KODEAKUN,0)),"")} -> Sewa Tempat sortir | G69: {=IFERROR(INDEX(COA_DEBET,MATCH(B69,KODEAKUN,0)),"")} | H69: {=IFERROR(INDEX(COA_KREDIT,MATCH(B69,KODEAKUN,0)),"")} | I69: =IF(B69="","",SUMIF(JU_Kodeakun,B69,JU_Debet)) -> 0 | J69: =IF(B69="","",SUMIF(JU_Kodeakun,B69,JU_Kredit)) -> 0 | K69: =IF(F69="Debet",G69+I69-H69-J69,0) -> 0 | L69: =IF(F69="Kredit",H69+J69-G69-I69,0) -> 0 | M69: =IF(E69="Laba Rugi",K69,0) -> 0 | N69: =IF(E69="Laba Rugi",L69,0) -> 0 | O69: =IF(E69="Neraca",K69,0) -> 0 | P69: =IF(E69="Neraca",L69,0) -> 0 | R69: =IF(AND(G154=0,H154=0,I154=0,J154=0,K154=0,L154=0,M154=0,N154=0,O154=0,P154=0),0,1) -> 0
B70: =IF(COA!B67="","",COA!B67) -> 5620 | C70: {=IFERROR(INDEX(Nama_Akun,MATCH(B70,KODEAKUN,0)),"")} -> sewa tempat shoepolice | G70: {=IFERROR(INDEX(COA_DEBET,MATCH(B70,KODEAKUN,0)),"")} | H70: {=IFERROR(INDEX(COA_KREDIT,MATCH(B70,KODEAKUN,0)),"")} | I70: =IF(B70="","",SUMIF(JU_Kodeakun,B70,JU_Debet)) -> 0 | J70: =IF(B70="","",SUMIF(JU_Kodeakun,B70,JU_Kredit)) -> 0 | K70: =IF(F70="Debet",G70+I70-H70-J70,0) -> 0 | L70: =IF(F70="Kredit",H70+J70-G70-I70,0) -> 0 | M70: =IF(E70="Laba Rugi",K70,0) -> 0 | N70: =IF(E70="Laba Rugi",L70,0) -> 0 | O70: =IF(E70="Neraca",K70,0) -> 0 | P70: =IF(E70="Neraca",L70,0) -> 0 | R70: =IF(AND(G155=0,H155=0,I155=0,J155=0,K155=0,L155=0,M155=0,N155=0,O155=0,P155=0),0,1) -> 0
B71: =IF(COA!B68="","",COA!B68) -> 5630 | C71: {=IFERROR(INDEX(Nama_Akun,MATCH(B71,KODEAKUN,0)),"")} -> Sewa Tempat Workshop | G71: {=IFERROR(INDEX(COA_DEBET,MATCH(B71,KODEAKUN,0)),"")} | H71: {=IFERROR(INDEX(COA_KREDIT,MATCH(B71,KODEAKUN,0)),"")} | I71: =IF(B71="","",SUMIF(JU_Kodeakun,B71,JU_Debet)) -> 0 | J71: =IF(B71="","",SUMIF(JU_Kodeakun,B71,JU_Kredit)) -> 2750000 | K71: =IF(F71="Debet",G71+I71-H71-J71,0) -> 0 | L71: =IF(F71="Kredit",H71+J71-G71-I71,0) -> 0 | M71: =IF(E71="Laba Rugi",K71,0) -> 0 | N71: =IF(E71="Laba Rugi",L71,0) -> 0 | O71: =IF(E71="Neraca",K71,0) -> 0 | P71: =IF(E71="Neraca",L71,0) -> 0 | R71: =IF(AND(G156=0,H156=0,I156=0,J156=0,K156=0,L156=0,M156=0,N156=0,O156=0,P156=0),0,1) -> 0
B72: =IF(COA!B69="","",COA!B69) -> 6000 | C72: {=IFERROR(INDEX(Nama_Akun,MATCH(B72,KODEAKUN,0)),"")} -> Beban Transport/ Bensin/ Parkir | G72: {=IFERROR(INDEX(COA_DEBET,MATCH(B72,KODEAKUN,0)),"")} | H72: {=IFERROR(INDEX(COA_KREDIT,MATCH(B72,KODEAKUN,0)),"")} | I72: =IF(B72="","",SUMIF(JU_Kodeakun,B72,JU_Debet)) -> 0 | J72: =IF(B72="","",SUMIF(JU_Kodeakun,B72,JU_Kredit)) -> 120000 | K72: =IF(F72="Debet",G72+I72-H72-J72,0) -> 0 | L72: =IF(F72="Kredit",H72+J72-G72-I72,0) -> 0 | M72: =IF(E72="Laba Rugi",K72,0) -> 0 | N72: =IF(E72="Laba Rugi",L72,0) -> 0 | O72: =IF(E72="Neraca",K72,0) -> 0 | P72: =IF(E72="Neraca",L72,0) -> 0 | R72: =IF(AND(G157=0,H157=0,I157=0,J157=0,K157=0,L157=0,M157=0,N157=0,O157=0,P157=0),0,1) -> 0
B73: =IF(COA!B70="","",COA!B70) -> 6010 | C73: {=IFERROR(INDEX(Nama_Akun,MATCH(B73,KODEAKUN,0)),"")} -> Beban Iuran Sampah & Keamanan | G73: {=IFERROR(INDEX(COA_DEBET,MATCH(B73,KODEAKUN,0)),"")} | H73: {=IFERROR(INDEX(COA_KREDIT,MATCH(B73,KODEAKUN,0)),"")} | I73: =IF(B73="","",SUMIF(JU_Kodeakun,B73,JU_Debet)) -> 0 | J73: =IF(B73="","",SUMIF(JU_Kodeakun,B73,JU_Kredit)) -> 0 | K73: =IF(F73="Debet",G73+I73-H73-J73,0) -> 0 | L73: =IF(F73="Kredit",H73+J73-G73-I73,0) -> 0 | M73: =IF(E73="Laba Rugi",K73,0) -> 0 | N73: =IF(E73="Laba Rugi",L73,0) -> 0 | O73: =IF(E73="Neraca",K73,0) -> 0 | P73: =IF(E73="Neraca",L73,0) -> 0 | R73: =IF(AND(G158=0,H158=0,I158=0,J158=0,K158=0,L158=0,M158=0,N158=0,O158=0,P158=0),0,1) -> 0
B74: =IF(COA!B71="","",COA!B71) -> 6020 | C74: {=IFERROR(INDEX(Nama_Akun,MATCH(B74,KODEAKUN,0)),"")} -> Beban Iuran RT, RW | G74: {=IFERROR(INDEX(COA_DEBET,MATCH(B74,KODEAKUN,0)),"")} | H74: {=IFERROR(INDEX(COA_KREDIT,MATCH(B74,KODEAKUN,0)),"")} | I74: =IF(B74="","",SUMIF(JU_Kodeakun,B74,JU_Debet)) -> 0 | J74: =IF(B74="","",SUMIF(JU_Kodeakun,B74,JU_Kredit)) -> 250000 | K74: =IF(F74="Debet",G74+I74-H74-J74,0) -> 0 | L74: =IF(F74="Kredit",H74+J74-G74-I74,0) -> 0 | M74: =IF(E74="Laba Rugi",K74,0) -> 0 | N74: =IF(E74="Laba Rugi",L74,0) -> 0 | O74: =IF(E74="Neraca",K74,0) -> 0 | P74: =IF(E74="Neraca",L74,0) -> 0 | R74: =IF(AND(G159=0,H159=0,I159=0,J159=0,K159=0,L159=0,M159=0,N159=0,O159=0,P159=0),0,1) -> 0
... B93: =IF(COA!B90="","",COA!B90) | C93: {=IFERROR(INDEX(Nama_Akun,MATCH(B93,KODEAKUN,0)),"")} | G93: {=IFERROR(INDEX(COA_DEBET,MATCH(B93,KODEAKUN,0)),"")} | H93: {=IFERROR(INDEX(COA_KREDIT,MATCH(B93,KODEAKUN,0)),"")} | I93: =IF(B93="","",SUMIF(JU_Kodeakun,B93,JU_Debet)) | J93: =IF(B93="","",SUMIF(JU_Kodeakun,B93,JU_Kredit)) | K93: =IF(F93="Debet",G93+I93-H93-J93,0) -> 0 | L93: =IF(F93="Kredit",H93+J93-G93-I93,0) -> 0 | M93: =IF(E93="Laba Rugi",K93,0) -> 0 | N93: =IF(E93="Laba Rugi",L93,0) -> 0 | O93: =IF(E93="Neraca",K93,0) -> 0 | P93: =IF(E93="Neraca",L93,0) -> 0 | R93: =IF(AND(G178=0,H178=0,I178=0,J178=0,K178=0,L178=0,M178=0,N178=0,O178=0,P178=0),0,1) -> 0
B94: =IF(COA!B91="","",COA!B91) | G94: {=IFERROR(INDEX(COA_DEBET,MATCH(B94,KODEAKUN,0)),"")} | H94: {=IFERROR(INDEX(COA_KREDIT,MATCH(B94,KODEAKUN,0)),"")} | I94: =IF(B94="","",SUMIF(JU_Kodeakun,B94,JU_Debet)) | J94: =IF(B94="","",SUMIF(JU_Kodeakun,B94,JU_Kredit)) | K94: =IF(F94="Debet",G94+I94-H94-J94,0) -> 0 | L94: =IF(F94="Kredit",H94+J94-G94-I94,0) -> 0 | M94: =IF(E94="Laba Rugi",K94,0) -> 0 | N94: =IF(E94="Laba Rugi",L94,0) -> 0 | O94: =IF(E94="Neraca",K94,0) -> 0 | P94: =IF(E94="Neraca",L94,0) -> 0 | R94: =IF(AND(G179=0,H179=0,I179=0,J179=0,K179=0,L179=0,M179=0,N179=0,O179=0,P179=0),0,1) -> 0
B95: =IF(COA!B92="","",COA!B92) | G95: {=IFERROR(INDEX(COA_DEBET,MATCH(B95,KODEAKUN,0)),"")} | H95: {=IFERROR(INDEX(COA_KREDIT,MATCH(B95,KODEAKUN,0)),"")} | I95: =IF(B95="","",SUMIF(JU_Kodeakun,B95,JU_Debet)) | J95: =IF(B95="","",SUMIF(JU_Kodeakun,B95,JU_Kredit)) | K95: =IF(F95="Debet",G95+I95-H95-J95,0) -> 0 | L95: =IF(F95="Kredit",H95+J95-G95-I95,0) -> 0 | M95: =IF(E95="Laba Rugi",K95,0) -> 0 | N95: =IF(E95="Laba Rugi",L95,0) -> 0 | O95: =IF(E95="Neraca",K95,0) -> 0 | P95: =IF(E95="Neraca",L95,0) -> 0 | R95: =IF(AND(G180=0,H180=0,I180=0,J180=0,K180=0,L180=0,M180=0,N180=0,O180=0,P180=0),0,1) -> 0
B96: =IF(COA!B93="","",COA!B93) | G96: {=IFERROR(INDEX(COA_DEBET,MATCH(B96,KODEAKUN,0)),"")} | H96: {=IFERROR(INDEX(COA_KREDIT,MATCH(B96,KODEAKUN,0)),"")} | I96: =IF(B96="","",SUMIF(JU_Kodeakun,B96,JU_Debet)) | J96: =IF(B96="","",SUMIF(JU_Kodeakun,B96,JU_Kredit)) | K96: =IF(F96="Debet",G96+I96-H96-J96,0) -> 0 | L96: =IF(F96="Kredit",H96+J96-G96-I96,0) -> 0 | M96: =IF(E96="Laba Rugi",K96,0) -> 0 | N96: =IF(E96="Laba Rugi",L96,0) -> 0 | O96: =IF(E96="Neraca",K96,0) -> 0 | P96: =IF(E96="Neraca",L96,0) -> 0 | R96: =IF(AND(G181=0,H181=0,I181=0,J181=0,K181=0,L181=0,M181=0,N181=0,O181=0,P181=0),0,1) -> 0
B97: =IF(COA!B94="","",COA!B94) | G97: {=IFERROR(INDEX(COA_DEBET,MATCH(B97,KODEAKUN,0)),"")} | H97: {=IFERROR(INDEX(COA_KREDIT,MATCH(B97,KODEAKUN,0)),"")} | I97: =IF(B97="","",SUMIF(JU_Kodeakun,B97,JU_Debet)) | J97: =IF(B97="","",SUMIF(JU_Kodeakun,B97,JU_Kredit)) | K97: =IF(F97="Debet",G97+I97-H97-J97,0) -> 0 | L97: =IF(F97="Kredit",H97+J97-G97-I97,0) -> 0 | M97: =IF(E97="Laba Rugi",K97,0) -> 0 | N97: =IF(E97="Laba Rugi",L97,0) -> 0 | O97: =IF(E97="Neraca",K97,0) -> 0 | P97: =IF(E97="Neraca",L97,0) -> 0 | R97: =IF(AND(G182=0,H182=0,I182=0,J182=0,K182=0,L182=0,M182=0,N182=0,O182=0,P182=0),0,1) -> 0
B98: =IF(COA!B95="","",COA!B95) | G98: {=IFERROR(INDEX(COA_DEBET,MATCH(B98,KODEAKUN,0)),"")} | H98: {=IFERROR(INDEX(COA_KREDIT,MATCH(B98,KODEAKUN,0)),"")} | I98: =IF(B98="","",SUMIF(JU_Kodeakun,B98,JU_Debet)) | J98: =IF(B98="","",SUMIF(JU_Kodeakun,B98,JU_Kredit)) | K98: =IF(F98="Debet",G98+I98-H98-J98,0) -> 0 | L98: =IF(F98="Kredit",H98+J98-G98-I98,0) -> 0 | M98: =IF(E98="Laba Rugi",K98,0) -> 0 | N98: =IF(E98="Laba Rugi",L98,0) -> 0 | O98: =IF(E98="Neraca",K98,0) -> 0 | P98: =IF(E98="Neraca",L98,0) -> 0 | R98: =IF(AND(G183=0,H183=0,I183=0,J183=0,K183=0,L183=0,M183=0,N183=0,O183=0,P183=0),0,1) -> 0
B99: =IF(COA!B96="","",COA!B96) | G99: {=IFERROR(INDEX(COA_DEBET,MATCH(B99,KODEAKUN,0)),"")} | H99: {=IFERROR(INDEX(COA_KREDIT,MATCH(B99,KODEAKUN,0)),"")} | I99: =IF(B99="","",SUMIF(JU_Kodeakun,B99,JU_Debet)) | J99: =IF(B99="","",SUMIF(JU_Kodeakun,B99,JU_Kredit)) | K99: =IF(F99="Debet",G99+I99-H99-J99,0) -> 0 | L99: =IF(F99="Kredit",H99+J99-G99-I99,0) -> 0 | M99: =IF(E99="Laba Rugi",K99,0) -> 0 | N99: =IF(E99="Laba Rugi",L99,0) -> 0 | O99: =IF(E99="Neraca",K99,0) -> 0 | P99: =IF(E99="Neraca",L99,0) -> 0 | R99: =IF(AND(G184=0,H184=0,I184=0,J184=0,K184=0,L184=0,M184=0,N184=0,O184=0,P184=0),0,1) -> 0
B100: =IF(COA!B97="","",COA!B97) | G100: {=IFERROR(INDEX(COA_DEBET,MATCH(B100,KODEAKUN,0)),"")} | H100: {=IFERROR(INDEX(COA_KREDIT,MATCH(B100,KODEAKUN,0)),"")} | I100: =IF(B100="","",SUMIF(JU_Kodeakun,B100,JU_Debet)) | J100: =IF(B100="","",SUMIF(JU_Kodeakun,B100,JU_Kredit)) | K100: =IF(F100="Debet",G100+I100-H100-J100,0) -> 0 | L100: =IF(F100="Kredit",H100+J100-G100-I100,0) -> 0 | M100: =IF(E100="Laba Rugi",K100,0) -> 0 | N100: =IF(E100="Laba Rugi",L100,0) -> 0 | O100: =IF(E100="Neraca",K100,0) -> 0 | P100: =IF(E100="Neraca",L100,0) -> 0 | R100: =IF(AND(G185=0,H185=0,I185=0,J185=0,K185=0,L185=0,M185=0,N185=0,O185=0,P185=0),0,1) -> 0
B101: =IF(COA!B98="","",COA!B98) | G101: {=IFERROR(INDEX(COA_DEBET,MATCH(B101,KODEAKUN,0)),"")} | H101: {=IFERROR(INDEX(COA_KREDIT,MATCH(B101,KODEAKUN,0)),"")} | I101: =IF(B101="","",SUMIF(JU_Kodeakun,B101,JU_Debet)) | J101: =IF(B101="","",SUMIF(JU_Kodeakun,B101,JU_Kredit)) | K101: =IF(F101="Debet",G101+I101-H101-J101,0) -> 0 | L101: =IF(F101="Kredit",H101+J101-G101-I101,0) -> 0 | M101: =IF(E101="Laba Rugi",K101,0) -> 0 | N101: =IF(E101="Laba Rugi",L101,0) -> 0 | O101: =IF(E101="Neraca",K101,0) -> 0 | P101: =IF(E101="Neraca",L101,0) -> 0 | R101: =IF(AND(G186=0,H186=0,I186=0,J186=0,K186=0,L186=0,M186=0,N186=0,O186=0,P186=0),0,1) -> 0
B102: =IF(COA!B99="","",COA!B99) | G102: {=IFERROR(INDEX(COA_DEBET,MATCH(B102,KODEAKUN,0)),"")} | H102: {=IFERROR(INDEX(COA_KREDIT,MATCH(B102,KODEAKUN,0)),"")} | I102: =IF(B102="","",SUMIF(JU_Kodeakun,B102,JU_Debet)) | J102: =IF(B102="","",SUMIF(JU_Kodeakun,B102,JU_Kredit)) | K102: =IF(F102="Debet",G102+I102-H102-J102,0) -> 0 | L102: =IF(F102="Kredit",H102+J102-G102-I102,0) -> 0 | M102: =IF(E102="Laba Rugi",K102,0) -> 0 | N102: =IF(E102="Laba Rugi",L102,0) -> 0 | O102: =IF(E102="Neraca",K102,0) -> 0 | P102: =IF(E102="Neraca",L102,0) -> 0 | R102: =IF(AND(G187=0,H187=0,I187=0,J187=0,K187=0,L187=0,M187=0,N187=0,O187=0,P187=0),0,1) -> 0
B103: =IF(COA!B100="","",COA!B100) | G103: {=IFERROR(INDEX(COA_DEBET,MATCH(B103,KODEAKUN,0)),"")} | H103: {=IFERROR(INDEX(COA_KREDIT,MATCH(B103,KODEAKUN,0)),"")} | I103: =IF(B103="","",SUMIF(JU_Kodeakun,B103,JU_Debet)) | J103: =IF(B103="","",SUMIF(JU_Kodeakun,B103,JU_Kredit)) | K103: =IF(F103="Debet",G103+I103-H103-J103,0) -> 0 | L103: =IF(F103="Kredit",H103+J103-G103-I103,0) -> 0 | M103: =IF(E103="Laba Rugi",K103,0) -> 0 | N103: =IF(E103="Laba Rugi",L103,0) -> 0 | O103: =IF(E103="Neraca",K103,0) -> 0 | P103: =IF(E103="Neraca",L103,0) -> 0 | R103: =IF(AND(G188=0,H188=0,I188=0,J188=0,K188=0,L188=0,M188=0,N188=0,O188=0,P188=0),0,1) -> 0
B104: =IF(COA!B101="","",COA!B101) | G104: {=IFERROR(INDEX(COA_DEBET,MATCH(B104,KODEAKUN,0)),"")} | H104: {=IFERROR(INDEX(COA_KREDIT,MATCH(B104,KODEAKUN,0)),"")} | I104: =IF(B104="","",SUMIF(JU_Kodeakun,B104,JU_Debet)) | J104: =IF(B104="","",SUMIF(JU_Kodeakun,B104,JU_Kredit)) | K104: =IF(F104="Debet",G104+I104-H104-J104,0) -> 0 | L104: =IF(F104="Kredit",H104+J104-G104-I104,0) -> 0 | M104: =IF(E104="Laba Rugi",K104,0) -> 0 | N104: =IF(E104="Laba Rugi",L104,0) -> 0 | O104: =IF(E104="Neraca",K104,0) -> 0 | P104: =IF(E104="Neraca",L104,0) -> 0 | R104: =IF(AND(G189=0,H189=0,I189=0,J189=0,K189=0,L189=0,M189=0,N189=0,O189=0,P189=0),0,1) -> 0
B105: =IF(COA!B102="","",COA!B102) | G105: {=IFERROR(INDEX(COA_DEBET,MATCH(B105,KODEAKUN,0)),"")} | H105: {=IFERROR(INDEX(COA_KREDIT,MATCH(B105,KODEAKUN,0)),"")} | I105: =IF(B105="","",SUMIF(JU_Kodeakun,B105,JU_Debet)) | J105: =IF(B105="","",SUMIF(JU_Kodeakun,B105,JU_Kredit)) | K105: =IF(F105="Debet",G105+I105-H105-J105,0) -> 0 | L105: =IF(F105="Kredit",H105+J105-G105-I105,0) -> 0 | M105: =IF(E105="Laba Rugi",K105,0) -> 0 | N105: =IF(E105="Laba Rugi",L105,0) -> 0 | O105: =IF(E105="Neraca",K105,0) -> 0 | P105: =IF(E105="Neraca",L105,0) -> 0 | R105: =IF(AND(G190=0,H190=0,I190=0,J190=0,K190=0,L190=0,M190=0,N190=0,O190=0,P190=0),0,1) -> 0
... B110: =IF(COA!B107="","",COA!B107) | G110: {=IFERROR(INDEX(COA_DEBET,MATCH(B110,KODEAKUN,0)),"")} | H110: {=IFERROR(INDEX(COA_KREDIT,MATCH(B110,KODEAKUN,0)),"")} | I110: =IF(B110="","",SUMIF(JU_Kodeakun,B110,JU_Debet)) | J110: =IF(B110="","",SUMIF(JU_Kodeakun,B110,JU_Kredit)) | K110: =IF(F110="Debet",G110+I110-H110-J110,0) -> 0 | L110: =IF(F110="Kredit",H110+J110-G110-I110,0) -> 0 | M110: =IF(E110="Laba Rugi",K110,0) -> 0 | N110: =IF(E110="Laba Rugi",L110,0) -> 0 | O110: =IF(E110="Neraca",K110,0) -> 0 | P110: =IF(E110="Neraca",L110,0) -> 0 | R110: =IF(AND(G195=0,H195=0,I195=0,J195=0,K195=0,L195=0,M195=0,N195=0,O195=0,P195=0),0,1) -> 0
B111: =IF(COA!B158="","",COA!B158) | G111: {=IFERROR(INDEX(COA_DEBET,MATCH(B111,KODEAKUN,0)),"")} | H111: {=IFERROR(INDEX(COA_KREDIT,MATCH(B111,KODEAKUN,0)),"")} | I111: =IF(B111="","",SUMIF(JU_Kodeakun,B111,JU_Debet)) | J111: =IF(B111="","",SUMIF(JU_Kodeakun,B111,JU_Kredit)) | K111: =IF(F111="Debet",G111+I111-H111-J111,0) -> 0 | L111: =IF(F111="Kredit",H111+J111-G111-I111,0) -> 0 | M111: =IF(E111="Laba Rugi",K111,0) -> 0 | N111: =IF(E111="Laba Rugi",L111,0) -> 0 | O111: =IF(E111="Neraca",K111,0) -> 0 | P111: =IF(E111="Neraca",L111,0) -> 0 | R111: =IF(AND(G196=0,H196=0,I196=0,J196=0,K196=0,L196=0,M196=0,N196=0,O196=0,P196=0),0,1) -> 0
B112: =IF(COA!B159="","",COA!B159) | G112: {=IFERROR(INDEX(COA_DEBET,MATCH(B112,KODEAKUN,0)),"")} | H112: {=IFERROR(INDEX(COA_KREDIT,MATCH(B112,KODEAKUN,0)),"")} | I112: =IF(B112="","",SUMIF(JU_Kodeakun,B112,JU_Debet)) | J112: =IF(B112="","",SUMIF(JU_Kodeakun,B112,JU_Kredit)) | K112: =IF(F112="Debet",G112+I112-H112-J112,0) -> 0 | L112: =IF(F112="Kredit",H112+J112-G112-I112,0) -> 0 | M112: =IF(E112="Laba Rugi",K112,0) -> 0 | N112: =IF(E112="Laba Rugi",L112,0) -> 0 | O112: =IF(E112="Neraca",K112,0) -> 0 | P112: =IF(E112="Neraca",L112,0) -> 0 | R112: =IF(AND(G197=0,H197=0,I197=0,J197=0,K197=0,L197=0,M197=0,N197=0,O197=0,P197=0),0,1) -> 0
B113: =IF(COA!B160="","",COA!B160) | G113: {=IFERROR(INDEX(COA_DEBET,MATCH(B113,KODEAKUN,0)),"")} | H113: {=IFERROR(INDEX(COA_KREDIT,MATCH(B113,KODEAKUN,0)),"")} | I113: =IF(B113="","",SUMIF(JU_Kodeakun,B113,JU_Debet)) | J113: =IF(B113="","",SUMIF(JU_Kodeakun,B113,JU_Kredit)) | K113: =IF(F113="Debet",G113+I113-H113-J113,0) -> 0 | L113: =IF(F113="Kredit",H113+J113-G113-I113,0) -> 0 | M113: =IF(E113="Laba Rugi",K113,0) -> 0 | N113: =IF(E113="Laba Rugi",L113,0) -> 0 | O113: =IF(E113="Neraca",K113,0) -> 0 | P113: =IF(E113="Neraca",L113,0) -> 0 | R113: =IF(AND(G198=0,H198=0,I198=0,J198=0,K198=0,L198=0,M198=0,N198=0,O198=0,P198=0),0,1) -> 0
B114: =IF(COA!B161="","",COA!B161) | G114: {=IFERROR(INDEX(COA_DEBET,MATCH(B114,KODEAKUN,0)),"")} | H114: {=IFERROR(INDEX(COA_KREDIT,MATCH(B114,KODEAKUN,0)),"")} | I114: =IF(B114="","",SUMIF(JU_Kodeakun,B114,JU_Debet)) | J114: =IF(B114="","",SUMIF(JU_Kodeakun,B114,JU_Kredit)) | K114: =IF(F114="Debet",G114+I114-H114-J114,0) -> 0 | L114: =IF(F114="Kredit",H114+J114-G114-I114,0) -> 0 | M114: =IF(E114="Laba Rugi",K114,0) -> 0 | N114: =IF(E114="Laba Rugi",L114,0) -> 0 | O114: =IF(E114="Neraca",K114,0) -> 0 | P114: =IF(E114="Neraca",L114,0) -> 0 | R114: =IF(AND(G199=0,H199=0,I199=0,J199=0,K199=0,L199=0,M199=0,N199=0,O199=0,P199=0),0,1) -> 0
B115: =IF(COA!B162="","",COA!B162) | C115: {=IFERROR(INDEX(Nama_Akun,MATCH(B115,KODEAKUN,0)),"")} | D115: {=IFERROR(INDEX(Type,MATCH(B115,KODEAKUN,0)),"")} | E115: {=INDEX(Posisi,MATCH(D115,Type,0))} -> #N/A | F115: {=IFERROR(INDEX(SaldoNormal,MATCH(D115,Type,)),"")} | G115: {=IFERROR(INDEX(COA_DEBET,MATCH(B115,KODEAKUN,0)),"")} | H115: {=IFERROR(INDEX(COA_KREDIT,MATCH(B115,KODEAKUN,0)),"")} | I115: =IF(B115="","",SUMIF(JU_Kodeakun,B115,JU_Debet)) | J115: =IF(B115="","",SUMIF(JU_Kodeakun,B115,JU_Kredit)) | K115: =IF(F115="Debet",G115+I115-H115-J115,0) -> 0 | L115: =IF(F115="Kredit",H115+J115-G115-I115,0) -> 0 | M115: =IF(E115="Laba Rugi",K115,0) -> #N/A | N115: =IF(E115="Laba Rugi",L115,0) -> #N/A | O115: =IF(E115="Neraca",K115,0) -> #N/A | P115: =IF(E115="Neraca",L115,0) -> #N/A | R115: =IF(AND(G120=0,H120=0,I120=0,J120=0,K120=0,L120=0,M120=0,N120=0,O120=0,P120=0),0,1) -> 0
B116: =IF(COA!B52="","",COA!B52) -> 5430 | C116: {=IFERROR(INDEX(Nama_Akun,MATCH(B116,KODEAKUN,0)),"")} -> server domainesia | F116: {=IFERROR(INDEX(SaldoNormal,MATCH(D116,Type,)),"")} | G116: {=IFERROR(INDEX(COA_DEBET,MATCH(B116,KODEAKUN,0)),"")} -> 0 | H116: {=IFERROR(INDEX(COA_KREDIT,MATCH(B116,KODEAKUN,0)),"")} -> 0 | M116: =IF(E116="Laba Rugi",K116,0) -> 0 | N116: =IF(E116="Laba Rugi",L116,0) -> 0 | O116: =IF(E116="Neraca",K116,0) -> 0 | P116: =IF(E116="Neraca",L116,0) -> 0 | R116: =IF(AND(G121=0,H121=0,I121=0,J121=0,K121=0,L121=0,M121=0,N121=0,O121=0,P121=0),0,1) -> 0
B117: =IF(COA!B53="","",COA!B53) -> 5440 | C117: {=IFERROR(INDEX(Nama_Akun,MATCH(B117,KODEAKUN,0)),"")} -> ADS | F117: {=IFERROR(INDEX(SaldoNormal,MATCH(D117,Type,)),"")} | M117: =IF(E117="Laba Rugi",K117,0) -> 0 | N117: =IF(E117="Laba Rugi",L117,0) -> 0 | O117: =IF(E117="Neraca",K117,0) -> 0 | P117: =IF(E117="Neraca",L117,0) -> 0 | R117: =IF(AND(G122=0,H122=0,I122=0,J122=0,K122=0,L122=0,M122=0,N122=0,O122=0,P122=0),0,1) -> 0
B118: =IF(COA!B54="","",COA!B54) -> 5450 | F118: {=IFERROR(INDEX(SaldoNormal,MATCH(D118,Type,)),"")} | M118: =IF(E118="Laba Rugi",K118,0) -> 0 | N118: =IF(E118="Laba Rugi",L118,0) -> 0 | O118: =IF(E118="Neraca",K118,0) -> 0 | P118: =IF(E118="Neraca",L118,0) -> 0 | R118: =IF(AND(G123=0,H123=0,I123=0,J123=0,K123=0,L123=0,M123=0,N123=0,O123=0,P123=0),0,1) -> 0
B119: =IF(COA!B55="","",COA!B55) -> 5460 | F119: {=IFERROR(INDEX(SaldoNormal,MATCH(D119,Type,)),"")} | M119: =IF(E119="Laba Rugi",K119,0) -> 0 | N119: =IF(E119="Laba Rugi",L119,0) -> 0 | O119: =IF(E119="Neraca",K119,0) -> 0 | P119: =IF(E119="Neraca",L119,0) -> 0 | R119: =IF(AND(G124=0,H124=0,I124=0,J124=0,K124=0,L124=0,M124=0,N124=0,O124=0,P124=0),0,1) -> 0
B120: =IF(COA!B56="","",COA!B56) -> 5500 | F120: {=IFERROR(INDEX(SaldoNormal,MATCH(D120,Type,)),"")} | M120: =IF(E120="Laba Rugi",K120,0) -> 0 | N120: =IF(E120="Laba Rugi",L120,0) -> 0 | O120: =IF(E120="Neraca",K120,0) -> 0 | P120: =IF(E120="Neraca",L120,0) -> 0
B121: =IF(COA!B57="","",COA!B57) -> 5510 | F121: {=IFERROR(INDEX(SaldoNormal,MATCH(D121,Type,)),"")} | M121: =IF(E121="Laba Rugi",K121,0) -> 0 | N121: =IF(E121="Laba Rugi",L121,0) -> 0 | O121: =IF(E121="Neraca",K121,0) -> 0 | P121: =IF(E121="Neraca",L121,0) -> 0
B122: =IF(COA!B58="","",COA!B58) -> 5520 | M122: =IF(E122="Laba Rugi",K122,0) -> 0 | N122: =IF(E122="Laba Rugi",L122,0) -> 0 | O122: =IF(E122="Neraca",K122,0) -> 0 | P122: =IF(E122="Neraca",L122,0) -> 0
B123: =IF(COA!B59="","",COA!B59) -> 5530 | M123: =IF(E123="Laba Rugi",K123,0) -> 0 | N123: =IF(E123="Laba Rugi",L123,0) -> 0 | O123: =IF(E123="Neraca",K123,0) -> 0 | P123: =IF(E123="Neraca",L123,0) -> 0
B124: =IF(COA!B60="","",COA!B60) -> 5540 | M124: =IF(E124="Laba Rugi",K124,0) -> 0 | N124: =IF(E124="Laba Rugi",L124,0) -> 0 | O124: =IF(E124="Neraca",K124,0) -> 0 | P124: =IF(E124="Neraca",L124,0) -> 0
B125: TOTAL | G125: =SUM(G8:G124) -> 0 | H125: =SUM(H8:H124) -> 0 | I125: =SUM(I8:I124) -> 128654329 | J125: =SUM(J8:J124) -> 216812242 | K125: =SUM(K8:K124) -> -13357594 | L125: =SUM(L8:L124) -> -22753162 | M125: =SUM(M8:M124) -> #N/A | N125: =SUM(N8:N124) -> #N/A | ... P125: =SUM(P8:P124) -> #N/A
L126: =IF(N126>0,"LABA","RUGI") -> #N/A | N126: =N125-M125 -> #N/A | P126: =O125-P125 -> #N/A
N127: =IF(O127=P127,"BALANCE","TIDAK BALANCE") -> #N/A | O127: =O125+O126 -> #N/A | P127: =P125+P126 -> #N/A

Sheet LR
B2: =NRL!B2 -> PT. TERANG GARAM SOLUSINDO | O2: PT. TERANG GARAM SOLUSINDO
B3: LABA (RUGI) OFFICE & WS | O3: LABA (RUGI) OFFICE & WS
B4: =NRL!B4 -> PERIODE | O4: PER MEI 2026 (28 april - 27 mei 2026)
O5: 40.00.00.00 | P5: PENDAPATAN
B6: KODE | C6: KETERANGAN | D6: SALDO | G6: KB DEBET | H6: KB KREDIT | I6: SN | L6: KETERANGAN | M6: SALDO | O6: 41.00.00.00 | P6: pendapatan jasa | Q6: 284789665 | R6: 0.9575
J7: PENDAPATAN | K7: =D9 -> -124642329 | O7: 43.00.00.00 | P7: pendapatan ongkir | Q7: 12643912 | R7: 0.0425
B8: PENDAPATAN | J8: PENDAPATAN | K8: =D10 -> 0 | L8: Total Pendapatan | M8: =D13 -> -126305329 | O8: OMZET | Q8: 297433577 | R8: 1
B9: =NRL!B24 -> 4110 | C9: {=IFERROR(INDEX(Nama_Akun,MATCH(B9,KODEAKUN,0)),"")} -> Pendapatan jasa | D9: =IF(I9="Kredit",H9-G9,G9-H9) -> -124642329 | G9: {=INDEX(NRCLDB,MATCH(B9,NRCLKODE,0))} -> 0 | H9: {=INDEX(NRCLKR,MATCH(B9,NRCLKODE,0))} -> -124642329 | I9: {=INDEX(NRCLSN,MATCH(B9,NRCLKODE,0))} -> Kredit | J9: PENDAPATAN | K9: =D11 -> -1663000 | L9: Total Pembelian | M9: =D19 -> -150000
B10: =NRL!B29 -> 4160 | C10: {=IFERROR(INDEX(Nama_Akun,MATCH(B10,KODEAKUN,0)),"")} -> pendapatan ongkir | D10: =IF(I10="Kredit",H10-G10,G10-H10) -> 0 | G10: {=INDEX(NRCLDB,MATCH(B10,NRCLKODE,0))} -> 0 | H10: {=INDEX(NRCLKR,MATCH(B10,NRCLKODE,0))} -> 0 | I10: {=INDEX(NRCLSN,MATCH(B10,NRCLKODE,0))} -> Kredit | J10: PENDAPATAN | K10: =D12 -> 0 | L10: Laba Kotor | M10: =M8-M9 -> -126155329 | P10: Retur & Refund | Q10: 3711413
B11: =NRL!B27 -> 4140 | C11: {=IFERROR(INDEX(Nama_Akun,MATCH(B11,KODEAKUN,0)),"")} -> pendapatan jasa eiger | D11: =IF(I11="Kredit",H11-G11,G11-H11) -> -1663000 | G11: {=INDEX(NRCLDB,MATCH(B11,NRCLKODE,0))} -> 0 | H11: {=INDEX(NRCLKR,MATCH(B11,NRCLKODE,0))} -> -1663000 | I11: {=INDEX(NRCLSN,MATCH(B11,NRCLKODE,0))} -> Kredit | J11: PENDAPATAN | K11: =#REF! -> #REF! | L11: Total Biaya Operasional | M11: =D87 -> 0 | P11: OMZET | Q11: 293722164
C12: {=IFERROR(INDEX(Nama_Akun,MATCH(B12,KODEAKUN,0)),"")} | G12: {=INDEX(NRCLDB,MATCH(B12,NRCLKODE,0))} -> #N/A | H12: {=INDEX(NRCLKR,MATCH(B12,NRCLKODE,0))} -> #N/A | I12: {=INDEX(NRCLSN,MATCH(B12,NRCLKODE,0))} -> #N/A | J12: PENDAPATAN | K12: =#REF! -> #REF! | L12: Laba Bersih | M12: =M10-M11 -> -126155329 | O12: 50.00.00.00 | P12: BEBAN POKOK PENJUALAN
B13: TOTAL PENDAPATAN | D13: =SUM(D9:D12) -> -126305329 | G13: {=INDEX(NRCLDB,MATCH(#REF!,NRCLKODE,0))} -> #REF! | H13: {=INDEX(NRCLKR,MATCH(#REF!,NRCLKODE,0))} -> #REF! | I13: {=INDEX(NRCLSN,MATCH(#REF!,NRCLKODE,0))} -> #REF! | K13: =#REF! -> #REF! | O13: 50.01.00.00 | P13: HPP aksesoris | Q13: 15000 | R13: 0.0003
G14: {=INDEX(NRCLDB,MATCH(#REF!,NRCLKODE,0))} -> #REF! | H14: {=INDEX(NRCLKR,MATCH(#REF!,NRCLKODE,0))} -> #REF! | I14: {=INDEX(NRCLSN,MATCH(#REF!,NRCLKODE,0))} -> #REF! | K14: =D13 -> -126305329 | O14: 50.02.00.00 | P14: HPP General | Q14: 1986408 | R14: 0.0426
B15: RETUR & KOMPENSASI | K15: =D14 -> 0 | O15: 50.03.00.00 | P15: HPP Reguler | Q15: 11000720 | R15: 0.2361
B16: =NRL!B30 -> 4170 | C16: {=IFERROR(INDEX(Nama_Akun,MATCH(B16,KODEAKUN,0)),"")} -> Retur & Refund | D16: =IF(I19="Kredit",H19-G19,G19-H19) -> -150000 | K16: =D15 -> 0 | O16: 50.04.00.00 | P16: HPP Ripen | Q16: - | R16: 0
B17: =NRL!B84 -> 6120 | C17: {=IFERROR(INDEX(Nama_Akun,MATCH(B17,KODEAKUN,0)),"")} -> kompensasi | D17: =IF(I20="Kredit",H20-G20,G20-H20) -> 0 | J17: Pembelian | K17: =D16 -> -150000 | O17: 50.05.00.00 | P17: HPP sole | Q17: 20734169 | R17: 0.4449
J18: Pembelian | K18: =D17 -> 0 | O18: 50.06.00.00 | P18: HPP Upper | Q18: 2186953 | R18: 0.0469
B19: TOTAL RETUR & KOMPENSASI | D19: =SUM(D16:D18) -> -150000 | G19: {=INDEX(NRCLDB,MATCH(B16,NRCLKODE,0))} -> -150000 | H19: {=INDEX(NRCLKR,MATCH(B16,NRCLKODE,0))} -> 0 | I19: {=INDEX(NRCLSN,MATCH(B16,NRCLKODE,0))} -> Debet | J19: Pembelian | K19: =#REF! -> #REF! | O19: 50.07.00.01 | P19: HPP vibram | Q19: - | R19: 0
G20: {=INDEX(NRCLDB,MATCH(B17,NRCLKODE,0))} -> 0 | H20: {=INDEX(NRCLKR,MATCH(B17,NRCLKODE,0))} -> 0 | I20: {=INDEX(NRCLSN,MATCH(B17,NRCLKODE,0))} -> 0 | K20: =D18 -> 0 | O20: 51.10.00.00 | P20: Gaji + bonus Produksi | Q20: 10680000 | R20: 0.2292
B21: BEBAN POKOK PENJUALAN | G21: {=INDEX(NRCLDB,MATCH(#REF!,NRCLKODE,0))} -> #REF! | H21: {=INDEX(NRCLKR,MATCH(#REF!,NRCLKODE,0))} -> #REF! | I21: {=INDEX(NRCLSN,MATCH(#REF!,NRCLKODE,0))} -> #REF! | K21: =D19 -> -150000 | O21: HPP | Q21: 46603250 | R21: 0.1567
B22: =COA!B28 -> 5010 | C22: {=IFERROR(INDEX(Nama_Akun,MATCH(B22,KODEAKUN,0)),"")} -> Hpp sole | D22: =IF(I25="Kredit",H25-G25,G25-H25) -> 0 | K22: =D33 -> -126155329 | O22: PENDAPATAN BRUTO | Q22: 247118914
B23: =COA!B29 -> 5020 | C23: {=IFERROR(INDEX(Nama_Akun,MATCH(B23,KODEAKUN,0)),"")} -> Hpp upper | D23: =IF(I26="Kredit",H26-G26,G26-H26) -> 0 | K23: =D34 -> 0 | O23: 51.00.00.00 | P23: BEBAN GAJI, THR & BONUS
B24: =COA!B30 -> 5030 | C24: {=IFERROR(INDEX(Nama_Akun,MATCH(B24,KODEAKUN,0)),"")} -> Hpp reguler | D24: =IF(I27="Kredit",H27-G27,G27-H27) -> #REF! | K24: =#REF! -> #REF! | O24: 51.01.00.00 | P24: Gaji karyawan | Q24: 15100000 | R24: 0.1939
B25: =COA!B31 -> 5040 | C25: {=IFERROR(INDEX(Nama_Akun,MATCH(B25,KODEAKUN,0)),"")} -> Hpp Vibram | D25: =IF(I28="Kredit",H28-G28,G28-H28) -> #REF! | J25: BEBAN | K25: =#REF! -> #REF! | O25: 51.03.00.00 | P25: Gaji Workshop | Q25: 10680000 | R25: 0.1372
B26: =COA!B32 -> 5050 | C26: {=IFERROR(INDEX(Nama_Akun,MATCH(B26,KODEAKUN,0)),"")} -> Hpp repaint | D26: =IF(I29="Kredit",H29-G29,G29-H29) -> #REF! | J26: BEBAN | K26: =#REF! -> #REF! | O26: 51.04.00.00 | P26: Gaji CS | Q26: 23677000 | R26: 0.3041
B27: =COA!B33 -> 5060 | C27: {=IFERROR(INDEX(Nama_Akun,MATCH(B27,KODEAKUN,0)),"")} -> Hpp general | D27: =IF(I30="Kredit",H30-G30,G30-H30) -> #REF! | G27: {=INDEX(NRCLDB,MATCH(#REF!,NRCLKODE,0))} -> #REF! | H27: {=INDEX(NRCLKR,MATCH(#REF!,NRCLKODE,0))} -> #REF! | I27: {=INDEX(NRCLSN,MATCH(#REF!,NRCLKODE,0))} -> #REF! | J27: BEBAN | K27: =#REF! -> #REF! | O27: 51.05.00.00 | P27: Gaji Finance | Q27: 3320000 | R27: 0.0426
B28: =COA!B34 -> 5070 | C28: {=IFERROR(INDEX(Nama_Akun,MATCH(B28,KODEAKUN,0)),"")} -> Hpp Aksesoris | D28: =IF(I31="Kredit",H31-G31,G31-H31) -> #REF! | G28: {=INDEX(NRCLDB,MATCH(#REF!,NRCLKODE,0))} -> #REF! | H28: {=INDEX(NRCLKR,MATCH(#REF!,NRCLKODE,0))} -> #REF! | I28: {=INDEX(NRCLSN,MATCH(#REF!,NRCLKODE,0))} -> #REF! | J28: BEBAN | K28: =#REF! -> #REF! | O28: 51.06.00.00 | P28: Gaji CC | Q28: 7811167 | R28: 0.1003
B29: =COA!B42 -> 5108 | C29: {=IFERROR(INDEX(Nama_Akun,MATCH(B29,KODEAKUN,0)),"")} -> Beban gaji tukang | D29: =IF(I32="Kredit",H32-G32,G32-H32) -> #REF! | G29: {=INDEX(NRCLDB,MATCH(#REF!,NRCLKODE,0))} -> #REF! | H29: {=INDEX(NRCLKR,MATCH(#REF!,NRCLKODE,0))} -> #REF! | I29: {=INDEX(NRCLSN,MATCH(#REF!,NRCLKODE,0))} -> #REF! | J29: BEBAN | K29: =#REF! -> #REF! | O29: 51.07.00.00 | P29: Gaji Data analisis | Q29: 6890000 | R29: 0.0885
B30: =COA!B44 -> 5120 | C30: {=IFERROR(INDEX(Nama_Akun,MATCH(B30,KODEAKUN,0)),"")} -> Bonus tukang | D30: =IF(I33="Kredit",H33-G33,G33-H33) -> #REF! | G30: {=INDEX(NRCLDB,MATCH(#REF!,NRCLKODE,0))} -> #REF! | H30: {=INDEX(NRCLKR,MATCH(#REF!,NRCLKODE,0))} -> #REF! | I30: {=INDEX(NRCLSN,MATCH(#REF!,NRCLKODE,0))} -> #REF! | J30: BEBAN | K30: =#REF! -> #REF! | O30: 51.08.00.00 | P30: Gaji Gudang | Q30: 8538000 | R30: 0.1096
G31: {=INDEX(NRCLDB,MATCH(#REF!,NRCLKODE,0))} -> #REF! | H31: {=INDEX(NRCLKR,MATCH(#REF!,NRCLKODE,0))} -> #REF! | I31: {=INDEX(NRCLSN,MATCH(#REF!,NRCLKODE,0))} -> #REF! | J31: BEBAN | K31: =#REF! -> #REF! | O31: 51.13.00.00 | P31: Bonus CS | Q31: 1850000 | R31: 0.0238
B32: TOTAL HPP | D32: =SUM(D22:D24) -> #REF! | G32: {=INDEX(NRCLDB,MATCH(#REF!,NRCLKODE,0))} -> #REF! | H32: {=INDEX(NRCLKR,MATCH(#REF!,NRCLKODE,0))} -> #REF! | I32: {=INDEX(NRCLSN,MATCH(#REF!,NRCLKODE,0))} -> #REF! | J32: BEBAN LAINNYA | K32: =#REF! -> #REF! | O32: 52.00.00.00 | P32: BEBAN INTERNAL
B33: LABA KOTOR | D33: =SUM(D13-D19) -> -126155329 | G33: {=INDEX(NRCLDB,MATCH(#REF!,NRCLKODE,0))} -> #REF! | H33: {=INDEX(NRCLKR,MATCH(#REF!,NRCLKODE,0))} -> #REF! | I33: {=INDEX(NRCLSN,MATCH(#REF!,NRCLKODE,0))} -> #REF! | K33: =#REF! -> #REF! | O33: 52.01.00.00 | P33: Operasional Reguler
G34: {=INDEX(NRCLDB,MATCH(#REF!,NRCLKODE,0))} -> #REF! | H34: {=INDEX(NRCLKR,MATCH(#REF!,NRCLKODE,0))} -> #REF! | I34: {=INDEX(NRCLSN,MATCH(#REF!,NRCLKODE,0))} -> #REF! | K34: =D87 -> 0 | O34: 52.02.00.00 | P34: Konsumsi lembur & Meeting | Q34: 678000 | R34: 1
C35: BEBAN GAJI, THR & BONUS | K35: =#REF! -> #REF! | O35: 53.00.00.00 | P35: BEBAN EKSPEDISI & PACKAGING
B36: =COA!B36 -> 5102 | C36: {=IFERROR(INDEX(Nama_Akun,MATCH(B36,KODEAKUN,0)),"")} -> Beban Gaji Workshop | E36: 0.1939 | K36: =D95 -> -126155329 | O36: 53.10.00.00 | P36: Ekspedisi & Ongkir | Q36: 447210 | R36: 0.1516
B37: =COA!B37 -> 5103 | C37: {=IFERROR(INDEX(Nama_Akun,MATCH(B37,KODEAKUN,0)),"")} -> Beban Gaji CS | E37: 0.1372 | K37: =#REF! -> #REF! | O37: 53.20.00.00 | P37: Packaging | Q37: 2322845 | R37: 0.7875
B38: =COA!B38 -> 5104 | C38: {=IFERROR(INDEX(Nama_Akun,MATCH(B38,KODEAKUN,0)),"")} -> Beban Gaji Finance | E38: 0.3041 | K38: =D50 -> 0 | O38: 54.00.00.00 | P38: BEBAN SOFTWARE & PERANGKAT LUNAK
B39: =COA!B39 -> 5105 | C39: {=IFERROR(INDEX(Nama_Akun,MATCH(B39,KODEAKUN,0)),"")} -> Beban Gaji CC | E39: 0.0426 | O39: 54.01.00.00 | P39: pancake | Q39: 150000 | R39: 0.0107
B40: =COA!B40 -> 5106 | C40: {=IFERROR(INDEX(Nama_Akun,MATCH(B40,KODEAKUN,0)),"")} -> Beban Gaji Data analisis | E40: 0.1003 | O40: 54.02.00.00 | P40: Sleekflow | Q40: 11735000 | R40: 0.8379
B41: =COA!B40 -> 5106 | C41: {=IFERROR(INDEX(Nama_Akun,MATCH(B41,KODEAKUN,0)),"")} -> Beban Gaji Data analisis | E41: 0.0885 | O41: 54.03.00.00 | P41: anty gravity | Q41: 343000 | R41: 0.0245
B42: =COA!B41 -> 5107 | C42: {=IFERROR(INDEX(Nama_Akun,MATCH(B42,KODEAKUN,0)),"")} -> Beban Gaji Gudang | E42: 0.1096 | O42: 54.04.00.00 | P42: server domainesia | Q42: 1778001 | R42: 0.1269
B43: =COA!B43 -> 5110 | C43: {=IFERROR(INDEX(Nama_Akun,MATCH(B43,KODEAKUN,0)),"")} -> Bonus CS | E43: 0.0238 | O43: 54.00.00.00 | P43: BEBAN MARKETING
B44: =COA!B45 -> 5130 | C44: {=IFERROR(INDEX(Nama_Akun,MATCH(B44,KODEAKUN,0)),"")} -> Bonus kehadiran
C45: BEBAN INTERNAL | O45: 54.10.00.00 | P45: ADS | Q45: 55000000 | R45: 0.8592
B46: 52.01.00.00 | C46: {=IFERROR(INDEX(Nama_Akun,MATCH(B46,KODEAKUN,0)),"")} | O46: 54.20.00.00 | P46: WA API | Q46: 10516498 | R46: 0.1643
B47: =NRL!B51 -> 5200 | C47: {=IFERROR(INDEX(Nama_Akun,MATCH(B47,KODEAKUN,0)),"")} -> Konsumsi lembur & Meeting | E47: 1 | O47: 55.00.00.00 | P47: BEBAN UTILITAS
C48: BEBAN EKSPEDISI & PACKAGING | O48: 55.01.00.00 | P48: Listrik Office | Q48: 503250 | R48: 0.1367
B49: =NRL!B49 -> 5300 | C49: {=IFERROR(INDEX(Nama_Akun,MATCH(B49,KODEAKUN,0)),"")} -> Biaya packaging | E49: 0.1516 | O49: 55.02.00.00 | P49: Listrik Workshop | Q49: 1710000 | R49: 0.4646
B50: =NRL!B50 -> 5310 | C50: {=IFERROR(INDEX(Nama_Akun,MATCH(B50,KODEAKUN,0)),"")} -> Biaya ekspedisi & ongkir | E50: 0.7875 | O50: 55.03.00.00 | P50: Listrik sortir | Q50: 504000 | R50: 0.1369
C51: BEBAN SOFTWARE & PERANGKAT LUNAK | O51: 55.04.00.00 | P51: PDAM Office | R51: 0
B52: =NRL!B52 -> 5400 | C52: {=IFERROR(INDEX(Nama_Akun,MATCH(B52,KODEAKUN,0)),"")} -> pancake | E52: 0.0107 | O52: 55.05.00.00 | P52: PDAM Workshop | R52: 0
B53: =NRL!B53 -> 5410 | C53: {=IFERROR(INDEX(Nama_Akun,MATCH(B53,KODEAKUN,0)),"")} -> Sleekflow | E53: 0.8379 | O53: 55.06.00.00 | P53: PDAM sortir | R53: 0
B54: =NRL!B54 -> 5420 | C54: {=IFERROR(INDEX(Nama_Akun,MATCH(B54,KODEAKUN,0)),"")} -> anty gravity | E54: 0.0245 | O54: 55.07.00.00 | P54: Wifi Office | Q54: 333000 | R54: 0.0905
B55: =NRL!B55 -> 5430 | C55: {=IFERROR(INDEX(Nama_Akun,MATCH(B55,KODEAKUN,0)),"")} -> server domainesia | E55: 0.1269 | O55: 55.08.00.00 | P55: Wifi Sortir | Q55: 389500 | R55: 0.1058
C56: BEBAN MARKETING | O56: 55.09.00.00 | P56: Wifi Workshop | Q56: 445000 | R56: 0.1209
B57: =NRL!B56 -> 5440 | C57: {=IFERROR(INDEX(Nama_Akun,MATCH(B57,KODEAKUN,0)),"")} -> ADS | E57: 0.8592 | O57: 56.00.00.00 | P57: BEBAN SEWA
B58: =NRL!B57 -> 5450 | C58: {=IFERROR(INDEX(Nama_Akun,MATCH(B58,KODEAKUN,0)),"")} -> WA API | E58: 0.1643 | O58: 56.01.00.00 | P58: Sewa Tempat Office
B59: =NRL!B58 -> 5460 | C59: {=IFERROR(INDEX(Nama_Akun,MATCH(B59,KODEAKUN,0)),"")} -> voucher marketing
C60: BEBAN UTILITAS | O60: 56.02.00.00 | P60: Sewa Tempat Workshop | Q60: 2750000 | R60: 1
B61: =NRL!B59 -> 5500 | C61: {=IFERROR(INDEX(Nama_Akun,MATCH(B61,KODEAKUN,0)),"")} -> Beban Listrik Office | E61: 0.1367 | O61: 60.00.00.00 | P61: BEBAN OPERASIONAL
B62: =NRL!B60 -> 5510 | C62: {=IFERROR(INDEX(Nama_Akun,MATCH(B62,KODEAKUN,0)),"")} -> Beban Listrik Workshop | E62: 0.4646 | O62: 60.01.00.00 | P62: Transport/ Bensin/ Parkir | Q62: 265000 | R62: 0.0429
B63: =NRL!B61 -> 5520 | C63: {=IFERROR(INDEX(Nama_Akun,MATCH(B63,KODEAKUN,0)),"")} -> Beban Listrik sortir | E63: 0.1369 | O63: 60.03.00.00 | P63: Iuran Sampah & Keamanan | Q63: 70000 | R63: 0.0113
B64: =NRL!B62 -> 5530 | C64: {=IFERROR(INDEX(Nama_Akun,MATCH(B64,KODEAKUN,0)),"")} -> Beban PDAM Office | E64: 0 | O64: 60.04.00.00 | P64: Iuran RT, RW | Q64: 250000 | R64: 0.0404
B65: =NRL!B63 -> 5540 | C65: {=IFERROR(INDEX(Nama_Akun,MATCH(B65,KODEAKUN,0)),"")} -> Beban PDAM Workshop | E65: 0 | O65: 60.05.00.00 | P65: ATK | Q65: 598000 | R65: 0.0967
B66: =NRL!B64 -> 5550 | C66: {=IFERROR(INDEX(Nama_Akun,MATCH(B66,KODEAKUN,0)),"")} -> Beban PDAM sortir | E66: 0 | O66: 60.08.00.00 | P66: Iklan Loker | Q66: 180000 | R66: 0.0291
B67: =NRL!B65 -> 5560 | C67: {=IFERROR(INDEX(Nama_Akun,MATCH(B67,KODEAKUN,0)),"")} -> Beban Wifi Office | E67: 0.0905 | O67: 60.09.00.00 | P67: iuran WS | Q67: 200000 | R67: 0.0323
B68: =NRL!B66 -> 5570 | C68: {=IFERROR(INDEX(Nama_Akun,MATCH(B68,KODEAKUN,0)),"")} -> Beban Wifi Sortir | E68: 0.1058 | O68: 60.12.00.00 | P68: Konsultan | Q68: 1000000 | R68: 0.1617
B69: =NRL!B67 -> 5580 | C69: {=IFERROR(INDEX(Nama_Akun,MATCH(B69,KODEAKUN,0)),"")} -> Beban Wifi Workshop | E69: 0.1209 | O69: 60.13.00.00 | P69: CSR | Q69: 2000000 | R69: 0.3235
C70: BEBAN SEWA | O70: 60.15.00.00 | P70: Beban dapur | Q70: 282000 | R70: 0.0456
B71: =NRL!B68 -> 5600 | C71: {=IFERROR(INDEX(Nama_Akun,MATCH(B71,KODEAKUN,0)),"")} -> Sewa Tempat Office | O71: 60.17.00.00 | P71: pemeliharaan kebersihan | Q71: 325700 | R71: 0.0527
B72: =NRL!B69 -> 5610 | C72: {=IFERROR(INDEX(Nama_Akun,MATCH(B72,KODEAKUN,0)),"")} -> Sewa Tempat sortir | E72: 1 | O72: 60.18.00.00 | P72: beban lainnya | Q72: 132000 | R72: 0.0213
B73: =NRL!B71 -> 5630 | C73: {=IFERROR(INDEX(Nama_Akun,MATCH(B73,KODEAKUN,0)),"")} -> Sewa Tempat Workshop
C74: BEBAN OPERASIONAL | O74: 60.19.00.01 | P74: coway oma | Q74: 280000 | R74: 0.0453
B75: =NRL!B72 -> 6000 | C75: {=IFERROR(INDEX(Nama_Akun,MATCH(B75,KODEAKUN,0)),"")} -> Beban Transport/ Bensin/ Parkir | E75: 0.0429 | O75: 60.20.00.00 | P75: kompensasi kehilangan sepatu (WS) | Q75: 400000 | R75: 0.0647
B76: =NRL!B73 -> 6010 | C76: {=IFERROR(INDEX(Nama_Akun,MATCH(B76,KODEAKUN,0)),"")} -> Beban Iuran Sampah & Keamanan | E76: 0.0113 | O76: 60.21.00.00 | P76: pemeliharaan perlengkapan | Q76: 200000 | R76: 0.0323
B77: =NRL!B74 -> 6020 | C77: {=IFERROR(INDEX(Nama_Akun,MATCH(B77,KODEAKUN,0)),"")} -> Beban Iuran RT, RW | E77: 0.0404 | O77: TOTAL BEBAN OPERASIONAL | Q77: 173654171 | R77: 0.5838
B78: =NRL!B75 -> 6030 | C78: {=IFERROR(INDEX(Nama_Akun,MATCH(B78,KODEAKUN,0)),"")} -> Beban ATK | E78: 0.0967 | O78: PENDAPATAN OPERASIONAL | Q78: 73464743 | R78: 0.247
B79: =NRL!B76 -> 6040 | C79: {=IFERROR(INDEX(Nama_Akun,MATCH(B79,KODEAKUN,0)),"")} -> Beban Iklan Loker | E79: 0.0291 | O79: 70.00.00.00 | P79: PENDAPATAN LAIN-LAIN
B80: =NRL!B77 -> 6050 | C80: {=IFERROR(INDEX(Nama_Akun,MATCH(B80,KODEAKUN,0)),"")} -> Beban iuran WS | E80: 0.0323 | O80: 71.00.00.00 | P80: Pendapatan Bunga Bank
B81: =NRL!B78 -> 6060 | C81: {=IFERROR(INDEX(Nama_Akun,MATCH(B81,KODEAKUN,0)),"")} -> Beban Konsultan | E81: 0.1617 | O81: 72.00.00.00 | P81: Pendapatan Lainya | Q81: 4597101 | R81: 1
B82: =NRL!B79 -> 6070 | C82: {=IFERROR(INDEX(Nama_Akun,MATCH(B82,KODEAKUN,0)),"")} -> Beban CSR | E82: 0.3235 | O82: 80.00.00.00 | P82: BEBAN LAIN-LAIN
B83: =NRL!B80 -> 6080 | C83: {=IFERROR(INDEX(Nama_Akun,MATCH(B83,KODEAKUN,0)),"")} -> Beban dapur | E83: 0.0456 | O83: 81.00.00.00 | P83: Biaya Admin Bank | Q83: 69500 | R83: 0.0323
B84: =NRL!B81 -> 6090 | C84: {=IFERROR(INDEX(Nama_Akun,MATCH(B84,KODEAKUN,0)),"")} -> Beban pemeliharaan kebersihan | E84: 0.0527 | O84: 82.00.00.00 | P84: Pajak | Q84: 1799614 | R84: 0.8366
B85: =NRL!B82 -> 6100 | C85: {=IFERROR(INDEX(Nama_Akun,MATCH(B85,KODEAKUN,0)),"")} -> beban lainnya | E85: 0.0213 | O85: LABA (RUGI) SETELAH PAJAK PENGHASILAN | Q85: 76192730 | R85: 0.2562
B86: =NRL!B85 -> 6130 | C86: {=IFERROR(INDEX(Nama_Akun,MATCH(B86,KODEAKUN,0)),"")} -> pemeliharaan perlengkapan | E86: 0.0453
B87: TOTAL BIAYA OPERASIONAL | D87: =SUM(D35:D86) -> 0
B88: PENDAPATAN OPERASIONAL | E88: 0.247
C89: PENDAPATAN LAIN-LAIN
B90: =NRL!B86 -> 7000 | C90: {=IFERROR(INDEX(Nama_Akun,MATCH(B90,KODEAKUN,0)),"")} -> Pendapatan Bunga Bank
B91: =NRL!B28 -> 7010 | C91: {=IFERROR(INDEX(Nama_Akun,MATCH(B91,KODEAKUN,0)),"")} -> pendapatan lain-lain | E91: 1
C92: BEBAN LAIN-LAIN
B93: =NRL!B87 -> 8000 | C93: {=IFERROR(INDEX(Nama_Akun,MATCH(B93,KODEAKUN,0)),"")} -> Biaya Admin Bank | E93: 0.0323
B94: =NRL!B88 -> 8010 | C94: {=IFERROR(INDEX(Nama_Akun,MATCH(B94,KODEAKUN,0)),"")} -> Pajak | E94: 0.8366
B95: =IF(D95>0,"LABA BERSIH","RUGI BERSIH") -> RUGI BERSIH | D95: =D33-D87 -> -126155329

Sheet LPE
B2: =NRC!B2 -> PT. TERANG GARAM SOLUSINDO
B3: LAPORAN PERUBAHAN EKUITAS
B4: =NRC!B4 -> PERIODE
B6: Modal Awal | F6: =NRL!H18 -> 0
B7: Penurunan Modal | D7: =NRL!J18 -> 0
B8: =IF(F9>0,"Laba","Kerugian") -> #N/A | D8: =NRL!N126 -> #N/A
B9: =IF(F9>0,"Kenaikan Modal","Penurunan Modal") -> #N/A | F9: =SUM(D7:D8) -> #N/A
B10: Modal Akhir | F10: =SUM(F6:F9) -> #N/A

Sheet NRC
B2: =LR!B2 -> PT. TERANG GARAM SOLUSINDO
B3: NERACA
B4: =LR!B4 -> PERIODE
B6: KODE | C6: KETERANGAN | D6: SALDO | F6: KB DEBET | G6: KB KREDIT | H6: SN
B7: ASET | D7: =IFERROR(IF(H7="Debet",F7-G7,G7-F7),"") | F7: {=IFERROR(INDEX(NRCLDB2,MATCH(B7,NRCLKODE,0)),"")} | H7: {=IFERROR(INDEX(NRCLSN,MATCH(B7,NRCLKODE,0)),"")}
B8: =COA!B5 -> 1101 | C8: {=IFERROR(INDEX(Nama_Akun,MATCH(B8,KODEAKUN,0)),"")} -> Kas | D8: =IFERROR(IF(H8="Debet",F8-G8,G8-F8),"") -> 0 | F8: {=IFERROR(INDEX(NRCLDB2,MATCH(B8,NRCLKODE,0)),"")} -> 0 | G8: {=IFERROR(INDEX(NRCLKR2,MATCH(B8,NRCLKODE,0)),"")} -> 0 | H8: {=IFERROR(INDEX(NRCLSN,MATCH(B8,NRCLKODE,0)),"")} -> Debet | I8: KAS DAN BANK | J8: =D8 -> 0
B9: =COA!B6 -> 1102 | C9: {=IFERROR(INDEX(Nama_Akun,MATCH(B9,KODEAKUN,0)),"")} -> Kas Di Bank | D9: =IFERROR(IF(H9="Debet",F9-G9,G9-F9),"") -> 0 | F9: {=IFERROR(INDEX(NRCLDB2,MATCH(B9,NRCLKODE,0)),"")} -> 0 | G9: {=IFERROR(INDEX(NRCLKR2,MATCH(B9,NRCLKODE,0)),"")} -> 0 | H9: {=IFERROR(INDEX(NRCLSN,MATCH(B9,NRCLKODE,0)),"")} -> Debet | I9: KAS DAN BANK | J9: =D9 -> 0
B10: =COA!B7 -> 1103 | C10: {=IFERROR(INDEX(Nama_Akun,MATCH(B10,KODEAKUN,0)),"")} -> Petty Cash | D10: =IFERROR(IF(H10="Debet",F10-G10,G10-F10),"") -> 0 | F10: {=IFERROR(INDEX(NRCLDB2,MATCH(B10,NRCLKODE,0)),"")} -> 0 | G10: {=IFERROR(INDEX(NRCLKR2,MATCH(B10,NRCLKODE,0)),"")} -> 0 | H10: {=IFERROR(INDEX(NRCLSN,MATCH(B10,NRCLKODE,0)),"")} -> Debet | I10: KAS DAN BANK | J10: =D10 -> 0
B11: =COA!B8 -> 1104 | C11: {=IFERROR(INDEX(Nama_Akun,MATCH(B11,KODEAKUN,0)),"")} -> Piutang | D11: =IFERROR(IF(H11="Debet",F11-G11,G11-F11),"") -> 0 | F11: {=IFERROR(INDEX(NRCLDB2,MATCH(B11,NRCLKODE,0)),"")} -> 0 | G11: {=IFERROR(INDEX(NRCLKR2,MATCH(B11,NRCLKODE,0)),"")} -> 0 | H11: {=IFERROR(INDEX(NRCLSN,MATCH(B11,NRCLKODE,0)),"")} -> Debet | I11: AKUN PIUTANG | J11: =D11 -> 0
B12: =COA!B9 -> 1105 | C12: {=IFERROR(INDEX(Nama_Akun,MATCH(B12,KODEAKUN,0)),"")} -> Persediaan | D12: =IFERROR(IF(H12="Debet",F12-G12,G12-F12),"") -> 0 | F12: {=IFERROR(INDEX(NRCLDB2,MATCH(B12,NRCLKODE,0)),"")} -> 0 | G12: {=IFERROR(INDEX(NRCLKR2,MATCH(B12,NRCLKODE,0)),"")} -> 0 | H12: {=IFERROR(INDEX(NRCLSN,MATCH(B12,NRCLKODE,0)),"")} -> Debet | I12: PERSEDIAAN | J12: =D12 -> 0
B13: =COA!B10 -> 1106 | C13: {=IFERROR(INDEX(Nama_Akun,MATCH(B13,KODEAKUN,0)),"")} -> Perlengkapan | D13: =IFERROR(IF(H13="Debet",F13-G13,G13-F13),"") -> 0 | F13: {=IFERROR(INDEX(NRCLDB2,MATCH(B13,NRCLKODE,0)),"")} -> 0 | G13: {=IFERROR(INDEX(NRCLKR2,MATCH(B13,NRCLKODE,0)),"")} -> 0 | H13: {=IFERROR(INDEX(NRCLSN,MATCH(B13,NRCLKODE,0)),"")} -> Debet | I13: AKTIVA LANCAR LAINNYA | J13: =D13 -> 0
B14: =COA!B11 -> 1201 | C14: {=IFERROR(INDEX(Nama_Akun,MATCH(B14,KODEAKUN,0)),"")} -> Peralatan | D14: =IFERROR(IF(H14="Debet",F14-G14,G14-F14),"") -> -515685 | F14: {=IFERROR(INDEX(NRCLDB2,MATCH(B14,NRCLKODE,0)),"")} -> -515685 | G14: {=IFERROR(INDEX(NRCLKR2,MATCH(B14,NRCLKODE,0)),"")} -> 0 | H14: {=IFERROR(INDEX(NRCLSN,MATCH(B14,NRCLKODE,0)),"")} -> Debet | I14: AKTIVA TETAP | J14: =D14 -> -515685
B15: =COA!B12 -> 1202 | C15: {=IFERROR(INDEX(Nama_Akun,MATCH(B15,KODEAKUN,0)),"")} -> Akumulasi Penyusutan Peralatan | D15: =IFERROR(IF(H15="Debet",F15-G15,G15-F15),"") -> 0 | F15: {=IFERROR(INDEX(NRCLDB2,MATCH(B15,NRCLKODE,0)),"")} -> 0 | G15: {=IFERROR(INDEX(NRCLKR2,MATCH(B15,NRCLKODE,0)),"")} -> 0 | H15: {=IFERROR(INDEX(NRCLSN,MATCH(B15,NRCLKODE,0)),"")} -> Kredit | I15: DEPRESIASI DAN AMORTISASI | J15: =D15 -> 0
B16: TOTAL ASET | D16: =SUM(D8:D15) -> -515685 | F16: {=IFERROR(INDEX(NRCLDB2,MATCH(B16,NRCLKODE,0)),"")} | G16: {=IFERROR(INDEX(NRCLKR2,MATCH(B16,NRCLKODE,0)),"")} | H16: {=IFERROR(INDEX(NRCLSN,MATCH(B16,NRCLKODE,0)),"")}
F17: {=IFERROR(INDEX(NRCLDB2,MATCH(B17,NRCLKODE,0)),"")} | G17: {=IFERROR(INDEX(NRCLKR2,MATCH(B17,NRCLKODE,0)),"")} | H17: {=IFERROR(INDEX(NRCLSN,MATCH(B17,NRCLKODE,0)),"")} | J17: =D17 -> 0
B18: KEWAJIBAN | D18: =IFERROR(IF(H18="Debet",F18-G18,G18-F18),"") | F18: {=IFERROR(INDEX(NRCLDB2,MATCH(B18,NRCLKODE,0)),"")} | G18: {=IFERROR(INDEX(NRCLKR2,MATCH(B18,NRCLKODE,0)),"")} | H18: {=IFERROR(INDEX(NRCLSN,MATCH(B18,NRCLKODE,0)),"")} | J18: =D18
B19: =COA!B13 -> 2110 | C19: {=IFERROR(INDEX(Nama_Akun,MATCH(B19,KODEAKUN,0)),"")} -> Utang | D19: =IFERROR(IF(H19="Debet",F19-G19,G19-F19),"") -> 0 | F19: {=IFERROR(INDEX(NRCLDB2,MATCH(B19,NRCLKODE,0)),"")} -> 0 | G19: {=IFERROR(INDEX(NRCLKR2,MATCH(B19,NRCLKODE,0)),"")} -> 0 | H19: {=IFERROR(INDEX(NRCLSN,MATCH(B19,NRCLKODE,0)),"")} -> Kredit | I19: AKUN UTANG | J19: =D19 -> 0
B20: =COA!B14 -> 2120 | C20: {=IFERROR(INDEX(Nama_Akun,MATCH(B20,KODEAKUN,0)),"")} -> Utang Gaji | D20: =IFERROR(IF(H20="kredit",F20-G20,G20-F20),"") -> -105901167 | F20: {=IFERROR(INDEX(NRCLDB2,MATCH(B20,NRCLKODE,0)),"")} -> 0 | G20: {=IFERROR(INDEX(NRCLKR2,MATCH(B20,NRCLKODE,0)),"")} -> 105901167 | H20: {=IFERROR(INDEX(NRCLSN,MATCH(B20,NRCLKODE,0)),"")} -> Kredit | J20: =D20 -> -105901167
B21: TOTAL KEWAJIBAN | D21: =SUM(D19:D20) -> -105901167 | F21: {=IFERROR(INDEX(NRCLDB2,MATCH(B21,NRCLKODE,0)),"")} | G21: {=IFERROR(INDEX(NRCLKR2,MATCH(B22,NRCLKODE,0)),"")} | H21: {=IFERROR(INDEX(NRCLSN,MATCH(B22,NRCLKODE,0)),"")} | J21: =D21 -> -105901167
B23: MODAL | D23: =IFERROR(IF(H23="Debet",F23-G23,G23-F23),"") | F23: {=IFERROR(INDEX(NRCLDB2,MATCH(B23,NRCLKODE,0)),"")} | G23: {=IFERROR(INDEX(NRCLKR2,MATCH(B23,NRCLKODE,0)),"")} | H23: {=IFERROR(INDEX(NRCLSN,MATCH(B23,NRCLKODE,0)),"")} | J23: =D23
B24: =COA!B15 -> 2130 | C24: {=IFERROR(INDEX(Nama_Akun,MATCH(B24,KODEAKUN,0)),"")} -> utang pajak | D24: =LPE!F10 -> #N/A | F24: {=IFERROR(INDEX(NRCLDB2,MATCH(B24,NRCLKODE,0)),"")} -> 0 | G24: {=IFERROR(INDEX(NRCLKR2,MATCH(B24,NRCLKODE,0)),"")} -> 0 | H24: {=IFERROR(INDEX(NRCLSN,MATCH(B24,NRCLKODE,0)),"")} -> Kredit | I24: EKUITAS | J24: =D24 -> #N/A
B25: TOTAL MODAL | D25: =SUM(D24) -> #N/A | F25: {=IFERROR(INDEX(NRCLDB2,MATCH(B25,NRCLKODE,0)),"")} | G25: {=IFERROR(INDEX(NRCLKR2,MATCH(B25,NRCLKODE,0)),"")} | H25: {=IFERROR(INDEX(NRCLSN,MATCH(B25,NRCLKODE,0)),"")}
F26: {=IFERROR(INDEX(NRCLDB2,MATCH(B26,NRCLKODE,0)),"")} | G26: {=IFERROR(INDEX(NRCLKR2,MATCH(B26,NRCLKODE,0)),"")} | H26: {=IFERROR(INDEX(NRCLSN,MATCH(B26,NRCLKODE,0)),"")}
B27: TOTAL KEWAJIBAN DAN MODAL | D27: =D21+D25 -> #N/A | F27: {=IFERROR(INDEX(NRCLDB2,MATCH(B27,NRCLKODE,0)),"")} | G27: {=IFERROR(INDEX(NRCLKR2,MATCH(B27,NRCLKODE,0)),"")} | H27: {=IFERROR(INDEX(NRCLSN,MATCH(B27,NRCLKODE,0)),"")}

Sheet LAK
B2: =LPE!B2 -> PT. TERANG GARAM SOLUSINDO
B3: LAPORAN ARUS KAS
B4: =LPE!B4 -> PERIODE
B6: Aktivitas Operasional
C7: Penerimaan dari pelanggan | F7: =LR!D13+NRL!J11-NRL!I11 -> -126305329
C8: Aset lancar lainnya | F8: =-NRL!I13+NRL!J13 -> 0
C9: Pembayaraan ke pemasok | F9: =-(NRL!I12-AKUNUTANG) -> 0
C10: Liabilitas jangka pendek | F10: =KEWAJIBANLANCARLAINNYA -> 0
C11: Pendapatan lainnya | F11: =PENDAPATANLAINNYA -> 0
C12: Pengeluaran operasional | F12: =DEPRESIASIDANAMORTISASI+BEBAN+BEBANLAINNYA -> #REF!
B13: Kas bersih yang diperoleh dari Aktifitas Operasional | F13: =SUM(F7:F12) -> #REF!
B15: Aktivitas Investasi
C16: Perolehan/Penjualan aset | F16: =-NRL!I14+NRL!J14 -> 515685
C17: Aktivitas Investasi lainnya | F17: =AKTIVALAINNYA -> 0
B18: Kas bersih yang diperoleh dari Aktivitas Investasi | F18: =SUM(F16:F17) -> 515685
B20: Aktivitas Pendanaan
C21: Pembayaran/Penerimaan pinjaman | F21: =KEWAJIBANJANGKAPANJANG -> 0
C22: Ekuitas/Modal | F22: =NRL!J18 -> 0
B23: Kas bersih yang diperoleh dari Aktivitas Pendanaan | F23: =SUM(F21:F22) -> 0
B25: Kenaikan (penurunan) kas | F25: =F13+F18+F23 -> #REF!
B26: Saldo kas awal | F26: =NRL!G8 -> 0
B27: Saldo kas akhir | F27: =SUM(F25:F26) -> #REF!

Sheet JP
B2: =LAK!B2 -> PT. TERANG GARAM SOLUSINDO
B3: Jurnal Penutup
B4: =NRC!B4 -> PERIODE
E6: =IF(G4=H4,"BALANCE","CEK KEMBALI") -> BALANCE | F6: =SUM(F8:F25) -> #REF! | G6: =SUM(G8:G25) -> #REF!
B7: Tanggal | C7: Ref | D7: Kode Akun | E7: Nama Akun | F7: Debet | G7: Kredit | I7: DEBET IKHTISAR | J7: =F15+F17 -> #REF!
B8: 45657 | D8: 4101 | E8: {=IFERROR(INDEX(COA!$C$5:$C$59,MATCH(D8,COA!$B$5:$B$59,0)),"")} | F8: =LR!D9 -> -124642329 | I8: KREDIT IKHTISAR | J8: =G14 -> #REF!
D9: 4102 | E9: {=IFERROR(INDEX(COA!$C$5:$C$59,MATCH(D9,COA!$B$5:$B$59,0)),"")} | F9: =LR!D10 -> 0 | I9: TOTAL | J9: =J8-J7 -> #REF!
D10: 4103 | E10: {=IFERROR(INDEX(COA!$C$5:$C$59,MATCH(D10,COA!$B$5:$B$59,0)),"")} | F10: =LR!D11 -> -1663000
D11: 4104 | E11: {=IFERROR(INDEX(COA!$C$5:$C$59,MATCH(D11,COA!$B$5:$B$59,0)),"")} | F11: =LR!D12 -> 0
D12: 4105 | E12: {=IFERROR(INDEX(COA!$C$5:$C$59,MATCH(D12,COA!$B$5:$B$59,0)),"")} | F12: =LR!#REF! -> #REF!
D13: 4106 | E13: {=IFERROR(INDEX(COA!$C$5:$C$59,MATCH(D13,COA!$B$5:$B$59,0)),"")} | F13: =LR!#REF! -> #REF!
D14: 3102 | E14: {=IFERROR(INDEX(COA!$C$5:$C$59,MATCH(D14,COA!$B$5:$B$59,0)),"")} | G14: =SUM(F8:F13) -> #REF!
B15: 45657 | D15: 3102 | E15: {=IFERROR(INDEX(COA!$C$5:$C$59,MATCH(D15,COA!$B$5:$B$59,0)),"")} | F15: =SUM(G16) -> -150000
D16: 5101 | E16: {=IFERROR(INDEX(COA!$C$5:$C$59,MATCH(D16,COA!$B$5:$B$59,0)),"")} -> Beban Gaji shoepolice | G16: =LR!D16 -> -150000
B17: 45657 | D17: 3102 | E17: {=IFERROR(INDEX(COA!$C$5:$C$59,MATCH(D17,COA!$B$5:$B$59,0)),"")} | F17: =SUM(G18:G22) -> #REF!
D18: 6101 | E18: {=IFERROR(INDEX(COA!$C$5:$C$59,MATCH(D18,COA!$B$5:$B$59,0)),"")} | G18: =LR!#REF! -> #REF!
D19: 6102 | E19: {=IFERROR(INDEX(COA!$C$5:$C$59,MATCH(D19,COA!$B$5:$B$59,0)),"")} | G19: =LR!#REF! -> #REF!
D20: 6103 | E20: {=IFERROR(INDEX(COA!$C$5:$C$59,MATCH(D20,COA!$B$5:$B$59,0)),"")} | G20: =LR!#REF! -> #REF!
D21: 6107 | E21: {=IFERROR(INDEX(COA!$C$5:$C$59,MATCH(D21,COA!$B$5:$B$59,0)),"")} | G21: =LR!#REF! -> #REF!
D22: 6108 | E22: {=IFERROR(INDEX(COA!$C$5:$C$59,MATCH(D22,COA!$B$5:$B$59,0)),"")} | G22: =LR!#REF! -> #REF!
B23: 45657 | D23: 3102 | E23: {=IFERROR(INDEX(COA!$C$5:$C$59,MATCH(D23,COA!$B$5:$B$59,0)),"")} | F23: =J9 -> #REF!
D24: 3102 | E24: {=IFERROR(INDEX(COA!$C$5:$C$59,MATCH(D24,COA!$B$5:$B$59,0)),"")} | G24: =F23 -> #REF!
E25: {=IFERROR(INDEX(COA!$C$5:$C$59,MATCH(D25,COA!$B$5:$B$59,0)),"")}

Sheet NRC STLH PENUTUPAN
B2: =JP!B2 -> PT. TERANG GARAM SOLUSINDO
B3: Neraca Saldo Setelah Penutup
B4: =JP!B4 -> PERIODE
C6: =IF(G4=H4,"BALANCE","CEK KEMBALI") -> BALANCE | D6: =SUM(D8:D24) -> -515685 | E6: =SUM(E8:E24) -> #N/A
B7: Kode Akun | C7: Nama Akun | D7: Debet | E7: Kredit
B8: 1101 | C8: {=IFERROR(INDEX(COA!$C$5:$C$59,MATCH(B8,COA!$B$5:$B$59,0)),"")} -> Kas | D8: =NRC!D8 -> 0
B9: 1102 | C9: {=IFERROR(INDEX(COA!$C$5:$C$59,MATCH(B9,COA!$B$5:$B$59,0)),"")} -> Kas Di Bank | D9: =NRC!D9 -> 0
B10: 1103 | C10: {=IFERROR(INDEX(COA!$C$5:$C$59,MATCH(B10,COA!$B$5:$B$59,0)),"")} -> Petty Cash | D10: =NRC!D10 -> 0
B11: 1104 | C11: {=IFERROR(INDEX(COA!$C$5:$C$59,MATCH(B11,COA!$B$5:$B$59,0)),"")} -> Piutang | D11: =NRC!D11 -> 0
B12: 1105 | C12: {=IFERROR(INDEX(COA!$C$5:$C$59,MATCH(B12,COA!$B$5:$B$59,0)),"")} -> Persediaan | D12: =NRC!D12 -> 0
B13: 1106 | C13: {=IFERROR(INDEX(COA!$C$5:$C$59,MATCH(B13,COA!$B$5:$B$59,0)),"")} -> Perlengkapan | D13: =NRC!D13 -> 0
B14: 1201 | C14: {=IFERROR(INDEX(COA!$C$5:$C$59,MATCH(B14,COA!$B$5:$B$59,0)),"")} -> Peralatan | D14: =NRC!D14 -> -515685
B15: 2101 | C15: {=IFERROR(INDEX(COA!$C$5:$C$59,MATCH(B15,COA!$B$5:$B$59,0)),"")} | E15: =NRC!D19 -> 0
B16: 2102 | C16: {=IFERROR(INDEX(COA!$C$5:$C$59,MATCH(B16,COA!$B$5:$B$59,0)),"")} | E16: =NRC!D20 -> -105901167
B17: 3101 | C17: {=IFERROR(INDEX(COA!$C$5:$C$59,MATCH(B17,COA!$B$5:$B$59,0)),"")} | E17: =NRC!D24 -> #N/A
C18: {=IFERROR(INDEX(COA!$C$5:$C$59,MATCH(B18,COA!$B$5:$B$59,0)),"")}
C19: {=IFERROR(INDEX(COA!$C$5:$C$59,MATCH(B19,COA!$B$5:$B$59,0)),"")}
C20: {=IFERROR(INDEX(COA!$C$5:$C$59,MATCH(B20,COA!$B$5:$B$59,0)),"")}
C21: {=IFERROR(INDEX(COA!$C$5:$C$59,MATCH(B21,COA!$B$5:$B$59,0)),"")}
C22: {=IFERROR(INDEX(COA!$C$5:$C$59,MATCH(B22,COA!$B$5:$B$59,0)),"")}
C23: {=IFERROR(INDEX(COA!$C$5:$C$59,MATCH(B23,COA!$B$5:$B$59,0)),"")}
C24: {=IFERROR(INDEX(COA!$C$5:$C$59,MATCH(B24,COA!$B$5:$B$59,0)),"")}
C25: {=IFERROR(INDEX(COA!$C$5:$C$59,MATCH(B25,COA!$B$5:$B$59,0)),"")}
C26: {=IFERROR(INDEX(COA!$C$5:$C$59,MATCH(B26,COA!$B$5:$B$59,0)),"")}
C27: {=IFERROR(INDEX(COA!$C$5:$C$59,MATCH(B27,COA!$B$5:$B$59,0)),"")}
C28: {=IFERROR(INDEX(COA!$C$5:$C$59,MATCH(B28,COA!$B$5:$B$59,0)),"")}
C29: {=IFERROR(INDEX(COA!$C$5:$C$59,MATCH(B29,COA!$B$5:$B$59,0)),"")}
... C31: {=IFERROR(INDEX(COA!$C$5:$C$59,MATCH(B31,COA!$B$5:$B$59,0)),"")}
